Workbook

Sheet Cover
B2: PORTFOLIO MANAGEMENT GROUP PROJECT
B3: Portfolio Construction, Performance Analysis and Investor Recommendations
C4: TEAM NUMBER 10
B6: Allocated Sector / Benchmark | C6: Power sector - benchmark identity to be confirmed (see Data Sources & Assumptions)
B8: Analysis Period | C8: Full 5 years of daily trading data (20-Sep-2021 to 16-Sep-2026, 1,238 trading days). ALL calculations (portfolios, correlation, covariance, Markowitz, benchmark, performance ratios) use DAILY returns (1,237 usable observations), annualised on a 252-trading-day basis. Superseded monthly sheets are kept for audit history only.
B10: Companies Selected (10) | C10: Adani Energy Solutions, Adani Green, Adani Power, CESC, JSW Energy, NHPC, NTPC, Power Grid, Tata Power, Torrent Power
B12: Nme | C12: Prajjwal Singh (153)
B14: Faculty | C14: Prof Pankajj Goel
B16: Status | C16: COMPLETE: fundamental analysis now includes a 3-year (FY23-FY25) revenue/profit/margin trend per company (not just a snapshot); criteria-based weighting uses a fixed-threshold scoring rubric (ROE, ROCE, growth, valuation) instead of relative normalisation; Dashboard adds a Rs 10,00,000 common-investment growth comparison across all six portfolios. Workbook trimmed to 18 active sheets (the two disconnected monthly-basis sheets were removed). Two open items remain: (1) confirm the benchmark index identity (Nifty Power vs Nifty Energy), and (2) the two mutual funds' risk metrics are provider-reported, not computed on the same daily basis as Portfolios 1-4.

Sheet Data Sources & Assumptions
B2: Data Sources and Assumptions
B4: Item | C4: Status / Note | D4: Needs action?
B5: Price data source | C5: Not stated in the uploaded workbook - confirm and record here (e.g. NSE India, Yahoo Finance, Screener, Bloomberg) before submission | D5: ACTION NEEDED
B6: Analysis period (daily) | C6: 20-Sep-2021 to 16-Sep-2026, 1,238 trading days, verified continuous with no missing prices or duplicate dates | D6: OK
B7: Analysis period (monthly) | C7: SUPERSEDED: the workbook now uses DAILY returns throughout, not monthly. The Monthly Prices/Monthly Returns sheets are kept for audit history only and are marked superseded - no live formula in the workbook reads from them anymore. | D7: RESOLVED
B8: Return frequency used | C8: DAILY (changed from monthly). Every portfolio, the benchmark, the correlation/covariance matrices, and Markowitz optimisation are computed on the full 1,237-day daily return series (21-Sep-2021 to 16-Sep-2026), per the group/faculty requirement to use daily data. Annualisation: (1 + average daily return)^252 - 1 for return; daily standard deviation x SQRT(252) for risk, using the standard 252-trading-day convention for the Indian market. | D8: RESOLVED
B9: Benchmark - FLAG | C9: Labelled 'Nifty Power (Energy)' in the raw data. Price level (~Rs 37,000) matches the Nifty Energy Index (broad energy incl. oil & gas), not the Nifty Power Index (~Rs 9,000, pure power/utilities). The 10 selected companies match Nifty Power Index constituents far more closely. CONFIRM the actual allocated benchmark and, if needed, replace this series with verified Nifty Power Index data from niftyindices.com. | D9: ACTION NEEDED
B10: Price adjustment status | C10: Not confirmed whether prices are adjusted for splits/bonuses/dividends. Needs verification against the source before final submission. | D10: ACTION NEEDED
B11: Risk-free rate | C11: 91-day Treasury Bill, cut-off yield ~5.28% at the 6-Aug-2026 RBI auction (rounded to 5.30% p.a. and held constant across the period as a disclosed simplification). Source: ICRA Analytics / Aditya Birla daily fixed-income tracker, 6-Aug-2026. | D11: RESOLVED
B12: Mutual fund data (Portfolios 5 and 6) | C12: Beta, Sharpe, Std. Dev. and Alpha for both funds are now shown on their sheets and in the Dashboard, sourced from advisorkhoj.com (retrieved Sep-2026), matched to the exact Growth plan cited elsewhere in this workbook. IMPORTANT CAVEAT: these are the provider's own risk figures (typically a 3-year, monthly-return basis with their own risk-free assumption) - NOT computed on the same 5-year, daily-return, 91-day-T-Bill basis as Portfolios 1-4. Treynor ratio for both funds is a mixed-source calculation: our own 5-year CAGR and risk-free rate combined with the provider's beta. A fully like-for-like comparison would require downloading each fund's actual daily or monthly NAV history from amfiindia.com. | D12: PARTIALLY RESOLVED
B13: Fundamental data (10 companies) | C13: Extended beyond a single snapshot: Fundamental Analysis now also carries a 3-year (FY23-FY25) Revenue, Net Profit and Operating Margin trend per company, sourced from company results announcements via Business Standard / Capital Market News (retrieved Sep-2026), with revenue and profit growth computed live via formula. Adani Green uses Operating Profit instead of Net Profit for the trend, disclosed on the sheet, since a consistent consolidated Net Profit series was not obtained this session. | D13: RESOLVED
B14: Rebalancing assumption | C14: Buy-and-hold: weights set once at the start of the 5-year period and held constant (no interim rebalancing). This is the standard simplifying assumption for this kind of static, in-sample comparison and is stated explicitly here per the assignment requirement. | D14: RESOLVED
B15: Criteria portfolio methodology | C15: Rebuilt as a fixed-threshold scoring rubric (ROE, ROCE, latest revenue growth, P/E valuation - each scored 1-5 against defined bands, not ranked only against these 10 peers), replacing the earlier min-max normalisation. Weights: Profitability 30%, Efficiency 25%, Growth 25%, Valuation 20% (editable on the Fundamental Scoring sheet). This makes the weighting logic independently defensible in a viva, since a score of 4 on ROE means the same thing regardless of which companies happen to be in the sample. | D15: RESOLVED
... B17: Workbook cleanup | C17: The two superseded monthly-basis sheets (Monthly Prices, Monthly Returns) have been deleted - they were fully disconnected from every downstream formula once the workbook moved to daily-return calculations, and kept no unique data (all of it survives in the daily Historical Data / Daily Returns sheets). 18 active sheets remain, each referenced by at least one other sheet. | D17: DONE

Sheet Data Audit
B2: Data Audit - Historical Data Sheet
B4: Data item | C4: Available / Missing | D4: Accuracy concern | E4: Required correction | F4: Priority
B5: Daily prices, 10 companies + benchmark | C5: Available | D5: None found - no missing prices, no duplicate dates, chronologically sorted | E5: None | F5: OK
B6: Date coverage | C6: Available | D6: 1,238 trading days, 20-Sep-2021 to 16-Sep-2026; one Saturday session (1-Feb-2025) is a genuine NSE special session, not an error | E6: None | F6: OK
B7: Data frequency | C7: Available (daily) | D7: Faculty/group requirement is DAILY (updated from an earlier monthly approach) | E7: Used natively - see Daily Returns sheet (1,237 daily observations); no conversion needed since source data was already daily | F7: Done
B8: Benchmark identity | C8: Available but mismatched | D8: Labelled 'Nifty Power (Energy)' but price level matches Nifty Energy Index, not Nifty Power Index which the 10 companies actually track | E8: Confirm allocated benchmark; replace with verified index series if needed | F8: HIGH
B9: Price adjustment (splits/bonus/dividends) | C9: Unconfirmed | D9: Cannot verify adjustment status from the file alone | E9: Confirm with data source | F9: MEDIUM
B10: Risk-free rate | C10: Missing | D10: Not present anywhere in the workbook | E10: Add T-Bill or G-Sec series matched to the analysis period | F10: HIGH
B11: Fundamental ratios (10 companies) | C11: Missing | D11: No ROE, ROCE, margins, P/E, P/B, growth data | E11: Source from annual reports / NSE-BSE disclosures / screener.in | F11: HIGH
B12: Mutual fund NAV data (2 schemes) | C12: Missing | D12: Not present | E12: Source from AMFI / fund house, 5-year growth-option NAV | F12: HIGH
B13: Source documentation | C13: Missing | D13: No source names, URLs, or retrieval dates recorded | E13: Add to Data Sources & Assumptions sheet | F13: HIGH

Sheet Fundamental Analysis
B2: Fundamental Analysis of the 10 Selected Companies
B3: Sector allocation: Power. Columns C-J are point-in-time snapshots (mid-September 2026). Columns K onward are a 3-year financial trend (FY23-FY25) sourced from company results announcements (Business Standard / Capital Market), added to satisfy the assignment requirement to show revenue and profit growth over the period, not just a single snapshot.
B5: Company | C5: Business Description | D5: Market Cap (Rs Cr) | E5: P/E (x) | F5: Book Value (Rs) | H5: ROE % | I5: ROCE % | J5: Source | K5: Revenue FY23 (Rs Cr) | L5: Revenue FY24 (Rs Cr) | M5: Revenue FY25 (Rs Cr) | N5: Revenue Growth FY24 % | O5: Revenue Growth FY25 % | P5: Profit FY23 (Rs Cr) | Q5: Profit FY24 (Rs Cr) | R5: Profit FY25 (Rs Cr) | S5: Profit Growth FY24 % | T5: Profit Growth FY25 % | U5: OPM FY23 % | V5: OPM FY24 % | W5: OPM FY25 % | X5: Profit Metric / Note
B6: Adani Energy Solutions | C6: Power transmission, distribution and smart metering (GTD) business; India's largest private transmission company. | D6: 112014 | E6: 180.9 | F6: 166.9 | H6: 0.0403 | I6: 0.0529 | J6: ticker.finology.in, Sep-2026 | K6: 13292.72 | L6: 16607.36 | M6: 23767.09 | N6: =L6/K6-1 -> 0.24935754 | O6: =M6/L6-1 -> 0.43111789 | P6: 1256.33 | Q6: 1137.28 | R6: 1059.97 | S6: =Q6/P6-1 -> -0.094760135 | T6: =R6/Q6-1 -> -0.067977983 | U6: 0.3399 | V6: 0.3439 | W6: 0.2973 | X6: Net Profit
B7: Adani Green | C7: India's largest pure-play renewable energy IPP; solar, wind and hybrid generation. | D7: 214347 | E7: 313 | F7: 90.4 | H7: 0.071 | I7: 0.0598 | J7: screener.in (consolidated), 04-Sep-2026 | K7: 7792 | L7: 9220 | M7: 11212 | N7: =L7/K7-1 -> 0.18326489 | O7: =M7/L7-1 -> 0.21605206 | P7: 4970 | Q7: 7339 | R7: 8889 | S7: =Q7/P7-1 -> 0.47665996 | T7: =R7/Q7-1 -> 0.21120044 | U7: 0.64 | V7: 0.8 | W7: 0.79 | X7: Operating Profit (Net Profit series was inconsistent across sources this session)
B8: Adani Power | C8: Largest private thermal (coal-based) power producer in India; also has power trading operations. | D8: 401700 | E8: 28.2 | F8: 33.7 | H8: 0.211 | I8: 0.172 | J8: screener.in (consolidated), 18-Sep-2026 | K8: 38773.3 | L8: 50351.25 | M8: 56203.09 | N8: =L8/K8-1 -> 0.29860626 | O8: =M8/L8-1 -> 0.11622035 | P8: 10726.64 | Q8: 20828.79 | R8: 12938.77 | S8: =Q8/P8-1 -> 0.9417814 | T8: =R8/Q8-1 -> -0.37880357 | U8: 0.2591 | V8: 0.3611 | W8: 0.3791 | X8: Net Profit
B9: CESC | C9: Integrated power utility generating and distributing electricity to Kolkata and licensed areas in Maharashtra, Rajasthan; part of RP-Sanjiv Goenka Group. | D9: 22707 | E9: 16.6 | F9: 90.6 | H9: 0.117 | I9: 0.109 | J9: screener.in (consolidated) | K9: 14246 | L9: 15293 | M9: 17001 | N9: =L9/K9-1 -> 0.073494314 | O9: =M9/L9-1 -> 0.11168508 | P9: 1343 | Q9: 1376 | R9: 1369 | S9: =Q9/P9-1 -> 0.024571854 | T9: =R9/Q9-1 -> -0.0050872093 | U9: 0.1508 | V9: 0.139 | W9: 0.1582 | X9: Net Profit
B10: JSW Energy | C10: Independent power producer (thermal, hydro, wind, solar) and part of the JSW Group; expanding into battery storage and pumped hydro. | D10: 89314 | E10: 99.3 | F10: 130 | H10: 0.0624 | I10: 0.0582 | J10: screener.in | K10: 10331.81 | L10: 11485.91 | M10: 11745.39 | N10: =L10/K10-1 -> 0.11170356 | O10: =M10/L10-1 -> 0.022591157 | P10: 1477.76 | Q10: 1722.71 | R10: 1950.89 | S10: =Q10/P10-1 -> 0.16575763 | T10: =R10/Q10-1 -> 0.1324541 | U10: 0.143 | V10: 0.15 | W10: 0.1661 | X10: Net Profit (margin shown is Net Profit Margin; OPM not captured this session)
B11: NHPC | C11: Government of India Mini Ratna; India's largest hydropower generation company, also expanding into solar and wind. | D11: 80250 | E11: 29.6 | F11: 40 | H11: 0.0961 | I11: 0.0767 | J11: screener.in (consolidated) | K11: 10607.4 | L11: 9630.96 | M11: 10379.86 | N11: =L11/K11-1 -> -0.092052718 | O11: =M11/L11-1 -> 0.077759642 | P11: 3903.31 | Q11: 3595.95 | R11: 3006.67 | S11: =Q11/P11-1 -> -0.078743425 | T11: =R11/Q11-1 -> -0.16387325 | U11: 0.5891 | V11: 0.538 | W11: 0.5318 | X11: Net Profit
B12: NTPC | C12: India's largest power generation company (Maharatna PSU); coal, gas and increasingly renewable generation plus consultancy. | D12: 335797 | E12: 15.3 | F12: 174 | H12: 0.136 | I12: 0.105 | J12: screener.in (consolidated) | K12: 176206.93 | L12: 178524.8 | M12: 188138.06 | N12: =L12/K12-1 -> 0.01315425 | O12: =M12/L12-1 -> 0.053848317 | P12: 16912.55 | Q12: 20811.89 | R12: 23422.46 | S12: =Q12/P12-1 -> 0.23055896 | T12: =R12/Q12-1 -> 0.12543647 | U12: 0.2685 | V12: 0.2863 | W12: 0.2877 | X12: Net Profit
B13: Power Grid | C13: Central Transmission Utility of India (Maharatna PSU); owns and operates the national interstate power transmission network. | D13: 263951 | E13: 16.86 | F13: 108.05 | H13: 0.1637 | I13: 0.12 | J13: share.market (ROE) / tipranks.com (ROCE) | K13: 45581.28 | L13: 45843.1 | M13: 45792.32 | N13: =L13/K13-1 -> 0.0057440247 | O13: =M13/L13-1 -> -0.0011076912 | P13: 15419.74 | Q13: 15573.16 | R13: 15521.44 | S13: =Q13/P13-1 -> 0.0099495841 | T13: =R13/Q13-1 -> -0.0033210986 | U13: 0.8643 | V13: 0.8575 | W13: 0.8507 | X13: Net Profit
B14: Tata Power | C14: India's largest integrated private power company; generation, transmission, distribution, renewables, EV charging and solar rooftop. | D14: 116023 | E14: 30.6 | F14: 105 | H14: 0.113 | I14: 0.111 | J14: screener.in (consolidated) | K14: 55109.08 | L14: 61448.9 | M14: 65478.24 | N14: =L14/K14-1 -> 0.1150413 | O14: =M14/L14-1 -> 0.065572207 | P14: 3336.44 | Q14: 3696.25 | R14: 3971 | S14: =Q14/P14-1 -> 0.10784249 | T14: =R14/Q14-1 -> 0.074332093 | U14: 0.1398 | V14: 0.1755 | W14: 0.1978 | X14: Net Profit
B15: Torrent Power | C15: Integrated power utility (generation, transmission, distribution and renewables) across Gujarat, Maharashtra, UP and Karnataka; part of Torrent Group. | D15: 71738 | E15: 38.7 | F15: 247 | H15: 0.196 | I15: 0.183 | J15: screener.in (consolidated) | K15: 25694.12 | L15: 27183.21 | M15: 29165.26 | N15: =L15/K15-1 -> 0.057954505 | O15: =M15/L15-1 -> 0.072914494 | P15: 2117.43 | Q15: 1833.23 | R15: 2988.5 | S15: =Q15/P15-1 -> -0.13421931 | T15: =R15/Q15-1 -> 0.63018279 | U15: 0.1852 | V15: 0.1677 | W15: 0.182 | X15: Net Profit
K17: Source: company quarterly/annual results announcements via Business Standard - Capital Market News, retrieved Sep-2026 (individual URLs available on request; all figures are as originally reported, consolidated basis).

Sheet Fundamental Scoring
B2: Fundamental Scoring - Criteria-Based Weighting Methodology (Rubric-Based)
B3: Each company is scored 1 (weakest) to 5 (strongest) on four pillars against FIXED thresholds (not scored relative to just these 10 companies), so the score is independently defensible in a viva. Composite Score = weighted average of the four pillar scores (weights below, editable). Final Weight = Composite Score / SUM(all Composite Scores), so weights always sum to 100%.
D4: Profitability (ROE) | E4: Efficiency (ROCE) | F4: Growth (Revenue Growth FY25) | G4: Valuation (P/E, lower=better)
B5: Pillar Weight -> | D5: 0.3 | E5: 0.25 | F5: 0.25 | G5: 0.2
B7: Scoring Rubric (fixed thresholds, not relative to this peer set)
B8: ROE: >=18% -> 5 | 14-18% -> 4 | 10-14% -> 3 | 6-10% -> 2 | <6% -> 1
B9: ROCE: >=15% -> 5 | 12-15% -> 4 | 9-12% -> 3 | 6-9% -> 2 | <6% -> 1
B10: Revenue Growth (FY25): >=20% -> 5 | 12-20% -> 4 | 6-12% -> 3 | 0-6% -> 2 | <0% -> 1
B11: P/E (lower is better - cheaper): <=15x -> 5 | 15-20x -> 4 | 20-30x -> 3 | 30-50x -> 2 | >50x -> 1
B13: Company | C13: ROE % | D13: ROCE % | E13: Rev. Growth FY25 % | F13: P/E (x) | G13: ROE Score | H13: ROCE Score | I13: Growth Score | J13: Valuation Score | K13: Composite Score | L13: Weight %
B14: Adani Energy Solutions | C14: ='Fundamental Analysis'!H6 -> 0.0403 | D14: ='Fundamental Analysis'!I6 -> 0.0529 | E14: ='Fundamental Analysis'!O6 -> 0.43111789 | F14: ='Fundamental Analysis'!E6 -> 180.9 | G14: =IF(C14>=0.18,5,IF(C14>=0.14,4,IF(C14>=0.1,3,IF(C14>=0.06,2,1)))) -> 1 | H14: =IF(D14>=0.15,5,IF(D14>=0.12,4,IF(D14>=0.09,3,IF(D14>=0.06,2,1)))) -> 1 | I14: =IF(E14>=0.2,5,IF(E14>=0.12,4,IF(E14>=0.06,3,IF(E14>=0,2,1)))) -> 5 | J14: =IF(F14<=15,5,IF(F14<=20,4,IF(F14<=30,3,IF(F14<=50,2,1)))) -> 1 | K14: =G14*$D$5+H14*$E$5+I14*$F$5+J14*$G$5 -> 2 | L14: =K14/SUM($K$14:$K$23) -> 0.070175439
B15: Adani Green | C15: ='Fundamental Analysis'!H7 -> 0.071 | D15: ='Fundamental Analysis'!I7 -> 0.0598 | E15: ='Fundamental Analysis'!O7 -> 0.21605206 | F15: ='Fundamental Analysis'!E7 -> 313 | G15: =IF(C15>=0.18,5,IF(C15>=0.14,4,IF(C15>=0.1,3,IF(C15>=0.06,2,1)))) -> 2 | H15: =IF(D15>=0.15,5,IF(D15>=0.12,4,IF(D15>=0.09,3,IF(D15>=0.06,2,1)))) -> 1 | I15: =IF(E15>=0.2,5,IF(E15>=0.12,4,IF(E15>=0.06,3,IF(E15>=0,2,1)))) -> 5 | J15: =IF(F15<=15,5,IF(F15<=20,4,IF(F15<=30,3,IF(F15<=50,2,1)))) -> 1 | K15: =G15*$D$5+H15*$E$5+I15*$F$5+J15*$G$5 -> 2.3 | L15: =K15/SUM($K$14:$K$23) -> 0.080701754
B16: Adani Power | C16: ='Fundamental Analysis'!H8 -> 0.211 | D16: ='Fundamental Analysis'!I8 -> 0.172 | E16: ='Fundamental Analysis'!O8 -> 0.11622035 | F16: ='Fundamental Analysis'!E8 -> 28.2 | G16: =IF(C16>=0.18,5,IF(C16>=0.14,4,IF(C16>=0.1,3,IF(C16>=0.06,2,1)))) -> 5 | H16: =IF(D16>=0.15,5,IF(D16>=0.12,4,IF(D16>=0.09,3,IF(D16>=0.06,2,1)))) -> 5 | I16: =IF(E16>=0.2,5,IF(E16>=0.12,4,IF(E16>=0.06,3,IF(E16>=0,2,1)))) -> 3 | J16: =IF(F16<=15,5,IF(F16<=20,4,IF(F16<=30,3,IF(F16<=50,2,1)))) -> 3 | K16: =G16*$D$5+H16*$E$5+I16*$F$5+J16*$G$5 -> 4.1 | L16: =K16/SUM($K$14:$K$23) -> 0.14385965
B17: CESC | C17: ='Fundamental Analysis'!H9 -> 0.117 | D17: ='Fundamental Analysis'!I9 -> 0.109 | E17: ='Fundamental Analysis'!O9 -> 0.11168508 | F17: ='Fundamental Analysis'!E9 -> 16.6 | G17: =IF(C17>=0.18,5,IF(C17>=0.14,4,IF(C17>=0.1,3,IF(C17>=0.06,2,1)))) -> 3 | H17: =IF(D17>=0.15,5,IF(D17>=0.12,4,IF(D17>=0.09,3,IF(D17>=0.06,2,1)))) -> 3 | I17: =IF(E17>=0.2,5,IF(E17>=0.12,4,IF(E17>=0.06,3,IF(E17>=0,2,1)))) -> 3 | J17: =IF(F17<=15,5,IF(F17<=20,4,IF(F17<=30,3,IF(F17<=50,2,1)))) -> 4 | K17: =G17*$D$5+H17*$E$5+I17*$F$5+J17*$G$5 -> 3.2 | L17: =K17/SUM($K$14:$K$23) -> 0.1122807
B18: JSW Energy | C18: ='Fundamental Analysis'!H10 -> 0.0624 | D18: ='Fundamental Analysis'!I10 -> 0.0582 | E18: ='Fundamental Analysis'!O10 -> 0.022591157 | F18: ='Fundamental Analysis'!E10 -> 99.3 | G18: =IF(C18>=0.18,5,IF(C18>=0.14,4,IF(C18>=0.1,3,IF(C18>=0.06,2,1)))) -> 2 | H18: =IF(D18>=0.15,5,IF(D18>=0.12,4,IF(D18>=0.09,3,IF(D18>=0.06,2,1)))) -> 1 | I18: =IF(E18>=0.2,5,IF(E18>=0.12,4,IF(E18>=0.06,3,IF(E18>=0,2,1)))) -> 2 | J18: =IF(F18<=15,5,IF(F18<=20,4,IF(F18<=30,3,IF(F18<=50,2,1)))) -> 1 | K18: =G18*$D$5+H18*$E$5+I18*$F$5+J18*$G$5 -> 1.55 | L18: =K18/SUM($K$14:$K$23) -> 0.054385965
B19: NHPC | C19: ='Fundamental Analysis'!H11 -> 0.0961 | D19: ='Fundamental Analysis'!I11 -> 0.0767 | E19: ='Fundamental Analysis'!O11 -> 0.077759642 | F19: ='Fundamental Analysis'!E11 -> 29.6 | G19: =IF(C19>=0.18,5,IF(C19>=0.14,4,IF(C19>=0.1,3,IF(C19>=0.06,2,1)))) -> 2 | H19: =IF(D19>=0.15,5,IF(D19>=0.12,4,IF(D19>=0.09,3,IF(D19>=0.06,2,1)))) -> 2 | I19: =IF(E19>=0.2,5,IF(E19>=0.12,4,IF(E19>=0.06,3,IF(E19>=0,2,1)))) -> 3 | J19: =IF(F19<=15,5,IF(F19<=20,4,IF(F19<=30,3,IF(F19<=50,2,1)))) -> 3 | K19: =G19*$D$5+H19*$E$5+I19*$F$5+J19*$G$5 -> 2.45 | L19: =K19/SUM($K$14:$K$23) -> 0.085964912
B20: NTPC | C20: ='Fundamental Analysis'!H12 -> 0.136 | D20: ='Fundamental Analysis'!I12 -> 0.105 | E20: ='Fundamental Analysis'!O12 -> 0.053848317 | F20: ='Fundamental Analysis'!E12 -> 15.3 | G20: =IF(C20>=0.18,5,IF(C20>=0.14,4,IF(C20>=0.1,3,IF(C20>=0.06,2,1)))) -> 3 | H20: =IF(D20>=0.15,5,IF(D20>=0.12,4,IF(D20>=0.09,3,IF(D20>=0.06,2,1)))) -> 3 | I20: =IF(E20>=0.2,5,IF(E20>=0.12,4,IF(E20>=0.06,3,IF(E20>=0,2,1)))) -> 2 | J20: =IF(F20<=15,5,IF(F20<=20,4,IF(F20<=30,3,IF(F20<=50,2,1)))) -> 4 | K20: =G20*$D$5+H20*$E$5+I20*$F$5+J20*$G$5 -> 2.95 | L20: =K20/SUM($K$14:$K$23) -> 0.10350877
B21: Power Grid | C21: ='Fundamental Analysis'!H13 -> 0.1637 | D21: ='Fundamental Analysis'!I13 -> 0.12 | E21: ='Fundamental Analysis'!O13 -> -0.0011076912 | F21: ='Fundamental Analysis'!E13 -> 16.86 | G21: =IF(C21>=0.18,5,IF(C21>=0.14,4,IF(C21>=0.1,3,IF(C21>=0.06,2,1)))) -> 4 | H21: =IF(D21>=0.15,5,IF(D21>=0.12,4,IF(D21>=0.09,3,IF(D21>=0.06,2,1)))) -> 4 | I21: =IF(E21>=0.2,5,IF(E21>=0.12,4,IF(E21>=0.06,3,IF(E21>=0,2,1)))) -> 1 | J21: =IF(F21<=15,5,IF(F21<=20,4,IF(F21<=30,3,IF(F21<=50,2,1)))) -> 4 | K21: =G21*$D$5+H21*$E$5+I21*$F$5+J21*$G$5 -> 3.25 | L21: =K21/SUM($K$14:$K$23) -> 0.11403509
B22: Tata Power | C22: ='Fundamental Analysis'!H14 -> 0.113 | D22: ='Fundamental Analysis'!I14 -> 0.111 | E22: ='Fundamental Analysis'!O14 -> 0.065572207 | F22: ='Fundamental Analysis'!E14 -> 30.6 | G22: =IF(C22>=0.18,5,IF(C22>=0.14,4,IF(C22>=0.1,3,IF(C22>=0.06,2,1)))) -> 3 | H22: =IF(D22>=0.15,5,IF(D22>=0.12,4,IF(D22>=0.09,3,IF(D22>=0.06,2,1)))) -> 3 | I22: =IF(E22>=0.2,5,IF(E22>=0.12,4,IF(E22>=0.06,3,IF(E22>=0,2,1)))) -> 3 | J22: =IF(F22<=15,5,IF(F22<=20,4,IF(F22<=30,3,IF(F22<=50,2,1)))) -> 2 | K22: =G22*$D$5+H22*$E$5+I22*$F$5+J22*$G$5 -> 2.8 | L22: =K22/SUM($K$14:$K$23) -> 0.098245614
B23: Torrent Power | C23: ='Fundamental Analysis'!H15 -> 0.196 | D23: ='Fundamental Analysis'!I15 -> 0.183 | E23: ='Fundamental Analysis'!O15 -> 0.072914494 | F23: ='Fundamental Analysis'!E15 -> 38.7 | G23: =IF(C23>=0.18,5,IF(C23>=0.14,4,IF(C23>=0.1,3,IF(C23>=0.06,2,1)))) -> 5 | H23: =IF(D23>=0.15,5,IF(D23>=0.12,4,IF(D23>=0.09,3,IF(D23>=0.06,2,1)))) -> 5 | I23: =IF(E23>=0.2,5,IF(E23>=0.12,4,IF(E23>=0.06,3,IF(E23>=0,2,1)))) -> 3 | J23: =IF(F23<=15,5,IF(F23<=20,4,IF(F23<=30,3,IF(F23<=50,2,1)))) -> 2 | K23: =G23*$D$5+H23*$E$5+I23*$F$5+J23*$G$5 -> 3.9 | L23: =K23/SUM($K$14:$K$23) -> 0.13684211
B24: TOTAL | L24: =SUM(L14:L23) -> 1

Sheet Portfolio 1 - Equal Weight
B2: Portfolio 1: Equally Weighted Portfolio
B3: 10% weight to each of the 10 selected companies. Daily return = SUMPRODUCT(weights, company daily returns), linked live to the Daily Returns sheet (1,237 trading days).
B4: (helper row - weights mirrored horizontally for SUMPRODUCT) | D4: =C6 -> 0.1 | E4: =C7 -> 0.1 | F4: =C8 -> 0.1 | G4: =C9 -> 0.1 | H4: =C10 -> 0.1 | I4: =C11 -> 0.1 | J4: =C12 -> 0.1 | K4: =C13 -> 0.1 | L4: =C14 -> 0.1 | M4: =C15 -> 0.1
B5: Company | C5: Weight | E5: Date | F5: Portfolio Daily Return
B6: Adani Energy Solutions | C6: 0.1 | E6: ='Daily Returns'!B6 -> 44460 | F6: =SUMPRODUCT($D$4:$M$4,'Daily Returns'!D6:M6) -> -0.0078737931
B7: Adani Green | C7: 0.1 | E7: ='Daily Returns'!B7 -> 44461 | F7: =SUMPRODUCT($D$4:$M$4,'Daily Returns'!D7:M7) -> -0.0024220608
B8: Adani Power | C8: 0.1 | E8: ='Daily Returns'!B8 -> 44462 | F8: =SUMPRODUCT($D$4:$M$4,'Daily Returns'!D8:M8) -> 0.013150958
B9: CESC | C9: 0.1 | E9: ='Daily Returns'!B9 -> 44463 | F9: =SUMPRODUCT($D$4:$M$4,'Daily Returns'!D9:M9) -> -0.0084675047
B10: JSW Energy | C10: 0.1 | E10: ='Daily Returns'!B10 -> 44466 | F10: =SUMPRODUCT($D$4:$M$4,'Daily Returns'!D10:M10) -> 0.00203978
B11: NHPC | C11: 0.1 | E11: ='Daily Returns'!B11 -> 44467 | F11: =SUMPRODUCT($D$4:$M$4,'Daily Returns'!D11:M11) -> 0.014134331
B12: NTPC | C12: 0.1 | E12: ='Daily Returns'!B12 -> 44468 | F12: =SUMPRODUCT($D$4:$M$4,'Daily Returns'!D12:M12) -> 0.037921793
B13: Power Grid | C13: 0.1 | E13: ='Daily Returns'!B13 -> 44469 | F13: =SUMPRODUCT($D$4:$M$4,'Daily Returns'!D13:M13) -> 0.010823112
B14: Tata Power | C14: 0.1 | E14: ='Daily Returns'!B14 -> 44470 | F14: =SUMPRODUCT($D$4:$M$4,'Daily Returns'!D14:M14) -> -0.0003275499
B15: Torrent Power | C15: 0.1 | E15: ='Daily Returns'!B15 -> 44473 | F15: =SUMPRODUCT($D$4:$M$4,'Daily Returns'!D15:M15) -> 0.019260004
B16: TOTAL | C16: =SUM(C6:C15) -> 1 | E16: ='Daily Returns'!B16 -> 44474 | F16: =SUMPRODUCT($D$4:$M$4,'Daily Returns'!D16:M16) -> 0.026301847
E17: ='Daily Returns'!B17 -> 44475 | F17: =SUMPRODUCT($D$4:$M$4,'Daily Returns'!D17:M17) -> -0.012295777
E18: ='Daily Returns'!B18 -> 44476 | F18: =SUMPRODUCT($D$4:$M$4,'Daily Returns'!D18:M18) -> -0.00020149416
E19: ='Daily Returns'!B19 -> 44477 | F19: =SUMPRODUCT($D$4:$M$4,'Daily Returns'!D19:M19) -> -0.010577193
E20: ='Daily Returns'!B20 -> 44480 | F20: =SUMPRODUCT($D$4:$M$4,'Daily Returns'!D20:M20) -> 0.024334458
E21: ='Daily Returns'!B21 -> 44481 | F21: =SUMPRODUCT($D$4:$M$4,'Daily Returns'!D21:M21) -> -0.0016884724
E22: ='Daily Returns'!B22 -> 44482 | F22: =SUMPRODUCT($D$4:$M$4,'Daily Returns'!D22:M22) -> 0.026732478
E23: ='Daily Returns'!B23 -> 44483 | F23: =SUMPRODUCT($D$4:$M$4,'Daily Returns'!D23:M23) -> 0.015243384
E24: ='Daily Returns'!B24 -> 44487 | F24: =SUMPRODUCT($D$4:$M$4,'Daily Returns'!D24:M24) -> 0.049034974
E25: ='Daily Returns'!B25 -> 44488 | F25: =SUMPRODUCT($D$4:$M$4,'Daily Returns'!D25:M25) -> -0.025469091
E26: ='Daily Returns'!B26 -> 44489 | F26: =SUMPRODUCT($D$4:$M$4,'Daily Returns'!D26:M26) -> -0.020768582
E27: ='Daily Returns'!B27 -> 44490 | F27: =SUMPRODUCT($D$4:$M$4,'Daily Returns'!D27:M27) -> 0.0031616308
E28: ='Daily Returns'!B28 -> 44491 | F28: =SUMPRODUCT($D$4:$M$4,'Daily Returns'!D28:M28) -> -0.0019391672
... E1242: ='Daily Returns'!B1242 -> 46281 | F1242: =SUMPRODUCT($D$4:$M$4,'Daily Returns'!D1242:M1242) -> -0.0013089092
E1244: Average Daily Return | F1244: =AVERAGE(F6:F1242) -> 0.0010034079
E1245: Annualised Return (compounded, 252 trading days) | F1245: =(1+F1244)^252-1 -> 0.28753819
E1246: Daily Std. Dev. | F1246: =STDEV(F6:F1242) -> 0.015769568
E1247: Annualised Std. Dev. | F1247: =F1246*SQRT(252) -> 0.25033414

Sheet Portfolio 2 - Criteria Based
B2: Portfolio 2: Criteria-Based Portfolio (Composite Fundamental Score)
B3: Weights from the composite fundamental score (ROE, ROCE, inverse P/E) on the Fundamental Scoring sheet - unchanged by the return-frequency switch. Daily return = SUMPRODUCT(weights, company daily returns).
B4: (helper row - weights mirrored horizontally for SUMPRODUCT) | D4: =C6 -> 0.070175439 | E4: =C7 -> 0.080701754 | F4: =C8 -> 0.14385965 | G4: =C9 -> 0.1122807 | H4: =C10 -> 0.054385965 | I4: =C11 -> 0.085964912 | J4: =C12 -> 0.10350877 | K4: =C13 -> 0.11403509 | L4: =C14 -> 0.098245614 | M4: =C15 -> 0.13684211
B5: Company | C5: Weight | E5: Date | F5: Portfolio Daily Return
B6: Adani Energy Solutions | C6: ='Fundamental Scoring'!L14 -> 0.070175439 | E6: ='Daily Returns'!B6 -> 44460 | F6: =SUMPRODUCT($D$4:$M$4,'Daily Returns'!D6:M6) -> -0.0074747346
B7: Adani Green | C7: ='Fundamental Scoring'!L15 -> 0.080701754 | E7: ='Daily Returns'!B7 -> 44461 | F7: =SUMPRODUCT($D$4:$M$4,'Daily Returns'!D7:M7) -> -0.0010212169
B8: Adani Power | C8: ='Fundamental Scoring'!L16 -> 0.14385965 | E8: ='Daily Returns'!B8 -> 44462 | F8: =SUMPRODUCT($D$4:$M$4,'Daily Returns'!D8:M8) -> 0.012353631
B9: CESC | C9: ='Fundamental Scoring'!L17 -> 0.1122807 | E9: ='Daily Returns'!B9 -> 44463 | F9: =SUMPRODUCT($D$4:$M$4,'Daily Returns'!D9:M9) -> -0.0091423539
B10: JSW Energy | C10: ='Fundamental Scoring'!L18 -> 0.054385965 | E10: ='Daily Returns'!B10 -> 44466 | F10: =SUMPRODUCT($D$4:$M$4,'Daily Returns'!D10:M10) -> 0.0014929421
B11: NHPC | C11: ='Fundamental Scoring'!L19 -> 0.085964912 | E11: ='Daily Returns'!B11 -> 44467 | F11: =SUMPRODUCT($D$4:$M$4,'Daily Returns'!D11:M11) -> 0.013267485
B12: NTPC | C12: ='Fundamental Scoring'!L20 -> 0.10350877 | E12: ='Daily Returns'!B12 -> 44468 | F12: =SUMPRODUCT($D$4:$M$4,'Daily Returns'!D12:M12) -> 0.039222541
B13: Power Grid | C13: ='Fundamental Scoring'!L21 -> 0.11403509 | E13: ='Daily Returns'!B13 -> 44469 | F13: =SUMPRODUCT($D$4:$M$4,'Daily Returns'!D13:M13) -> 0.0082326286
B14: Tata Power | C14: ='Fundamental Scoring'!L22 -> 0.098245614 | E14: ='Daily Returns'!B14 -> 44470 | F14: =SUMPRODUCT($D$4:$M$4,'Daily Returns'!D14:M14) -> -0.00018375596
B15: Torrent Power | C15: ='Fundamental Scoring'!L23 -> 0.13684211 | E15: ='Daily Returns'!B15 -> 44473 | F15: =SUMPRODUCT($D$4:$M$4,'Daily Returns'!D15:M15) -> 0.020603456
B16: TOTAL | C16: =SUM(C6:C15) -> 1 | E16: ='Daily Returns'!B16 -> 44474 | F16: =SUMPRODUCT($D$4:$M$4,'Daily Returns'!D16:M16) -> 0.025550457
E17: ='Daily Returns'!B17 -> 44475 | F17: =SUMPRODUCT($D$4:$M$4,'Daily Returns'!D17:M17) -> -0.015222357
E18: ='Daily Returns'!B18 -> 44476 | F18: =SUMPRODUCT($D$4:$M$4,'Daily Returns'!D18:M18) -> 0.00020762235
E19: ='Daily Returns'!B19 -> 44477 | F19: =SUMPRODUCT($D$4:$M$4,'Daily Returns'!D19:M19) -> -0.009741014
E20: ='Daily Returns'!B20 -> 44480 | F20: =SUMPRODUCT($D$4:$M$4,'Daily Returns'!D20:M20) -> 0.02665423
E21: ='Daily Returns'!B21 -> 44481 | F21: =SUMPRODUCT($D$4:$M$4,'Daily Returns'!D21:M21) -> -0.0024008125
E22: ='Daily Returns'!B22 -> 44482 | F22: =SUMPRODUCT($D$4:$M$4,'Daily Returns'!D22:M22) -> 0.027267844
E23: ='Daily Returns'!B23 -> 44483 | F23: =SUMPRODUCT($D$4:$M$4,'Daily Returns'!D23:M23) -> 0.017761936
E24: ='Daily Returns'!B24 -> 44487 | F24: =SUMPRODUCT($D$4:$M$4,'Daily Returns'!D24:M24) -> 0.051246472
E25: ='Daily Returns'!B25 -> 44488 | F25: =SUMPRODUCT($D$4:$M$4,'Daily Returns'!D25:M25) -> -0.023597132
E26: ='Daily Returns'!B26 -> 44489 | F26: =SUMPRODUCT($D$4:$M$4,'Daily Returns'!D26:M26) -> -0.022098438
E27: ='Daily Returns'!B27 -> 44490 | F27: =SUMPRODUCT($D$4:$M$4,'Daily Returns'!D27:M27) -> 0.0034969673
E28: ='Daily Returns'!B28 -> 44491 | F28: =SUMPRODUCT($D$4:$M$4,'Daily Returns'!D28:M28) -> -0.0064509369
... E1242: ='Daily Returns'!B1242 -> 46281 | F1242: =SUMPRODUCT($D$4:$M$4,'Daily Returns'!D1242:M1242) -> -0.0015383151
E1244: Average Daily Return | F1244: =AVERAGE(F6:F1242) -> 0.0011028145
E1245: Annualised Return (compounded, 252 trading days) | F1245: =(1+F1244)^252-1 -> 0.32016421
E1246: Daily Std. Dev. | F1246: =STDEV(F6:F1242) -> 0.015490194
E1247: Annualised Std. Dev. | F1247: =F1246*SQRT(252) -> 0.2458992

Sheet Correlation Matrix
B2: Correlation Matrix - 10 Selected Companies (Monthly Returns)
B3: Computed with Excel CORREL across the 1,237 daily return observations (21-Sep-2021 to 16-Sep-2026) for each pair of companies, linked to the Daily Returns sheet.
C5: ADANIENSOL | D5: ADANIGREEN | E5: ADANIPOWER | F5: CESC | G5: JSWENERGY | H5: NHPC | I5: NTPC | J5: POWERGRID | K5: TATAPOWER | L5: TORNTPOWER
B6: ADANIENSOL | C6: =CORREL('Daily Returns'!D6:D1242,'Daily Returns'!D6:D1242) -> 1 | D6: =CORREL('Daily Returns'!D6:D1242,'Daily Returns'!E6:E1242) -> 0.7123365 | E6: =CORREL('Daily Returns'!D6:D1242,'Daily Returns'!F6:F1242) -> 0.55151203 | F6: =CORREL('Daily Returns'!D6:D1242,'Daily Returns'!G6:G1242) -> 0.26876095 | G6: =CORREL('Daily Returns'!D6:D1242,'Daily Returns'!H6:H1242) -> 0.28867672 | H6: =CORREL('Daily Returns'!D6:D1242,'Daily Returns'!I6:I1242) -> 0.27627533 | I6: =CORREL('Daily Returns'!D6:D1242,'Daily Returns'!J6:J1242) -> 0.32166574 | J6: =CORREL('Daily Returns'!D6:D1242,'Daily Returns'!K6:K1242) -> 0.26912385 | K6: =CORREL('Daily Returns'!D6:D1242,'Daily Returns'!L6:L1242) -> 0.3387659 | L6: =CORREL('Daily Returns'!D6:D1242,'Daily Returns'!M6:M1242) -> 0.24168163
B7: ADANIGREEN | C7: =CORREL('Daily Returns'!E6:E1242,'Daily Returns'!D6:D1242) -> 0.7123365 | D7: =CORREL('Daily Returns'!E6:E1242,'Daily Returns'!E6:E1242) -> 1 | E7: =CORREL('Daily Returns'!E6:E1242,'Daily Returns'!F6:F1242) -> 0.55704869 | F7: =CORREL('Daily Returns'!E6:E1242,'Daily Returns'!G6:G1242) -> 0.24969577 | G7: =CORREL('Daily Returns'!E6:E1242,'Daily Returns'!H6:H1242) -> 0.3108042 | H7: =CORREL('Daily Returns'!E6:E1242,'Daily Returns'!I6:I1242) -> 0.26648999 | I7: =CORREL('Daily Returns'!E6:E1242,'Daily Returns'!J6:J1242) -> 0.29384545 | J7: =CORREL('Daily Returns'!E6:E1242,'Daily Returns'!K6:K1242) -> 0.21641338 | K7: =CORREL('Daily Returns'!E6:E1242,'Daily Returns'!L6:L1242) -> 0.33080037 | L7: =CORREL('Daily Returns'!E6:E1242,'Daily Returns'!M6:M1242) -> 0.22226259
B8: ADANIPOWER | C8: =CORREL('Daily Returns'!F6:F1242,'Daily Returns'!D6:D1242) -> 0.55151203 | D8: =CORREL('Daily Returns'!F6:F1242,'Daily Returns'!E6:E1242) -> 0.55704869 | E8: =CORREL('Daily Returns'!F6:F1242,'Daily Returns'!F6:F1242) -> 1 | F8: =CORREL('Daily Returns'!F6:F1242,'Daily Returns'!G6:G1242) -> 0.29817998 | G8: =CORREL('Daily Returns'!F6:F1242,'Daily Returns'!H6:H1242) -> 0.37861597 | H8: =CORREL('Daily Returns'!F6:F1242,'Daily Returns'!I6:I1242) -> 0.30717777 | I8: =CORREL('Daily Returns'!F6:F1242,'Daily Returns'!J6:J1242) -> 0.36227624 | J8: =CORREL('Daily Returns'!F6:F1242,'Daily Returns'!K6:K1242) -> 0.249803 | K8: =CORREL('Daily Returns'!F6:F1242,'Daily Returns'!L6:L1242) -> 0.42779696 | L8: =CORREL('Daily Returns'!F6:F1242,'Daily Returns'!M6:M1242) -> 0.22148553
B9: CESC | C9: =CORREL('Daily Returns'!G6:G1242,'Daily Returns'!D6:D1242) -> 0.26876095 | D9: =CORREL('Daily Returns'!G6:G1242,'Daily Returns'!E6:E1242) -> 0.24969577 | E9: =CORREL('Daily Returns'!G6:G1242,'Daily Returns'!F6:F1242) -> 0.29817998 | F9: =CORREL('Daily Returns'!G6:G1242,'Daily Returns'!G6:G1242) -> 1 | G9: =CORREL('Daily Returns'!G6:G1242,'Daily Returns'!H6:H1242) -> 0.37432442 | H9: =CORREL('Daily Returns'!G6:G1242,'Daily Returns'!I6:I1242) -> 0.4366281 | I9: =CORREL('Daily Returns'!G6:G1242,'Daily Returns'!J6:J1242) -> 0.4564523 | J9: =CORREL('Daily Returns'!G6:G1242,'Daily Returns'!K6:K1242) -> 0.37084185 | K9: =CORREL('Daily Returns'!G6:G1242,'Daily Returns'!L6:L1242) -> 0.50082152 | L9: =CORREL('Daily Returns'!G6:G1242,'Daily Returns'!M6:M1242) -> 0.31852673
B10: JSWENERGY | C10: =CORREL('Daily Returns'!H6:H1242,'Daily Returns'!D6:D1242) -> 0.28867672 | D10: =CORREL('Daily Returns'!H6:H1242,'Daily Returns'!E6:E1242) -> 0.3108042 | E10: =CORREL('Daily Returns'!H6:H1242,'Daily Returns'!F6:F1242) -> 0.37861597 | F10: =CORREL('Daily Returns'!H6:H1242,'Daily Returns'!G6:G1242) -> 0.37432442 | G10: =CORREL('Daily Returns'!H6:H1242,'Daily Returns'!H6:H1242) -> 1 | H10: =CORREL('Daily Returns'!H6:H1242,'Daily Returns'!I6:I1242) -> 0.35236708 | I10: =CORREL('Daily Returns'!H6:H1242,'Daily Returns'!J6:J1242) -> 0.407494 | J10: =CORREL('Daily Returns'!H6:H1242,'Daily Returns'!K6:K1242) -> 0.35903812 | K10: =CORREL('Daily Returns'!H6:H1242,'Daily Returns'!L6:L1242) -> 0.47672422 | L10: =CORREL('Daily Returns'!H6:H1242,'Daily Returns'!M6:M1242) -> 0.32839048
B11: NHPC | C11: =CORREL('Daily Returns'!I6:I1242,'Daily Returns'!D6:D1242) -> 0.27627533 | D11: =CORREL('Daily Returns'!I6:I1242,'Daily Returns'!E6:E1242) -> 0.26648999 | E11: =CORREL('Daily Returns'!I6:I1242,'Daily Returns'!F6:F1242) -> 0.30717777 | F11: =CORREL('Daily Returns'!I6:I1242,'Daily Returns'!G6:G1242) -> 0.4366281 | G11: =CORREL('Daily Returns'!I6:I1242,'Daily Returns'!H6:H1242) -> 0.35236708 | H11: =CORREL('Daily Returns'!I6:I1242,'Daily Returns'!I6:I1242) -> 1 | I11: =CORREL('Daily Returns'!I6:I1242,'Daily Returns'!J6:J1242) -> 0.42330181 | J11: =CORREL('Daily Returns'!I6:I1242,'Daily Returns'!K6:K1242) -> 0.36172284 | K11: =CORREL('Daily Returns'!I6:I1242,'Daily Returns'!L6:L1242) -> 0.49198183 | L11: =CORREL('Daily Returns'!I6:I1242,'Daily Returns'!M6:M1242) -> 0.31579502
B12: NTPC | C12: =CORREL('Daily Returns'!J6:J1242,'Daily Returns'!D6:D1242) -> 0.32166574 | D12: =CORREL('Daily Returns'!J6:J1242,'Daily Returns'!E6:E1242) -> 0.29384545 | E12: =CORREL('Daily Returns'!J6:J1242,'Daily Returns'!F6:F1242) -> 0.36227624 | F12: =CORREL('Daily Returns'!J6:J1242,'Daily Returns'!G6:G1242) -> 0.4564523 | G12: =CORREL('Daily Returns'!J6:J1242,'Daily Returns'!H6:H1242) -> 0.407494 | H12: =CORREL('Daily Returns'!J6:J1242,'Daily Returns'!I6:I1242) -> 0.42330181 | I12: =CORREL('Daily Returns'!J6:J1242,'Daily Returns'!J6:J1242) -> 1 | J12: =CORREL('Daily Returns'!J6:J1242,'Daily Returns'!K6:K1242) -> 0.59614378 | K12: =CORREL('Daily Returns'!J6:J1242,'Daily Returns'!L6:L1242) -> 0.55505059 | L12: =CORREL('Daily Returns'!J6:J1242,'Daily Returns'!M6:M1242) -> 0.39430667
B13: POWERGRID | C13: =CORREL('Daily Returns'!K6:K1242,'Daily Returns'!D6:D1242) -> 0.26912385 | D13: =CORREL('Daily Returns'!K6:K1242,'Daily Returns'!E6:E1242) -> 0.21641338 | E13: =CORREL('Daily Returns'!K6:K1242,'Daily Returns'!F6:F1242) -> 0.249803 | F13: =CORREL('Daily Returns'!K6:K1242,'Daily Returns'!G6:G1242) -> 0.37084185 | G13: =CORREL('Daily Returns'!K6:K1242,'Daily Returns'!H6:H1242) -> 0.35903812 | H13: =CORREL('Daily Returns'!K6:K1242,'Daily Returns'!I6:I1242) -> 0.36172284 | I13: =CORREL('Daily Returns'!K6:K1242,'Daily Returns'!J6:J1242) -> 0.59614378 | J13: =CORREL('Daily Returns'!K6:K1242,'Daily Returns'!K6:K1242) -> 1 | K13: =CORREL('Daily Returns'!K6:K1242,'Daily Returns'!L6:L1242) -> 0.45187652 | L13: =CORREL('Daily Returns'!K6:K1242,'Daily Returns'!M6:M1242) -> 0.30577951
B14: TATAPOWER | C14: =CORREL('Daily Returns'!L6:L1242,'Daily Returns'!D6:D1242) -> 0.3387659 | D14: =CORREL('Daily Returns'!L6:L1242,'Daily Returns'!E6:E1242) -> 0.33080037 | E14: =CORREL('Daily Returns'!L6:L1242,'Daily Returns'!F6:F1242) -> 0.42779696 | F14: =CORREL('Daily Returns'!L6:L1242,'Daily Returns'!G6:G1242) -> 0.50082152 | G14: =CORREL('Daily Returns'!L6:L1242,'Daily Returns'!H6:H1242) -> 0.47672422 | H14: =CORREL('Daily Returns'!L6:L1242,'Daily Returns'!I6:I1242) -> 0.49198183 | I14: =CORREL('Daily Returns'!L6:L1242,'Daily Returns'!J6:J1242) -> 0.55505059 | J14: =CORREL('Daily Returns'!L6:L1242,'Daily Returns'!K6:K1242) -> 0.45187652 | K14: =CORREL('Daily Returns'!L6:L1242,'Daily Returns'!L6:L1242) -> 1 | L14: =CORREL('Daily Returns'!L6:L1242,'Daily Returns'!M6:M1242) -> 0.4439229
B15: TORNTPOWER | C15: =CORREL('Daily Returns'!M6:M1242,'Daily Returns'!D6:D1242) -> 0.24168163 | D15: =CORREL('Daily Returns'!M6:M1242,'Daily Returns'!E6:E1242) -> 0.22226259 | E15: =CORREL('Daily Returns'!M6:M1242,'Daily Returns'!F6:F1242) -> 0.22148553 | F15: =CORREL('Daily Returns'!M6:M1242,'Daily Returns'!G6:G1242) -> 0.31852673 | G15: =CORREL('Daily Returns'!M6:M1242,'Daily Returns'!H6:H1242) -> 0.32839048 | H15: =CORREL('Daily Returns'!M6:M1242,'Daily Returns'!I6:I1242) -> 0.31579502 | I15: =CORREL('Daily Returns'!M6:M1242,'Daily Returns'!J6:J1242) -> 0.39430667 | J15: =CORREL('Daily Returns'!M6:M1242,'Daily Returns'!K6:K1242) -> 0.30577951 | K15: =CORREL('Daily Returns'!M6:M1242,'Daily Returns'!L6:L1242) -> 0.4439229 | L15: =CORREL('Daily Returns'!M6:M1242,'Daily Returns'!M6:M1242) -> 1

Sheet Covariance Matrix
B2: Covariance Matrix - 10 Selected Companies (Monthly Returns)
B3: Computed with Excel COVAR across the 1,237 daily return observations (21-Sep-2021 to 16-Sep-2026) for each pair of companies, linked to the Daily Returns sheet.
C5: ADANIENSOL | D5: ADANIGREEN | E5: ADANIPOWER | F5: CESC | G5: JSWENERGY | H5: NHPC | I5: NTPC | J5: POWERGRID | K5: TATAPOWER | L5: TORNTPOWER
B6: ADANIENSOL | C6: =COVAR('Daily Returns'!D6:D1242,'Daily Returns'!D6:D1242) -> 0.0010064446 | D6: =COVAR('Daily Returns'!D6:D1242,'Daily Returns'!E6:E1242) -> 0.00073847232 | E6: =COVAR('Daily Returns'!D6:D1242,'Daily Returns'!F6:F1242) -> 0.00054189114 | F6: =COVAR('Daily Returns'!D6:D1242,'Daily Returns'!G6:G1242) -> 0.00017403346 | G6: =COVAR('Daily Returns'!D6:D1242,'Daily Returns'!H6:H1242) -> 0.00024284038 | H6: =COVAR('Daily Returns'!D6:D1242,'Daily Returns'!I6:I1242) -> 0.00018853735 | I6: =COVAR('Daily Returns'!D6:D1242,'Daily Returns'!J6:J1242) -> 0.00016084264 | J6: =COVAR('Daily Returns'!D6:D1242,'Daily Returns'!K6:K1242) -> 0.00013554785 | K6: =COVAR('Daily Returns'!D6:D1242,'Daily Returns'!L6:L1242) -> 0.00021912302 | L6: =COVAR('Daily Returns'!D6:D1242,'Daily Returns'!M6:M1242) -> 0.00017374417
B7: ADANIGREEN | C7: =COVAR('Daily Returns'!E6:E1242,'Daily Returns'!D6:D1242) -> 0.00073847232 | D7: =COVAR('Daily Returns'!E6:E1242,'Daily Returns'!E6:E1242) -> 0.0010678448 | E7: =COVAR('Daily Returns'!E6:E1242,'Daily Returns'!F6:F1242) -> 0.00056377959 | F7: =COVAR('Daily Returns'!E6:E1242,'Daily Returns'!G6:G1242) -> 0.00016654703 | G7: =COVAR('Daily Returns'!E6:E1242,'Daily Returns'!H6:H1242) -> 0.00026931165 | H7: =COVAR('Daily Returns'!E6:E1242,'Daily Returns'!I6:I1242) -> 0.00018732482 | I7: =COVAR('Daily Returns'!E6:E1242,'Daily Returns'!J6:J1242) -> 0.00015134724 | J7: =COVAR('Daily Returns'!E6:E1242,'Daily Returns'!K6:K1242) -> 0.00011227516 | K7: =COVAR('Daily Returns'!E6:E1242,'Daily Returns'!L6:L1242) -> 0.00022040093 | L7: =COVAR('Daily Returns'!E6:E1242,'Daily Returns'!M6:M1242) -> 0.0001645857
B8: ADANIPOWER | C8: =COVAR('Daily Returns'!F6:F1242,'Daily Returns'!D6:D1242) -> 0.00054189114 | D8: =COVAR('Daily Returns'!F6:F1242,'Daily Returns'!E6:E1242) -> 0.00056377959 | E8: =COVAR('Daily Returns'!F6:F1242,'Daily Returns'!F6:F1242) -> 0.00095923329 | F8: =COVAR('Daily Returns'!F6:F1242,'Daily Returns'!G6:G1242) -> 0.00018850039 | G8: =COVAR('Daily Returns'!F6:F1242,'Daily Returns'!H6:H1242) -> 0.00031093902 | H8: =COVAR('Daily Returns'!F6:F1242,'Daily Returns'!I6:I1242) -> 0.00020465024 | I8: =COVAR('Daily Returns'!F6:F1242,'Daily Returns'!J6:J1242) -> 0.00017684933 | J8: =COVAR('Daily Returns'!F6:F1242,'Daily Returns'!K6:K1242) -> 0.00012283023 | K8: =COVAR('Daily Returns'!F6:F1242,'Daily Returns'!L6:L1242) -> 0.00027014267 | L8: =COVAR('Daily Returns'!F6:F1242,'Daily Returns'!M6:M1242) -> 0.00015544585
B9: CESC | C9: =COVAR('Daily Returns'!G6:G1242,'Daily Returns'!D6:D1242) -> 0.00017403346 | D9: =COVAR('Daily Returns'!G6:G1242,'Daily Returns'!E6:E1242) -> 0.00016654703 | E9: =COVAR('Daily Returns'!G6:G1242,'Daily Returns'!F6:F1242) -> 0.00018850039 | F9: =COVAR('Daily Returns'!G6:G1242,'Daily Returns'!G6:G1242) -> 0.00041662304 | G9: =COVAR('Daily Returns'!G6:G1242,'Daily Returns'!H6:H1242) -> 0.00020259745 | H9: =COVAR('Daily Returns'!G6:G1242,'Daily Returns'!I6:I1242) -> 0.00019170952 | I9: =COVAR('Daily Returns'!G6:G1242,'Daily Returns'!J6:J1242) -> 0.00014684815 | J9: =COVAR('Daily Returns'!G6:G1242,'Daily Returns'!K6:K1242) -> 0.00012017271 | K9: =COVAR('Daily Returns'!G6:G1242,'Daily Returns'!L6:L1242) -> 0.00020842412 | L9: =COVAR('Daily Returns'!G6:G1242,'Daily Returns'!M6:M1242) -> 0.00014732932
B10: JSWENERGY | C10: =COVAR('Daily Returns'!H6:H1242,'Daily Returns'!D6:D1242) -> 0.00024284038 | D10: =COVAR('Daily Returns'!H6:H1242,'Daily Returns'!E6:E1242) -> 0.00026931165 | E10: =COVAR('Daily Returns'!H6:H1242,'Daily Returns'!F6:F1242) -> 0.00031093902 | F10: =COVAR('Daily Returns'!H6:H1242,'Daily Returns'!G6:G1242) -> 0.00020259745 | G10: =COVAR('Daily Returns'!H6:H1242,'Daily Returns'!H6:H1242) -> 0.00070311825 | H10: =COVAR('Daily Returns'!H6:H1242,'Daily Returns'!I6:I1242) -> 0.00020098788 | I10: =COVAR('Daily Returns'!H6:H1242,'Daily Returns'!J6:J1242) -> 0.0001703087 | J10: =COVAR('Daily Returns'!H6:H1242,'Daily Returns'!K6:K1242) -> 0.00015114725 | K10: =COVAR('Daily Returns'!H6:H1242,'Daily Returns'!L6:L1242) -> 0.00025773581 | L10: =COVAR('Daily Returns'!H6:H1242,'Daily Returns'!M6:M1242) -> 0.0001973224
B11: NHPC | C11: =COVAR('Daily Returns'!I6:I1242,'Daily Returns'!D6:D1242) -> 0.00018853735 | D11: =COVAR('Daily Returns'!I6:I1242,'Daily Returns'!E6:E1242) -> 0.00018732482 | E11: =COVAR('Daily Returns'!I6:I1242,'Daily Returns'!F6:F1242) -> 0.00020465024 | F11: =COVAR('Daily Returns'!I6:I1242,'Daily Returns'!G6:G1242) -> 0.00019170952 | G11: =COVAR('Daily Returns'!I6:I1242,'Daily Returns'!H6:H1242) -> 0.00020098788 | H11: =COVAR('Daily Returns'!I6:I1242,'Daily Returns'!I6:I1242) -> 0.00046272259 | I11: =COVAR('Daily Returns'!I6:I1242,'Daily Returns'!J6:J1242) -> 0.00014351983 | J11: =COVAR('Daily Returns'!I6:I1242,'Daily Returns'!K6:K1242) -> 0.00012353265 | K11: =COVAR('Daily Returns'!I6:I1242,'Daily Returns'!L6:L1242) -> 0.00021577582 | L11: =COVAR('Daily Returns'!I6:I1242,'Daily Returns'!M6:M1242) -> 0.00015393496
B12: NTPC | C12: =COVAR('Daily Returns'!J6:J1242,'Daily Returns'!D6:D1242) -> 0.00016084264 | D12: =COVAR('Daily Returns'!J6:J1242,'Daily Returns'!E6:E1242) -> 0.00015134724 | E12: =COVAR('Daily Returns'!J6:J1242,'Daily Returns'!F6:F1242) -> 0.00017684933 | F12: =COVAR('Daily Returns'!J6:J1242,'Daily Returns'!G6:G1242) -> 0.00014684815 | G12: =COVAR('Daily Returns'!J6:J1242,'Daily Returns'!H6:H1242) -> 0.0001703087 | H12: =COVAR('Daily Returns'!J6:J1242,'Daily Returns'!I6:I1242) -> 0.00014351983 | I12: =COVAR('Daily Returns'!J6:J1242,'Daily Returns'!J6:J1242) -> 0.00024842934 | J12: =COVAR('Daily Returns'!J6:J1242,'Daily Returns'!K6:K1242) -> 0.00014917565 | K12: =COVAR('Daily Returns'!J6:J1242,'Daily Returns'!L6:L1242) -> 0.00017837228 | L12: =COVAR('Daily Returns'!J6:J1242,'Daily Returns'!M6:M1242) -> 0.0001408339
B13: POWERGRID | C13: =COVAR('Daily Returns'!K6:K1242,'Daily Returns'!D6:D1242) -> 0.00013554785 | D13: =COVAR('Daily Returns'!K6:K1242,'Daily Returns'!E6:E1242) -> 0.00011227516 | E13: =COVAR('Daily Returns'!K6:K1242,'Daily Returns'!F6:F1242) -> 0.00012283023 | F13: =COVAR('Daily Returns'!K6:K1242,'Daily Returns'!G6:G1242) -> 0.00012017271 | G13: =COVAR('Daily Returns'!K6:K1242,'Daily Returns'!H6:H1242) -> 0.00015114725 | H13: =COVAR('Daily Returns'!K6:K1242,'Daily Returns'!I6:I1242) -> 0.00012353265 | I13: =COVAR('Daily Returns'!K6:K1242,'Daily Returns'!J6:J1242) -> 0.00014917565 | J13: =COVAR('Daily Returns'!K6:K1242,'Daily Returns'!K6:K1242) -> 0.00025205249 | K13: =COVAR('Daily Returns'!K6:K1242,'Daily Returns'!L6:L1242) -> 0.00014627114 | L13: =COVAR('Daily Returns'!K6:K1242,'Daily Returns'!M6:M1242) -> 0.00011000832
B14: TATAPOWER | C14: =COVAR('Daily Returns'!L6:L1242,'Daily Returns'!D6:D1242) -> 0.00021912302 | D14: =COVAR('Daily Returns'!L6:L1242,'Daily Returns'!E6:E1242) -> 0.00022040093 | E14: =COVAR('Daily Returns'!L6:L1242,'Daily Returns'!F6:F1242) -> 0.00027014267 | F14: =COVAR('Daily Returns'!L6:L1242,'Daily Returns'!G6:G1242) -> 0.00020842412 | G14: =COVAR('Daily Returns'!L6:L1242,'Daily Returns'!H6:H1242) -> 0.00025773581 | H14: =COVAR('Daily Returns'!L6:L1242,'Daily Returns'!I6:I1242) -> 0.00021577582 | I14: =COVAR('Daily Returns'!L6:L1242,'Daily Returns'!J6:J1242) -> 0.00017837228 | J14: =COVAR('Daily Returns'!L6:L1242,'Daily Returns'!K6:K1242) -> 0.00014627114 | K14: =COVAR('Daily Returns'!L6:L1242,'Daily Returns'!L6:L1242) -> 0.00041570641 | L14: =COVAR('Daily Returns'!L6:L1242,'Daily Returns'!M6:M1242) -> 0.00020510326
B15: TORNTPOWER | C15: =COVAR('Daily Returns'!M6:M1242,'Daily Returns'!D6:D1242) -> 0.00017374417 | D15: =COVAR('Daily Returns'!M6:M1242,'Daily Returns'!E6:E1242) -> 0.0001645857 | E15: =COVAR('Daily Returns'!M6:M1242,'Daily Returns'!F6:F1242) -> 0.00015544585 | F15: =COVAR('Daily Returns'!M6:M1242,'Daily Returns'!G6:G1242) -> 0.00014732932 | G15: =COVAR('Daily Returns'!M6:M1242,'Daily Returns'!H6:H1242) -> 0.0001973224 | H15: =COVAR('Daily Returns'!M6:M1242,'Daily Returns'!I6:I1242) -> 0.00015393496 | I15: =COVAR('Daily Returns'!M6:M1242,'Daily Returns'!J6:J1242) -> 0.0001408339 | J15: =COVAR('Daily Returns'!M6:M1242,'Daily Returns'!K6:K1242) -> 0.00011000832 | K15: =COVAR('Daily Returns'!M6:M1242,'Daily Returns'!L6:L1242) -> 0.00020510326 | L15: =COVAR('Daily Returns'!M6:M1242,'Daily Returns'!M6:M1242) -> 0.00051350337

Sheet Markowitz Optimisation
B2: Portfolio 3: Efficient Markowitz Portfolio
B3: Objective: maximise the Sharpe ratio, subject to weights summing to 100%, no short-selling (weights >= 0) and no borrowing (weights <= 1). Solved using Python/SciPy SLSQP on the 1,237-day covariance matrix and mean daily returns - mathematically equivalent to Excel Solver's GRG Nonlinear engine on the same objective and constraints. NOT run inside Excel Solver itself; open Data > Solver with the objective/constraint cells below to verify or re-optimise for the viva.
B6: Solver Setup (replicate this in Excel Data > Solver)
B7: Objective cell | C7: F1273 (Sharpe ratio) - Set to: Max
B8: By changing variable cells | C8: C16:C25 (portfolio weights)
B9: Constraint 1 | C9: C26 = 1
B10: Constraint 2 | C10: C16:C25 >= 0 (no short-selling)
B11: Constraint 3 | C11: C16:C25 <= 1 (no borrowing / leverage)
B12: Solving method | C12: GRG Nonlinear
B15: Company | C15: Optimal Weight
B16: Adani Energy Solutions | C16: 0
B17: Adani Green | C17: 0
B18: Adani Power | C18: 0.3756
B19: CESC | C19: 0
B20: JSW Energy | C20: 0
B21: NHPC | C21: 0.1225
B22: NTPC | C22: 0.2282
B23: Power Grid | C23: 0.1287
B24: Tata Power | C24: 0
B25: Torrent Power | C25: 0.1451
B26: TOTAL | C26: =SUM(C16:C25) -> 1.0001
B28: (helper row - weights mirrored horizontally) | D28: =C16 -> 0 | E28: =C17 -> 0 | F28: =C18 -> 0.3756 | G28: =C19 -> 0 | H28: =C20 -> 0 | I28: =C21 -> 0.1225 | J28: =C22 -> 0.2282 | K28: =C23 -> 0.1287 | L28: =C24 -> 0 | M28: =C25 -> 0.1451
E29: Date | F29: Portfolio Daily Return
E30: ='Daily Returns'!B6 -> 44460 | F30: =SUMPRODUCT($D$28:$M$28,'Daily Returns'!D6:M6) -> -0.0019823817
E31: ='Daily Returns'!B7 -> 44461 | F31: =SUMPRODUCT($D$28:$M$28,'Daily Returns'!D7:M7) -> 0.0064433329
E32: ='Daily Returns'!B8 -> 44462 | F32: =SUMPRODUCT($D$28:$M$28,'Daily Returns'!D8:M8) -> 0.011564987
E33: ='Daily Returns'!B9 -> 44463 | F33: =SUMPRODUCT($D$28:$M$28,'Daily Returns'!D9:M9) -> -0.0078072749
E34: ='Daily Returns'!B10 -> 44466 | F34: =SUMPRODUCT($D$28:$M$28,'Daily Returns'!D10:M10) -> 0.0072331229
E35: ='Daily Returns'!B11 -> 44467 | F35: =SUMPRODUCT($D$28:$M$28,'Daily Returns'!D11:M11) -> 0.015992174
E36: ='Daily Returns'!B12 -> 44468 | F36: =SUMPRODUCT($D$28:$M$28,'Daily Returns'!D12:M12) -> 0.03993115
E37: ='Daily Returns'!B13 -> 44469 | F37: =SUMPRODUCT($D$28:$M$28,'Daily Returns'!D13:M13) -> -0.0069260677
E38: ='Daily Returns'!B14 -> 44470 | F38: =SUMPRODUCT($D$28:$M$28,'Daily Returns'!D14:M14) -> -0.006522254
E39: ='Daily Returns'!B15 -> 44473 | F39: =SUMPRODUCT($D$28:$M$28,'Daily Returns'!D15:M15) -> 0.030550958
E40: ='Daily Returns'!B16 -> 44474 | F40: =SUMPRODUCT($D$28:$M$28,'Daily Returns'!D16:M16) -> 0.021430346
E41: ='Daily Returns'!B17 -> 44475 | F41: =SUMPRODUCT($D$28:$M$28,'Daily Returns'!D17:M17) -> -0.024396841
... E95: ='Daily Returns'!B71 -> 44554 | F95: =SUMPRODUCT($D$28:$M$28,'Daily Returns'!D71:M71) -> -0.014862539
B96: Efficient Frontier (illustrative, 6 points) | E96: ='Daily Returns'!B72 -> 44557 | F96: =SUMPRODUCT($D$28:$M$28,'Daily Returns'!D72:M72) -> 0.0046542345
B97: Target Ann. Return | C97: Ann. Std Dev (Risk) | E97: ='Daily Returns'!B73 -> 44558 | F97: =SUMPRODUCT($D$28:$M$28,'Daily Returns'!D73:M73) -> 0.015095025
B98: 0.24377825 | C98: 0.21123595 | E98: ='Daily Returns'!B74 -> 44559 | F98: =SUMPRODUCT($D$28:$M$28,'Daily Returns'!D74:M74) -> -0.0087189721
B99: 0.33095328 | C99: 0.22957764 | E99: ='Daily Returns'!B75 -> 44560 | F99: =SUMPRODUCT($D$28:$M$28,'Daily Returns'!D75:M75) -> 0.010500327
B100: 0.42369683 | C100: 0.2760375 | E100: ='Daily Returns'!B76 -> 44561 | F100: =SUMPRODUCT($D$28:$M$28,'Daily Returns'!D76:M76) -> -0.004133633
B101: 0.5223304 | C101: 0.33934905 | E101: ='Daily Returns'!B77 -> 44564 | F101: =SUMPRODUCT($D$28:$M$28,'Daily Returns'!D77:M77) -> 0.010736278
B102: 0.62719211 | C102: 0.41196375 | E102: ='Daily Returns'!B78 -> 44565 | F102: =SUMPRODUCT($D$28:$M$28,'Daily Returns'!D78:M78) -> 0.017872102
B103: 0.73863747 | C103: 0.49093985 | E103: ='Daily Returns'!B79 -> 44566 | F103: =SUMPRODUCT($D$28:$M$28,'Daily Returns'!D79:M79) -> -0.005884672
E104: ='Daily Returns'!B80 -> 44567 | F104: =SUMPRODUCT($D$28:$M$28,'Daily Returns'!D80:M80) -> -0.00086437771
E105: ='Daily Returns'!B81 -> 44568 | F105: =SUMPRODUCT($D$28:$M$28,'Daily Returns'!D81:M81) -> 1.7329385e-05
E106: ='Daily Returns'!B82 -> 44571 | F106: =SUMPRODUCT($D$28:$M$28,'Daily Returns'!D82:M82) -> 0.033377739
E107: ='Daily Returns'!B83 -> 44572 | F107: =SUMPRODUCT($D$28:$M$28,'Daily Returns'!D83:M83) -> -0.00024840029
E108: ='Daily Returns'!B84 -> 44573 | F108: =SUMPRODUCT($D$28:$M$28,'Daily Returns'!D84:M84) -> 0.040675445
E109: ='Daily Returns'!B85 -> 44574 | F109: =SUMPRODUCT($D$28:$M$28,'Daily Returns'!D85:M85) -> -0.0033184456
E110: ='Daily Returns'!B86 -> 44575 | F110: =SUMPRODUCT($D$28:$M$28,'Daily Returns'!D86:M86) -> 0.00096019872
E111: ='Daily Returns'!B87 -> 44578 | F111: =SUMPRODUCT($D$28:$M$28,'Daily Returns'!D87:M87) -> -0.00106685
E112: ='Daily Returns'!B88 -> 44579 | F112: =SUMPRODUCT($D$28:$M$28,'Daily Returns'!D88:M88) -> -0.027974508
E113: ='Daily Returns'!B89 -> 44580 | F113: =SUMPRODUCT($D$28:$M$28,'Daily Returns'!D89:M89) -> 0.012306283
E114: ='Daily Returns'!B90 -> 44581 | F114: =SUMPRODUCT($D$28:$M$28,'Daily Returns'!D90:M90) -> 0.0066620555
E115: ='Daily Returns'!B91 -> 44582 | F115: =SUMPRODUCT($D$28:$M$28,'Daily Returns'!D91:M91) -> -0.02018832
... E1266: ='Daily Returns'!B1242 -> 46281 | F1266: =SUMPRODUCT($D$28:$M$28,'Daily Returns'!D1242:M1242) -> -0.0027387529
E1268: Risk-Free Rate (annual, 91-day T-Bill) | F1268: 0.053
E1269: Average Daily Return | F1269: =AVERAGE(F30:F1266) -> 0.0015546487
E1270: Annualised Return (compounded, 252 days) | F1270: =(1+F1269)^252-1 -> 0.47914949
E1271: Daily Std. Dev. | F1271: =STDEV(F30:F1266) -> 0.01696998
E1272: Annualised Std. Dev. | F1272: =F1271*SQRT(252) -> 0.26939008
E1273: Sharpe Ratio (objective cell) | F1273: =(F1270-F1268)/F1272 -> 1.5819049
B1275: Efficient Frontier (illustrative, 6 points, daily-basis)
B1276: Target Ann. Return | C1276: Ann. Std Dev (Risk)
B1277: 0.28753819 | C1277: 0.25033414
B1278: 0.3635224 | C1278: 0.2562195
B1279: 0.443972 | C1279: 0.27255704
B1280: 0.52914828 | C1280: 0.30506783
B1281: 0.6193278 | C1281: 0.35780652
B1282: 0.7148032 | C1282: 0.41857648

Sheet Portfolio 4 - Benchmark
B2: Portfolio 4: Benchmark Portfolio
B3: Uses the benchmark daily return series from the Daily Returns sheet, labelled 'Nifty Power (Energy)'. FLAGGED: this series' price level matches the Nifty Energy Index, not the Nifty Power Index that the 10 selected companies more closely track - confirm the allocated benchmark before final submission (see Data Sources & Assumptions).
B5: Date | C5: Benchmark Daily Return
B6: ='Daily Returns'!B6 -> 44460 | C6: ='Daily Returns'!C6 -> 0.0052348864
B7: ='Daily Returns'!B7 -> 44461 | C7: ='Daily Returns'!C7 -> 0.0081947994
B8: ='Daily Returns'!B8 -> 44462 | C8: ='Daily Returns'!C8 -> 0.018326221
B9: ='Daily Returns'!B9 -> 44463 | C9: ='Daily Returns'!C9 -> -0.0080755484
B10: ='Daily Returns'!B10 -> 44466 | C10: ='Daily Returns'!C10 -> 0.013335513
B11: ='Daily Returns'!B11 -> 44467 | C11: ='Daily Returns'!C11 -> 0.02014446
B12: ='Daily Returns'!B12 -> 44468 | C12: ='Daily Returns'!C12 -> 0.018494968
B13: ='Daily Returns'!B13 -> 44469 | C13: ='Daily Returns'!C13 -> -0.00026241496
B14: ='Daily Returns'!B14 -> 44470 | C14: ='Daily Returns'!C14 -> 0.006196806
B15: ='Daily Returns'!B15 -> 44473 | C15: ='Daily Returns'!C15 -> 0.014539004
B16: ='Daily Returns'!B16 -> 44474 | C16: ='Daily Returns'!C16 -> 0.028779152
B17: ='Daily Returns'!B17 -> 44475 | C17: ='Daily Returns'!C17 -> -0.0045050956
... B1242: ='Daily Returns'!B1242 -> 46281 | C1242: ='Daily Returns'!C1242 -> 0.00095429223
B1244: Average Daily Return | C1244: =AVERAGE(C6:C1242) -> 0.00053116448
B1245: Annualised Return (compounded, 252 days) | C1245: =(1+C1244)^252-1 -> 0.14318464
B1246: Daily Std. Dev. | C1246: =STDEV(C6:C1242) -> 0.012390123
B1247: Annualised Std. Dev. | C1247: =C1246*SQRT(252) -> 0.1966871

Sheet Portfolio 5 - Mutual Fund 1
B2: Portfolio 5: Comparable Mutual Fund Scheme 1
B3: Selected because it is one of the longest-running (since 2004) power & infrastructure sectoral funds in India, giving a genuine 5-year track record comparable to the analysis period, and its top holdings overlap materially with the 10 selected companies (NTPC, Tata Power).
B5: Scheme name | C5: Nippon India Power & Infra Fund - Growth
B6: Fund house | C6: Nippon India Mutual Fund
B7: Investment objective | C7: Long-term capital appreciation by investing in power and allied infrastructure sector companies
B8: Launch date | C8: 08-May-2004
B9: AUM (Rs Cr, approx.) | C9: 8043 | D9: share.market, Jul-2026
B10: Top holdings | C10: Reliance Industries, NTPC, Bharti Airtel, L&T, Tata Power | D10: share.market, Jul-2026
B11: 5-Year CAGR | C11: 0.2263 | D11: share.market, Jul-2026
B12: 1-Year Return
B14: THIRD-PARTY RISK METRICS (not computed on the same daily/5-yr basis as Portfolios 1-4)
B15: Annualised Std. Dev. (3-yr, provider-computed) | C15: 0.1787
B16: Beta (3-yr, vs provider benchmark) | C16: 1.03
B17: Sharpe Ratio (3-yr, provider-computed) | C17: 1.13
B18: Alpha (3-yr, provider-computed) | C18: 0.0331
B19: Treynor Ratio (our 5-yr CAGR & Rf, provider's beta - mixed-source) | C19: =(C11-0.053)/C16 -> 0.16825243
B20: Source: advisorkhoj.com, Nippon India Power & Infra Fund - Growth Plan, retrieved Sep-2026. These figures use the provider's own methodology (typically 3-year, monthly-return basis and their own risk-free assumption) - NOT the same 5-year daily-return, 91-day-T-Bill basis used for Portfolios 1-4. Shown to satisfy the Dashboard's completeness requirement, but not strictly like-for-like comparable to the other four portfolios. A fully consistent comparison would require downloading this fund's actual daily/monthly NAV history.

Sheet Portfolio 6 - Mutual Fund 2
B2: Portfolio 6: Comparable Mutual Fund Scheme 2
B3: Selected as a second comparable scheme with meaningful power-sector exposure (Adani Power and Adani Energy Solutions are top-10 holdings), though its mandate is broader (Resources & Energy, including cement, steel and metals) than a pure power play - a disclosed limitation, not full sector overlap with the benchmark.
B5: Scheme name | C5: Tata Resources & Energy Fund - Growth
B6: Fund house | C6: Tata Mutual Fund
B7: Investment objective | C7: Long-term capital appreciation by investing at least 80% of net assets in equity/equity-related instruments of Resources & Energy sector companies
B8: Launch date | C8: 04-Dec-2015
B9: AUM (Rs Cr, approx.) | C9: 1361 | D9: share.market, Jul-2026
B10: Top holdings | C10: UltraTech Cement, Ambuja Cements, Tata Steel, Adani Power, Adani Energy Solutions | D10: share.market, Jul-2026
B11: 5-Year CAGR | C11: 0.13 | D11: share.market, Jul-2026
B12: Expense Ratio | C12: 0.0212 | D12: equiruswealth.com, Jan-2026
B14: THIRD-PARTY RISK METRICS (not computed on the same daily/5-yr basis as Portfolios 1-4)
B15: Annualised Std. Dev. (3-yr, provider-computed) | C15: 0.1721
B16: Beta (3-yr, vs provider benchmark) | C16: 0.84
B17: Sharpe Ratio (3-yr, provider-computed) | C17: 0.28
B18: Alpha (3-yr, provider-computed) | C18: -0.0051
B19: Treynor Ratio (our 5-yr CAGR & Rf, provider's beta - mixed-source) | C19: =(C11-0.053)/C16 -> 0.091666667
B20: Source: advisorkhoj.com, Tata Resources & Energy Fund - Regular Plan Growth, retrieved Sep-2026. These figures use the provider's own methodology (typically 3-year, monthly-return basis and their own risk-free assumption) - NOT the same 5-year daily-return, 91-day-T-Bill basis used for Portfolios 1-4. Shown to satisfy the Dashboard's completeness requirement, but not strictly like-for-like comparable to the other four portfolios. A fully consistent comparison would require downloading this fund's actual daily/monthly NAV history.

Sheet Portfolio Performance
B2: Comparative Performance - All Six Portfolios
B3: Beta = COVAR(portfolio returns, benchmark returns) / VAR(benchmark returns), computed on DAILY returns (1,237 observations). Sharpe = (Ann. Return - Rf) / Ann. Std Dev. Treynor = (Ann. Return - Rf) / Beta. Jensen Alpha = Actual Return - [Rf + Beta x (Benchmark Return - Rf)]. Risk-free rate = 5.30% p.a. (91-day T-Bill, Aug-2026). Annualisation: (1+avg daily return)^252 - 1 for return; daily SD x SQRT(252) for risk. Portfolios 5 and 6 (mutual funds) show only the reported 5-year CAGR - no daily NAV series was available for them.
B5: Portfolio | C5: Ann. Return (CAGR proxy) | D5: Ann. Std Dev (Risk) | E5: Beta | F5: Sharpe Ratio | G5: Treynor Ratio | H5: Jensen's Alpha
B6: 1. Equal Weighted | C6: ='Portfolio 1 - Equal Weight'!F1245 -> 0.28753819 | D6: ='Portfolio 1 - Equal Weight'!F1247 -> 0.25033414 | E6: =COVAR('Portfolio 1 - Equal Weight'!F6:F1242,'Portfolio 4 - Benchmark'!C6:C1242)/VAR('Portfolio 4 - Benchmark'!C6:C1242) -> 0.42812329 | F6: =(C6-0.053)/D6 -> 0.93690056 | G6: =(C6-0.053)/E6 -> 0.54782861 | H6: =C6-(0.053+E6*('Portfolio 4 - Benchmark'!C1245-0.053)) -> 0.19592805
B7: 2. Criteria-Based (Composite Score) | C7: ='Portfolio 2 - Criteria Based'!F1245 -> 0.32016421 | D7: ='Portfolio 2 - Criteria Based'!F1247 -> 0.2458992 | E7: =COVAR('Portfolio 2 - Criteria Based'!F6:F1242,'Portfolio 4 - Benchmark'!C6:C1242)/VAR('Portfolio 4 - Benchmark'!C6:C1242) -> 0.40968806 | F7: =(C7-0.053)/D7 -> 1.0864786 | G7: =(C7-0.053)/E7 -> 0.65211617 | H7: =C7-(0.053+E7*('Portfolio 4 - Benchmark'!C1245-0.053)) -> 0.23021664
B8: 3. Markowitz (Max Sharpe) | C8: ='Markowitz Optimisation'!F1270 -> 0.47914949 | D8: ='Markowitz Optimisation'!F1272 -> 0.26939008 | E8: =COVAR('Markowitz Optimisation'!F30:F1266,'Portfolio 4 - Benchmark'!C6:C1242)/VAR('Portfolio 4 - Benchmark'!C6:C1242) -> 0.39150566 | F8: =(C8-0.053)/D8 -> 1.5819049 | G8: =(C8-0.053)/E8 -> 1.0884887 | H8: =C8-(0.053+E8*('Portfolio 4 - Benchmark'!C1245-0.053)) -> 0.39084169
B9: 4. Benchmark (Nifty Power/Energy - flagged) | C9: ='Portfolio 4 - Benchmark'!C1245 -> 0.14318464 | D9: ='Portfolio 4 - Benchmark'!C1247 -> 0.1966871 | E9: =COVAR('Portfolio 4 - Benchmark'!C6:C1242,'Portfolio 4 - Benchmark'!C6:C1242)/VAR('Portfolio 4 - Benchmark'!C6:C1242) -> 0.99919159 | F9: =(C9-0.053)/D9 -> 0.45851833 | G9: =(C9-0.053)/E9 -> 0.090257605 | H9: =C9-(0.053+E9*('Portfolio 4 - Benchmark'!C1245-0.053)) -> 7.2905934e-05
B10: 5. Mutual Fund 1 - Nippon India Power & Infra | C10: ='Portfolio 5 - Mutual Fund 1'!C11 -> 0.2263 | D10: ='Portfolio 5 - Mutual Fund 1'!C15 -> 0.1787 | E10: ='Portfolio 5 - Mutual Fund 1'!C16 -> 1.03 | F10: ='Portfolio 5 - Mutual Fund 1'!C17 -> 1.13 | G10: ='Portfolio 5 - Mutual Fund 1'!C19 -> 0.16825243 | H10: ='Portfolio 5 - Mutual Fund 1'!C18 -> 0.0331
B11: 6. Mutual Fund 2 - Tata Resources & Energy | C11: ='Portfolio 6 - Mutual Fund 2'!C11 -> 0.13 | D11: ='Portfolio 6 - Mutual Fund 2'!C15 -> 0.1721 | E11: ='Portfolio 6 - Mutual Fund 2'!C16 -> 0.84 | F11: ='Portfolio 6 - Mutual Fund 2'!C17 -> 0.28 | G11: ='Portfolio 6 - Mutual Fund 2'!C19 -> 0.091666667 | H11: ='Portfolio 6 - Mutual Fund 2'!C18 -> -0.0051

Sheet Returns & Ratios
B2: Return-wise Calculation (Daily Basis): Periodic Returns -> Cumulative Return -> CAGR -> Risk-Adjusted Ratios
B3: Self-contained sheet: pulls each portfolio's DAILY return from its own sheet, builds a Rs 100 cumulative value index day by day (1,237 trading days, 21-Sep-2021 to 16-Sep-2026), then derives Cumulative Return, CAGR, Annualised Return, Annualised Risk, Beta, Sharpe, Treynor and Jensen's Alpha from that index and return series.
B5: A. Daily Returns and Cumulative Value Index (Rs 100 base)
B7: Date | C7: P1: Equal Weight - Return | D7: P1: Equal Weight - Value Index | E7: P2: Criteria-Based - Return | F7: P2: Criteria-Based - Value Index | G7: P3: Markowitz - Return | H7: P3: Markowitz - Value Index | I7: P4: Benchmark - Return | J7: P4: Benchmark - Value Index
B8: ='Daily Returns'!B6 -> 44460 | C8: ='Portfolio 1 - Equal Weight'!F6 -> -0.0078737931 | D8: =100*(1+C8) -> 99.212621 | E8: ='Portfolio 2 - Criteria Based'!F6 -> -0.0074747346 | F8: =100*(1+E8) -> 99.252527 | G8: ='Markowitz Optimisation'!F30 -> -0.0019823817 | H8: =100*(1+G8) -> 99.801762 | I8: ='Portfolio 4 - Benchmark'!C6 -> 0.0052348864 | J8: =100*(1+I8) -> 100.52349
B9: ='Daily Returns'!B7 -> 44461 | C9: ='Portfolio 1 - Equal Weight'!F7 -> -0.0024220608 | D9: =D8*(1+C9) -> 98.972322 | E9: ='Portfolio 2 - Criteria Based'!F7 -> -0.0010212169 | F9: =F8*(1+E9) -> 99.151168 | G9: ='Markowitz Optimisation'!F31 -> 0.0064433329 | H9: =H8*(1+G9) -> 100.44482 | I9: ='Portfolio 4 - Benchmark'!C7 -> 0.0081947994 | J9: =J8*(1+I9) -> 101.34726
B10: ='Daily Returns'!B8 -> 44462 | C10: ='Portfolio 1 - Equal Weight'!F8 -> 0.013150958 | D10: =D9*(1+C10) -> 100.2739 | E10: ='Portfolio 2 - Criteria Based'!F8 -> 0.012353631 | F10: =F9*(1+E10) -> 100.37605 | G10: ='Markowitz Optimisation'!F32 -> 0.011564987 | H10: =H9*(1+G10) -> 101.60646 | I10: ='Portfolio 4 - Benchmark'!C8 -> 0.018326221 | J10: =J9*(1+I10) -> 103.20457
B11: ='Daily Returns'!B9 -> 44463 | C11: ='Portfolio 1 - Equal Weight'!F9 -> -0.0084675047 | D11: =D10*(1+C11) -> 99.424833 | E11: ='Portfolio 2 - Criteria Based'!F9 -> -0.0091423539 | F11: =F10*(1+E11) -> 99.458372 | G11: ='Markowitz Optimisation'!F33 -> -0.0078072749 | H11: =H10*(1+G11) -> 100.81319 | I11: ='Portfolio 4 - Benchmark'!C9 -> -0.0080755484 | J11: =J10*(1+I11) -> 102.37114
B12: ='Daily Returns'!B10 -> 44466 | C12: ='Portfolio 1 - Equal Weight'!F10 -> 0.00203978 | D12: =D11*(1+C12) -> 99.627638 | E12: ='Portfolio 2 - Criteria Based'!F10 -> 0.0014929421 | F12: =F11*(1+E12) -> 99.606857 | G12: ='Markowitz Optimisation'!F34 -> 0.0072331229 | H12: =H11*(1+G12) -> 101.54239 | I12: ='Portfolio 4 - Benchmark'!C10 -> 0.013335513 | J12: =J11*(1+I12) -> 103.73631
B13: ='Daily Returns'!B11 -> 44467 | C13: ='Portfolio 1 - Equal Weight'!F11 -> 0.014134331 | D13: =D12*(1+C13) -> 101.03581 | E13: ='Portfolio 2 - Criteria Based'!F11 -> 0.013267485 | F13: =F12*(1+E13) -> 100.92839 | G13: ='Markowitz Optimisation'!F35 -> 0.015992174 | H13: =H12*(1+G13) -> 103.16627 | I13: ='Portfolio 4 - Benchmark'!C11 -> 0.02014446 | J13: =J12*(1+I13) -> 105.82602
B14: ='Daily Returns'!B12 -> 44468 | C14: ='Portfolio 1 - Equal Weight'!F12 -> 0.037921793 | D14: =D13*(1+C14) -> 104.86727 | E14: ='Portfolio 2 - Criteria Based'!F12 -> 0.039222541 | F14: =F13*(1+E14) -> 104.88706 | G14: ='Markowitz Optimisation'!F36 -> 0.03993115 | H14: =H13*(1+G14) -> 107.28582 | I14: ='Portfolio 4 - Benchmark'!C12 -> 0.018494968 | J14: =J13*(1+I14) -> 107.78327
B15: ='Daily Returns'!B13 -> 44469 | C15: ='Portfolio 1 - Equal Weight'!F13 -> 0.010823112 | D15: =D14*(1+C15) -> 106.00226 | E15: ='Portfolio 2 - Criteria Based'!F13 -> 0.0082326286 | F15: =F14*(1+E15) -> 105.75055 | G15: ='Markowitz Optimisation'!F37 -> -0.0069260677 | H15: =H14*(1+G15) -> 106.54275 | I15: ='Portfolio 4 - Benchmark'!C13 -> -0.00026241496 | J15: =J14*(1+I15) -> 107.75499
B16: ='Daily Returns'!B14 -> 44470 | C16: ='Portfolio 1 - Equal Weight'!F14 -> -0.0003275499 | D16: =D15*(1+C16) -> 105.96754 | E16: ='Portfolio 2 - Criteria Based'!F14 -> -0.00018375596 | F16: =F15*(1+E16) -> 105.73112 | G16: ='Markowitz Optimisation'!F38 -> -0.006522254 | H16: =H15*(1+G16) -> 105.84785 | I16: ='Portfolio 4 - Benchmark'!C14 -> 0.006196806 | J16: =J15*(1+I16) -> 108.42272
B17: ='Daily Returns'!B15 -> 44473 | C17: ='Portfolio 1 - Equal Weight'!F15 -> 0.019260004 | D17: =D16*(1+C17) -> 108.00847 | E17: ='Portfolio 2 - Criteria Based'!F15 -> 0.020603456 | F17: =F16*(1+E17) -> 107.90955 | G17: ='Markowitz Optimisation'!F39 -> 0.030550958 | H17: =H16*(1+G17) -> 109.0816 | I17: ='Portfolio 4 - Benchmark'!C15 -> 0.014539004 | J17: =J16*(1+I17) -> 109.99908
B18: ='Daily Returns'!B16 -> 44474 | C18: ='Portfolio 1 - Equal Weight'!F16 -> 0.026301847 | D18: =D17*(1+C18) -> 110.84929 | E18: ='Portfolio 2 - Criteria Based'!F16 -> 0.025550457 | F18: =F17*(1+E18) -> 110.66669 | G18: ='Markowitz Optimisation'!F40 -> 0.021430346 | H18: =H17*(1+G18) -> 111.41926 | I18: ='Portfolio 4 - Benchmark'!C16 -> 0.028779152 | J18: =J17*(1+I18) -> 113.16476
B19: ='Daily Returns'!B17 -> 44475 | C19: ='Portfolio 1 - Equal Weight'!F17 -> -0.012295777 | D19: =D18*(1+C19) -> 109.48631 | E19: ='Portfolio 2 - Criteria Based'!F17 -> -0.015222357 | F19: =F18*(1+E19) -> 108.98208 | G19: ='Markowitz Optimisation'!F41 -> -0.024396841 | H19: =H18*(1+G19) -> 108.70098 | I19: ='Portfolio 4 - Benchmark'!C17 -> -0.0045050956 | J19: =J18*(1+I19) -> 112.65494
B20: ='Daily Returns'!B18 -> 44476 | C20: ='Portfolio 1 - Equal Weight'!F18 -> -0.00020149416 | D20: =D19*(1+C20) -> 109.46425 | E20: ='Portfolio 2 - Criteria Based'!F18 -> 0.00020762235 | F20: =F19*(1+E20) -> 109.00471 | G20: ='Markowitz Optimisation'!F42 -> 0.0036264775 | H20: =H19*(1+G20) -> 109.09518 | I20: ='Portfolio 4 - Benchmark'!C18 -> -0.0039166457 | J20: =J19*(1+I20) -> 112.21371
... B1244: ='Daily Returns'!B1242 -> 46281 | C1244: ='Portfolio 1 - Equal Weight'!F1242 -> -0.0013089092 | D1244: =D1243*(1+C1244) -> 296.2402 | E1244: ='Portfolio 2 - Criteria Based'!F1242 -> -0.0015383151 | F1244: =F1243*(1+E1244) -> 336.85011 | G1244: ='Markowitz Optimisation'!F1266 -> -0.0027387529 | H1244: =H1243*(1+G1244) -> 572.07809 | I1244: ='Portfolio 4 - Benchmark'!C1242 -> 0.00095429223 | J1244: =J1243*(1+I1244) -> 175.28219
B1247: B. Risk-Free Rate and Benchmark Reference
B1248: Risk-Free Rate (annual, 91-day T-Bill, Aug-2026) | C1248: 0.053
B1250: C. Return-Wise Ratio Derivation (Portfolios 1-4, Daily Basis)
B1251: Step / Metric | C1251: P1: Equal Weight | D1251: P2: Criteria-Based | E1251: P3: Markowitz | F1251: P4: Benchmark | G1251: Formula used
B1252: 1. Average Daily Return | D1252: =AVERAGE(C8:C1244) -> 0.0010034079 | E1252: =AVERAGE(E8:E1244) -> 0.0011028145 | F1252: =AVERAGE(G8:G1244) -> 0.0015546487 | G1252: =AVERAGE(I8:I1244) -> 0.00053116448
B1253: 2. Cumulative Return (5-Yr) | D1253: =(D1244/100)-1 -> 1.962402 | E1253: =(F1244/100)-1 -> 2.3685011 | F1253: =(H1244/100)-1 -> 4.7207809 | G1253: =(J1244/100)-1 -> 0.75282191
B1254: 3. CAGR (compounded over period) | D1254: =(D1244/100)^(252/1237)-1 -> 0.24762104 | E1254: =(F1244/100)^(252/1237)-1 -> 0.28070382 | F1254: =(H1244/100)^(252/1237)-1 -> 0.42661831 | G1254: =(J1244/100)^(252/1237)-1 -> 0.12112475
B1255: 4. Annualised Return (compounded, x252 days) | D1255: =(1+D1252)^252-1 -> 0.28753819 | E1255: =(1+E1252)^252-1 -> 0.32016421 | F1255: =(1+F1252)^252-1 -> 0.47914949 | G1255: =(1+G1252)^252-1 -> 0.14318464
B1256: 5. Daily Std. Dev. | D1256: =STDEV(C8:C1244) -> 0.015769568 | E1256: =STDEV(E8:E1244) -> 0.015490194 | F1256: =STDEV(G8:G1244) -> 0.01696998 | G1256: =STDEV(I8:I1244) -> 0.012390123
B1257: 6. Annualised Std. Dev. (Risk, x SQRT(252)) | D1257: =D1256*SQRT(252) -> 0.25033414 | E1257: =E1256*SQRT(252) -> 0.2458992 | F1257: =F1256*SQRT(252) -> 0.26939008 | G1257: =G1256*SQRT(252) -> 0.1966871
B1258: 7. Beta (vs Benchmark) | D1258: =COVAR(C8:C1244,$I$8:$I$1244)/VAR($I$8:$I$1244) -> 0.42812329 | E1258: =COVAR(E8:E1244,$I$8:$I$1244)/VAR($I$8:$I$1244) -> 0.40968806 | F1258: =COVAR(G8:G1244,$I$8:$I$1244)/VAR($I$8:$I$1244) -> 0.39150566 | G1258: =COVAR(I8:I1244,$I$8:$I$1244)/VAR($I$8:$I$1244) -> 0.99919159
B1259: 8. Sharpe Ratio | D1259: =(D1255-$C$1248)/D1257 -> 0.93690056 | E1259: =(E1255-$C$1248)/E1257 -> 1.0864786 | F1259: =(F1255-$C$1248)/F1257 -> 1.5819049 | G1259: =(G1255-$C$1248)/G1257 -> 0.45851833
B1260: 9. Treynor Ratio | D1260: =(D1255-$C$1248)/D1258 -> 0.54782861 | E1260: =(E1255-$C$1248)/E1258 -> 0.65211617 | F1260: =(F1255-$C$1248)/F1258 -> 1.0884887 | G1260: =(G1255-$C$1248)/G1258 -> 0.090257605
B1261: 10. Jensen's Alpha | D1261: =D1255-($C$1248+D1258*(G1255-$C$1248)) -> 0.19592805 | E1261: =E1255-($C$1248+E1258*(G1255-$C$1248)) -> 0.23021664 | F1261: =F1255-($C$1248+F1258*(G1255-$C$1248)) -> 0.39084169 | G1261: =G1255-($C$1248+G1258*(G1255-$C$1248)) -> 7.2905934e-05
B1263: D. Portfolios 5 & 6 (Mutual Funds) - Reported CAGR Only
B1264: Portfolio | C1264: 5-Year CAGR (reported) | D1264: Note
B1265: P5: Nippon India Power & Infra Fund | C1265: ='Portfolio 5 - Mutual Fund 1'!C11 -> 0.2263 | D1265: No daily NAV series available - beta/Sharpe/Treynor/Jensen not computed
B1266: P6: Tata Resources & Energy Fund | C1266: ='Portfolio 6 - Mutual Fund 2'!C11 -> 0.13 | D1266: No daily NAV series available - beta/Sharpe/Treynor/Jensen not computed
B1269: E. Quick Ranking (by Sharpe Ratio, Portfolios 1-4) | D1269: P1: Equal Weight | E1269: P2: Criteria-Based | F1269: P3: Markowitz | G1269: P4: Benchmark
B1270: Rank | C1270: Portfolio | D1270: Sharpe Ratio
B1271: 1 | C1271: =INDEX($D$1269:$G$1269,MATCH(LARGE($D$1259:$G$1259,1),$D$1259:$G$1259,0)) -> P3: Markowitz | D1271: =LARGE($D$1259:$G$1259,1) -> 1.5819049
B1272: 2 | C1272: =INDEX($D$1269:$G$1269,MATCH(LARGE($D$1259:$G$1259,2),$D$1259:$G$1259,0)) -> P2: Criteria-Based | D1272: =LARGE($D$1259:$G$1259,2) -> 1.0864786
B1273: 3 | C1273: =INDEX($D$1269:$G$1269,MATCH(LARGE($D$1259:$G$1259,3),$D$1259:$G$1259,0)) -> P1: Equal Weight | D1273: =LARGE($D$1259:$G$1259,3) -> 0.93690056
B1274: 4 | C1274: =INDEX($D$1269:$G$1269,MATCH(LARGE($D$1259:$G$1259,4),$D$1259:$G$1259,0)) -> P4: Benchmark | D1274: =LARGE($D$1259:$G$1259,4) -> 0.45851833

Sheet Investor Recommendations
B2: Recommendations by Investor Profile
B3: Based on the computed performance metrics on the Portfolio Performance sheet, now on a DAILY-return basis (1,237 trading days, annualised x252/SQRT(252)).
B5: Conservative Investor
B6: None of the six portfolios is genuinely low-volatility: even the benchmark carries ~19.7% annualised standard deviation on a daily basis, and every equity portfolio's beta sits at or above roughly 0.35-1.0. Strictly, no single portfolio here is a good fit for a conservative mandate as a full allocation. If one must be chosen, Mutual Fund 2 (Tata Resources & Energy) has the lowest beta (0.84, provider-reported) among all six, though its Sharpe ratio (0.28) is also the weakest, reflecting a genuine return-for-risk trade-off rather than a free lunch. Among the four fully daily-computed portfolios, the Benchmark has the lowest risk (19.7%) and beta (0.99 by construction).
B8: Moderate Investor
B9: The Criteria-Based Portfolio, now weighted using a fixed-threshold fundamental rubric (ROE, ROCE, revenue growth, valuation each scored 1-5 against defined bands, not just ranked against these 10 peers), offers a solid balance: Sharpe ratio of 1.09 versus 0.94 for the Equal-Weighted portfolio, at similar risk (24.6% vs 25.0% annualised standard deviation). The rubric rewards profitable, efficiently-run, reasonably-valued companies like Adani Power and Torrent Power over richly-valued, lower-profitability names like Adani Green and Adani Energy Solutions. This remains a reasonable core holding for a moderate risk-return balance, and the fixed thresholds make the weighting logic defensible independent of which 10 companies happen to be in the sample.
B11: Aggressive Investor
B12: The Markowitz (Max Sharpe) Portfolio delivers the highest annualised return (47.9%) and the highest Sharpe (1.58) and Treynor (1.09) ratios of all six portfolios on the daily-return, 1,237-observation optimisation, concentrating in Adani Power (37.6%), NTPC (22.8%), Power Grid (12.9%), Torrent Power (14.5%) and NHPC (12.3%). This is appropriate only for an investor who accepts the look-ahead/in-sample risk (Section on Limitations) and can tolerate concentration in five names rather than a diversified basket of ten.
B14: Why rankings differ across measures
B15: Sharpe ratio penalises total volatility (including company-specific risk), so it favours the more diversified Criteria-Based portfolio relative to what Treynor alone would suggest. Treynor and Jensen's alpha use beta (systematic risk only), so a concentrated but high-beta portfolio like Markowitz can still rank well on those measures even though its total risk (Sharpe denominator) is higher. This is exactly the kind of divergence the assignment brief asks the group to interpret in the research report.

Sheet Dashboard
B1: Portfolio Management Project - Dashboard
B5: Power sector | Analysis period: 5 years | All figures link live to the underlying sheets
B7: Six-Portfolio Performance Summary
B8: Portfolio | C8: Ann. Return | D8: Ann. Risk (SD) | E8: Beta | F8: Sharpe | G8: Treynor | H8: Jensen's Alpha
B9: ='Portfolio Performance'!B6 -> 1. Equal Weighted | C9: ='Portfolio Performance'!C6 -> 0.28753819 | D9: ='Portfolio Performance'!D6 -> 0.25033414 | E9: ='Portfolio Performance'!E6 -> 0.42812329 | F9: ='Portfolio Performance'!F6 -> 0.93690056 | G9: ='Portfolio Performance'!G6 -> 0.54782861 | H9: ='Portfolio Performance'!H6 -> 0.19592805
B10: ='Portfolio Performance'!B7 -> 2. Criteria-Based (Composite Score) | C10: ='Portfolio Performance'!C7 -> 0.32016421 | D10: ='Portfolio Performance'!D7 -> 0.2458992 | E10: ='Portfolio Performance'!E7 -> 0.40968806 | F10: ='Portfolio Performance'!F7 -> 1.0864786 | G10: ='Portfolio Performance'!G7 -> 0.65211617 | H10: ='Portfolio Performance'!H7 -> 0.23021664
B11: ='Portfolio Performance'!B8 -> 3. Markowitz (Max Sharpe) | C11: ='Portfolio Performance'!C8 -> 0.47914949 | D11: ='Portfolio Performance'!D8 -> 0.26939008 | E11: ='Portfolio Performance'!E8 -> 0.39150566 | F11: ='Portfolio Performance'!F8 -> 1.5819049 | G11: ='Portfolio Performance'!G8 -> 1.0884887 | H11: ='Portfolio Performance'!H8 -> 0.39084169
B12: ='Portfolio Performance'!B9 -> 4. Benchmark (Nifty Power/Energy - flagged) | C12: ='Portfolio Performance'!C9 -> 0.14318464 | D12: ='Portfolio Performance'!D9 -> 0.1966871 | E12: ='Portfolio Performance'!E9 -> 0.99919159 | F12: ='Portfolio Performance'!F9 -> 0.45851833 | G12: ='Portfolio Performance'!G9 -> 0.090257605 | H12: ='Portfolio Performance'!H9 -> 7.2905934e-05
B13: ='Portfolio Performance'!B10 -> 5. Mutual Fund 1 - Nippon India Power & Infra | C13: ='Portfolio Performance'!C10 -> 0.2263 | D13: ='Portfolio Performance'!D10 -> 0.1787 | E13: ='Portfolio Performance'!E10 -> 1.03 | F13: ='Portfolio Performance'!F10 -> 1.13 | G13: ='Portfolio Performance'!G10 -> 0.16825243 | H13: ='Portfolio Performance'!H10 -> 0.0331
B14: ='Portfolio Performance'!B11 -> 6. Mutual Fund 2 - Tata Resources & Energy | C14: ='Portfolio Performance'!C11 -> 0.13 | D14: ='Portfolio Performance'!D11 -> 0.1721 | E14: ='Portfolio Performance'!E11 -> 0.84 | F14: ='Portfolio Performance'!F11 -> 0.28 | G14: ='Portfolio Performance'!G11 -> 0.091666667 | H14: ='Portfolio Performance'!H11 -> -0.0051
B17: Company Weights Across the 3 Constructed Portfolios
B18: Company | C18: Equal Weight | D18: Criteria-Based | E18: Markowitz (Max Sharpe)
B19: Adani Energy Solutions | C19: ='Portfolio 1 - Equal Weight'!C6 -> 0.1 | D19: ='Portfolio 2 - Criteria Based'!C6 -> 0.070175439 | E19: ='Markowitz Optimisation'!C16 -> 0
B20: Adani Green | C20: ='Portfolio 1 - Equal Weight'!C7 -> 0.1 | D20: ='Portfolio 2 - Criteria Based'!C7 -> 0.080701754 | E20: ='Markowitz Optimisation'!C17 -> 0
B21: Adani Power | C21: ='Portfolio 1 - Equal Weight'!C8 -> 0.1 | D21: ='Portfolio 2 - Criteria Based'!C8 -> 0.14385965 | E21: ='Markowitz Optimisation'!C18 -> 0.3756
B22: CESC | C22: ='Portfolio 1 - Equal Weight'!C9 -> 0.1 | D22: ='Portfolio 2 - Criteria Based'!C9 -> 0.1122807 | E22: ='Markowitz Optimisation'!C19 -> 0
B23: JSW Energy | C23: ='Portfolio 1 - Equal Weight'!C10 -> 0.1 | D23: ='Portfolio 2 - Criteria Based'!C10 -> 0.054385965 | E23: ='Markowitz Optimisation'!C20 -> 0
B24: NHPC | C24: ='Portfolio 1 - Equal Weight'!C11 -> 0.1 | D24: ='Portfolio 2 - Criteria Based'!C11 -> 0.085964912 | E24: ='Markowitz Optimisation'!C21 -> 0.1225
B25: NTPC | C25: ='Portfolio 1 - Equal Weight'!C12 -> 0.1 | D25: ='Portfolio 2 - Criteria Based'!C12 -> 0.10350877 | E25: ='Markowitz Optimisation'!C22 -> 0.2282
B26: Power Grid | C26: ='Portfolio 1 - Equal Weight'!C13 -> 0.1 | D26: ='Portfolio 2 - Criteria Based'!C13 -> 0.11403509 | E26: ='Markowitz Optimisation'!C23 -> 0.1287
B27: Tata Power | C27: ='Portfolio 1 - Equal Weight'!C14 -> 0.1 | D27: ='Portfolio 2 - Criteria Based'!C14 -> 0.098245614 | E27: ='Markowitz Optimisation'!C24 -> 0
B28: Torrent Power | C28: ='Portfolio 1 - Equal Weight'!C15 -> 0.1 | D28: ='Portfolio 2 - Criteria Based'!C15 -> 0.13684211 | E28: ='Markowitz Optimisation'!C25 -> 0.1451
B31: Fundamental Indicators - 10 Companies
B32: Company | C32: P/E (x) | D32: ROE % | E32: ROCE %
B33: Adani Energy Solutions | C33: ='Fundamental Analysis'!E6 -> 180.9 | D33: ='Fundamental Analysis'!H6 -> 0.0403 | E33: ='Fundamental Analysis'!I6 -> 0.0529
B34: Adani Green | C34: ='Fundamental Analysis'!E7 -> 313 | D34: ='Fundamental Analysis'!H7 -> 0.071 | E34: ='Fundamental Analysis'!I7 -> 0.0598
B35: Adani Power | C35: ='Fundamental Analysis'!E8 -> 28.2 | D35: ='Fundamental Analysis'!H8 -> 0.211 | E35: ='Fundamental Analysis'!I8 -> 0.172
B36: CESC | C36: ='Fundamental Analysis'!E9 -> 16.6 | D36: ='Fundamental Analysis'!H9 -> 0.117 | E36: ='Fundamental Analysis'!I9 -> 0.109
B37: JSW Energy | C37: ='Fundamental Analysis'!E10 -> 99.3 | D37: ='Fundamental Analysis'!H10 -> 0.0624 | E37: ='Fundamental Analysis'!I10 -> 0.0582
B38: NHPC | C38: ='Fundamental Analysis'!E11 -> 29.6 | D38: ='Fundamental Analysis'!H11 -> 0.0961 | E38: ='Fundamental Analysis'!I11 -> 0.0767
B39: NTPC | C39: ='Fundamental Analysis'!E12 -> 15.3 | D39: ='Fundamental Analysis'!H12 -> 0.136 | E39: ='Fundamental Analysis'!I12 -> 0.105
B40: Power Grid | C40: ='Fundamental Analysis'!E13 -> 16.86 | D40: ='Fundamental Analysis'!H13 -> 0.1637 | E40: ='Fundamental Analysis'!I13 -> 0.12
B41: Tata Power | C41: ='Fundamental Analysis'!E14 -> 30.6 | D41: ='Fundamental Analysis'!H14 -> 0.113 | E41: ='Fundamental Analysis'!I14 -> 0.111
B42: Torrent Power | C42: ='Fundamental Analysis'!E15 -> 38.7 | D42: ='Fundamental Analysis'!H15 -> 0.196 | E42: ='Fundamental Analysis'!I15 -> 0.183
B45: Key Findings
B46: Markowitz (Max Sharpe) delivered the best risk-adjusted return on the full daily-return dataset (Sharpe 1.58), concentrated in Adani Power, NTPC, Power Grid, Torrent Power and NHPC. The Criteria-Based portfolio, now weighted using a fixed-threshold fundamental rubric, achieved a solid Sharpe of 1.09 with a more diversified, fundamentals-driven approach and no look-ahead risk. The Equal-Weighted portfolio (Sharpe 0.94) and the flagged Benchmark (Sharpe 0.46) trailed both on a risk-adjusted basis. See Investor Recommendations for profile-specific guidance, and the Data Sources & Assumptions sheet for the benchmark identity issue that should be resolved before this is submitted.
B52: 4. Growth of Rs 10,00,000 Invested 5 Years Ago (Common Investment Comparison)
B53: Final value = Initial investment x (Cumulative Value Index / 100), from the Returns & Ratios sheet. Portfolios 5-6 use their reported 5-year CAGR.
B55: Portfolio | C55: Initial Investment (Rs) | D55: Final Value (Rs) | E55: Profit / (Loss) (Rs) | F55: Total Return %
B56: 1. Equal Weighted | C56: 1000000 | D56: =C56*('Returns & Ratios'!D1244/100) -> 2962402 | E56: =D56-C56 -> 1962402 | F56: =D56/C56-1 -> 1.962402
B57: 2. Criteria-Based | C57: 1000000 | D57: =C57*('Returns & Ratios'!F1244/100) -> 3368501.1 | E57: =D57-C57 -> 2368501.1 | F57: =D57/C57-1 -> 2.3685011
B58: 3. Markowitz (Max Sharpe) | C58: 1000000 | D58: =C58*('Returns & Ratios'!H1244/100) -> 5720780.9 | E58: =D58-C58 -> 4720780.9 | F58: =D58/C58-1 -> 4.7207809
B59: 4. Benchmark | C59: 1000000 | D59: =C59*('Returns & Ratios'!J1244/100) -> 1752821.9 | E59: =D59-C59 -> 752821.91 | F59: =D59/C59-1 -> 0.75282191
B60: 5. Mutual Fund 1 - Nippon India Power & Infra | C60: 1000000 | D60: =C60*(1+'Portfolio 5 - Mutual Fund 1'!C11)^5 -> 2773215.6 | E60: =D60-C60 -> 1773215.6 | F60: =D60/C60-1 -> 1.7732156
B61: 6. Mutual Fund 2 - Tata Resources & Energy | C61: 1000000 | D61: =C61*(1+'Portfolio 6 - Mutual Fund 2'!C11)^5 -> 1842435.2 | E61: =D61-C61 -> 842435.18 | F61: =D61/C61-1 -> 0.84243518

Sheet Daily Returns
B2: Daily Returns - All 10 Companies + Benchmark
B3: Chronological (oldest to newest), linked live to Historical Data. Daily Return = (Today's Price / Previous Trading Day's Price) - 1, as already computed in Historical Data. 1,237 daily observations, 21-Sep-2021 to 16-Sep-2026 (the first trading day, 20-Sep-2021, has no prior day in the file and so no return).
B5: Date | C5: Nifty Power (Energy) | D5: Adani Energy Solutions | E5: Adani Green | F5: Adani Power | G5: CESC | H5: JSW Energy | I5: NHPC | J5: NTPC | K5: Power Grid | L5: Tata Power | M5: Torrent Power
B6: ='Historical Data'!C1240 -> 44460 | C6: ='Historical Data'!E1240 -> 0.0052348864 | D6: ='Historical Data'!G1240 -> -0.049989853 | E6: ='Historical Data'!I1240 -> -0.0092384503 | F6: ='Historical Data'!K1240 -> -0.0094290363 | G6: ='Historical Data'!M1240 -> -0.04410956 | H6: ='Historical Data'!O1240 -> 0.021765439 | I6: ='Historical Data'!Q1240 -> -0.017888954 | J6: ='Historical Data'!S1240 -> 0.011409872 | K6: ='Historical Data'!U1240 -> -0.0062145925 | L6: ='Historical Data'!W1240 -> 0.011541308 | M6: ='Historical Data'!Y1240 -> 0.013415896
B7: ='Historical Data'!C1239 -> 44461 | C7: ='Historical Data'!E1239 -> 0.0081947994 | D7: ='Historical Data'!G1239 -> -0.049972594 | E7: ='Historical Data'!I1239 -> 0.018604532 | F7: ='Historical Data'!K1239 -> 0.014278184 | G7: ='Historical Data'!M1239 -> -0.032639215 | H7: ='Historical Data'!O1239 -> 0.0050296949 | I7: ='Historical Data'!Q1239 -> -0.0054646449 | J7: ='Historical Data'!S1239 -> 0.0024175821 | K7: ='Historical Data'!U1239 -> 0.0048323223 | L7: ='Historical Data'!W1239 -> 0.014722105 | M7: ='Historical Data'!Y1239 -> 0.0039714255
B8: ='Historical Data'!C1238 -> 44462 | C8: ='Historical Data'!E1238 -> 0.018326221 | D8: ='Historical Data'!G1238 -> -0.0084572481 | E8: ='Historical Data'!I1238 -> 0.0067013289 | F8: ='Historical Data'!K1238 -> 0.011991634 | G8: ='Historical Data'!M1238 -> 0.0023268554 | H8: ='Historical Data'!O1238 -> 0.032970112 | I8: ='Historical Data'!Q1238 -> 0.016483518 | J8: ='Historical Data'!S1238 -> 0.014469424 | K8: ='Historical Data'!U1238 -> 0.0084864496 | L8: ='Historical Data'!W1238 -> 0.042074586 | M8: ='Historical Data'!Y1238 -> 0.0044629223
B9: ='Historical Data'!C1237 -> 44463 | C9: ='Historical Data'!E1237 -> -0.0080755484 | D9: ='Historical Data'!G1237 -> -0.0035215503 | E9: ='Historical Data'!I1237 -> 0.0022625285 | F9: ='Historical Data'!K1237 -> -0.012364749 | G9: ='Historical Data'!M1237 -> -0.023795718 | H9: ='Historical Data'!O1237 -> -0.0024224398 | I9: ='Historical Data'!Q1237 -> 0.0072072349 | J9: ='Historical Data'!S1237 -> -0.015451722 | K9: ='Historical Data'!U1237 -> -0.011781036 | L9: ='Historical Data'!W1237 -> -0.031674175 | M9: ='Historical Data'!Y1237 -> 0.0068665798
B10: ='Historical Data'!C1236 -> 44466 | C10: ='Historical Data'!E1236 -> 0.013335513 | D10: ='Historical Data'!G1236 -> 0.023506144 | E10: ='Historical Data'!I1236 -> 0.0014324555 | F10: ='Historical Data'!K1236 -> 0.011997889 | G10: ='Historical Data'!M1236 -> -0.01961956 | H10: ='Historical Data'!O1236 -> 0 | I10: ='Historical Data'!Q1236 -> -0.0071556624 | J10: ='Historical Data'!S1236 -> 0.020925536 | K10: ='Historical Data'!U1236 -> -0.00085173379 | L10: ='Historical Data'!W1236 -> -0.0025160767 | M10: ='Historical Data'!Y1236 -> -0.0073211927
B11: ='Historical Data'!C1235 -> 44467 | C11: ='Historical Data'!E1235 -> 0.02014446 | D11: ='Historical Data'!G1235 -> -0.018056259 | E11: ='Historical Data'!I1235 -> -0.0077592887 | F11: ='Historical Data'!K1235 -> -0.01030922 | G11: ='Historical Data'!M1235 -> -0.0018190758 | H11: ='Historical Data'!O1235 -> 0.047850355 | I11: ='Historical Data'!Q1235 -> 0.019819876 | J11: ='Historical Data'!S1235 -> 0.040204995 | K11: ='Historical Data'!U1235 -> 0.045170526 | L11: ='Historical Data'!W1235 -> 0.0093692121 | M11: ='Historical Data'!Y1235 -> 0.016872195
B12: ='Historical Data'!C1234 -> 44468 | C12: ='Historical Data'!E1234 -> 0.018494968 | D12: ='Historical Data'!G1234 -> -0.012452448 | E12: ='Historical Data'!I1234 -> -0.005111381 | F12: ='Historical Data'!K1234 -> 0.023958285 | G12: ='Historical Data'!M1234 -> 0.052855236 | H12: ='Historical Data'!O1234 -> 0.049754672 | I12: ='Historical Data'!Q1234 -> 0.035335743 | J12: ='Historical Data'!S1234 -> 0.065934243 | K12: ='Historical Data'!U1234 -> 0.060342723 | L12: ='Historical Data'!W1234 -> 0.082470697 | M12: ='Historical Data'!Y1234 -> 0.026130165
B13: ='Historical Data'!C1233 -> 44469 | C13: ='Historical Data'!E1233 -> -0.00026241496 | D13: ='Historical Data'!G1233 -> 0.018228162 | E13: ='Historical Data'!I1233 -> 0.0069819093 | F13: ='Historical Data'!K1233 -> -0.012207516 | G13: ='Historical Data'!M1233 -> 0.056549276 | H13: ='Historical Data'!O1233 -> 0.012595785 | I13: ='Historical Data'!Q1233 -> 0.018771228 | J13: ='Historical Data'!S1233 -> 0.0085317343 | K13: ='Historical Data'!U1233 -> -0.026403772 | L13: ='Historical Data'!W1233 -> 0.047163475 | M13: ='Historical Data'!Y1233 -> -0.021979161
B14: ='Historical Data'!C1232 -> 44470 | C14: ='Historical Data'!E1232 -> 0.006196806 | D14: ='Historical Data'!G1232 -> 0.012415769 | E14: ='Historical Data'!I1232 -> 0.0038811036 | F14: ='Historical Data'!K1232 -> -0.0015448345 | G14: ='Historical Data'!M1232 -> -0.0016383672 | H14: ='Historical Data'!O1232 -> -0.012054375 | I14: ='Historical Data'!Q1232 -> -0.025125706 | J14: ='Historical Data'!S1232 -> -0.01374703 | K14: ='Historical Data'!U1232 -> 0.010268842 | L14: ='Historical Data'!W1232 -> 0.031496135 | M14: ='Historical Data'!Y1232 -> -0.0072270356
B15: ='Historical Data'!C1231 -> 44473 | C15: ='Historical Data'!E1231 -> 0.014539004 | D15: ='Historical Data'!G1231 -> 0.036853963 | E15: ='Historical Data'!I1231 -> 0.021762674 | F15: ='Historical Data'!K1231 -> 0.049510109 | G15: ='Historical Data'!M1231 -> 0.0082057042 | H15: ='Historical Data'!O1231 -> -0.015706107 | I15: ='Historical Data'!Q1231 -> 0.020618637 | J15: ='Historical Data'!S1231 -> 0.040386067 | K15: ='Historical Data'!U1231 -> -0.0010427097 | L15: ='Historical Data'!W1231 -> 0.029618355 | M15: ='Historical Data'!Y1231 -> 0.0023933454
B16: ='Historical Data'!C1230 -> 44474 | C16: ='Historical Data'!E1230 -> 0.028779152 | D16: ='Historical Data'!G1230 -> 0.05000003 | E16: ='Historical Data'!I1230 -> 0.039197327 | F16: ='Historical Data'!K1230 -> 0.04668299 | G16: ='Historical Data'!M1230 -> 0.0092241219 | H16: ='Historical Data'!O1230 -> 0.025319819 | I16: ='Historical Data'!Q1230 -> 0.013468065 | J16: ='Historical Data'!S1230 -> -0.0010307108 | K16: ='Historical Data'!U1230 -> -0.0088702593 | L16: ='Historical Data'!W1230 -> 0.064056802 | M16: ='Historical Data'!Y1230 -> 0.02497028
B17: ='Historical Data'!C1229 -> 44475 | C17: ='Historical Data'!E1229 -> -0.0045050956 | D17: ='Historical Data'!G1229 -> 0.027185906 | E17: ='Historical Data'!I1229 -> -0.0062182752 | F17: ='Historical Data'!K1229 -> -0.046478864 | G17: ='Historical Data'!M1229 -> -0.017204346 | H17: ='Historical Data'!O1229 -> -0.020836043 | I17: ='Historical Data'!Q1229 -> 0.0049833888 | J17: ='Historical Data'!S1229 -> -0.014442734 | K17: ='Historical Data'!U1229 -> -0.012371872 | L17: ='Historical Data'!W1229 -> -0.019230669 | M17: ='Historical Data'!Y1229 -> -0.018344262
B18: ='Historical Data'!C1228 -> 44476 | C18: ='Historical Data'!E1228 -> -0.0039166457 | D18: ='Historical Data'!G1228 -> -0.00011331888 | E18: ='Historical Data'!I1228 -> -0.007368641 | F18: ='Historical Data'!K1228 -> 0.0039389427 | G18: ='Historical Data'!M1228 -> -0.023522898 | H18: ='Historical Data'!O1228 -> -0.0039406215 | I18: ='Historical Data'!Q1228 -> 0.009917281 | J18: ='Historical Data'!S1228 -> -0.0034892287 | K18: ='Historical Data'!U1228 -> 0.0037315424 | L18: ='Historical Data'!W1228 -> 0.010230098 | M18: ='Historical Data'!Y1228 -> 0.0086019032
B19: ='Historical Data'!C1227 -> 44477 | C19: ='Historical Data'!E1227 -> 0.004112685 | D19: ='Historical Data'!G1227 -> -0.04851788 | E19: ='Historical Data'!I1227 -> -0.024136337 | F19: ='Historical Data'!K1227 -> -0.0034330406 | G19: ='Historical Data'!M1227 -> -0.0061625555 | H19: ='Historical Data'!O1227 -> 0.0068573892 | I19: ='Historical Data'!Q1227 -> 0.001636686 | J19: ='Historical Data'!S1227 -> -0.01190479 | K19: ='Historical Data'!U1227 -> -0.0031866231 | L19: ='Historical Data'!W1227 -> -0.0050632068 | M19: ='Historical Data'!Y1227 -> -0.011861568
B20: ='Historical Data'!C1226 -> 44480 | C20: ='Historical Data'!E1226 -> 0.010846237 | D20: ='Historical Data'!G1226 -> 0.010722583 | E20: ='Historical Data'!I1226 -> -0.012281733 | F20: ='Historical Data'!K1226 -> 0.0024606863 | G20: ='Historical Data'!M1226 -> 0.015219848 | H20: ='Historical Data'!O1226 -> 0.019122493 | I20: ='Historical Data'!Q1226 -> -0.0016340116 | J20: ='Historical Data'!S1226 -> 0.026222559 | K20: ='Historical Data'!U1226 -> 0.030634036 | L20: ='Historical Data'!W1226 -> 0.082838472 | M20: ='Historical Data'!Y1226 -> 0.070039649
B21: ='Historical Data'!C1225 -> 44481 | C21: ='Historical Data'!E1225 -> 0.0043209148 | D21: ='Historical Data'!G1225 -> -0.0046560397 | E21: ='Historical Data'!I1225 -> 0.039798641 | F21: ='Historical Data'!K1225 -> -0.0019637169 | G21: ='Historical Data'!M1225 -> 0.0022210212 | H21: ='Historical Data'!O1225 -> -0.02364733 | I21: ='Historical Data'!Q1225 -> -0.014729878 | J21: ='Historical Data'!S1225 -> -0.0017266039 | K21: ='Historical Data'!U1225 -> -0.00051697611 | L21: ='Historical Data'!W1225 -> 0.022454346 | M21: ='Historical Data'!Y1225 -> -0.034118188
B22: ='Historical Data'!C1224 -> 44482 | C22: ='Historical Data'!E1224 -> 0.013947527 | D22: ='Historical Data'!G1224 -> 0.008260274 | E22: ='Historical Data'!I1224 -> -0.012289466 | F22: ='Historical Data'!K1224 -> 0.049680287 | G22: ='Historical Data'!M1224 -> 0.012742355 | H22: ='Historical Data'!O1224 -> 0.049888056 | I22: ='Historical Data'!Q1224 -> -0.026578024 | J22: ='Historical Data'!S1224 -> 0.012452601 | K22: ='Historical Data'!U1224 -> 0.031290457 | L22: ='Historical Data'!W1224 -> 0.14504596 | M22: ='Historical Data'!Y1224 -> -0.0031677211
B23: ='Historical Data'!C1223 -> 44483 | C23: ='Historical Data'!E1223 -> 0.006582156 | D23: ='Historical Data'!G1223 -> -0.0090735288 | E23: ='Historical Data'!I1223 -> 0.010934268 | F23: ='Historical Data'!K1223 -> 0.049671952 | G23: ='Historical Data'!M1223 -> 0.025711221 | H23: ='Historical Data'!O1223 -> -0.012036043 | I23: ='Historical Data'!Q1223 -> 0.054607404 | J23: ='Historical Data'!S1223 -> 0.020840351 | K23: ='Historical Data'!U1223 -> 0.026329256 | L23: ='Historical Data'!W1223 -> -0.007136507 | M23: ='Historical Data'!Y1223 -> -0.0074145318
B24: ='Historical Data'!C1222 -> 44487 | C24: ='Historical Data'!E1222 -> 0.015438286 | D24: ='Historical Data'!G1222 -> 0.036093108 | E24: ='Historical Data'!I1222 -> -0.0024035674 | F24: ='Historical Data'!K1222 -> 0.099999991 | G24: ='Historical Data'!M1222 -> 0.04906656 | H24: ='Historical Data'!O1222 -> -0.0054568334 | I24: ='Historical Data'!Q1222 -> 0.1488673 | J24: ='Historical Data'!S1222 -> 0.0010041496 | K24: ='Historical Data'!U1222 -> -0.004153459 | L24: ='Historical Data'!W1222 -> 0.15588502 | M24: ='Historical Data'!Y1222 -> 0.011447466
B25: ='Historical Data'!C1221 -> 44488 | C25: ='Historical Data'!E1221 -> -0.014436134 | D25: ='Historical Data'!G1221 -> -0.0018017975 | E25: ='Historical Data'!I1221 -> -0.018527021 | F25: ='Historical Data'!K1221 -> 0.013392854 | G25: ='Historical Data'!M1221 -> -0.023385719 | H25: ='Historical Data'!O1221 -> -0.032282778 | I25: ='Historical Data'!Q1221 -> -0.040845053 | J25: ='Historical Data'!S1221 -> 0.00066850074 | K25: ='Historical Data'!U1221 -> -0.025270022 | L25: ='Historical Data'!W1221 -> -0.10707342 | M25: ='Historical Data'!Y1221 -> -0.019566457
B26: ='Historical Data'!C1220 -> 44489 | C26: ='Historical Data'!E1220 -> -0.016291685 | D26: ='Historical Data'!G1220 -> -0.01997083 | E26: ='Historical Data'!I1220 -> -0.0018622349 | F26: ='Historical Data'!K1220 -> -0.031637927 | G26: ='Historical Data'!M1220 -> -0.028110468 | H26: ='Historical Data'!O1220 -> -0.0079114622 | I26: ='Historical Data'!Q1220 -> -0.051394856 | J26: ='Historical Data'!S1220 -> -0.022719555 | K26: ='Historical Data'!U1220 -> -0.021646111 | L26: ='Historical Data'!W1220 -> 0.0026115593 | M26: ='Historical Data'!Y1220 -> -0.025043932
B27: ='Historical Data'!C1219 -> 44490 | C27: ='Historical Data'!E1219 -> -0.003094515 | D27: ='Historical Data'!G1219 -> 0.046427334 | E27: ='Historical Data'!I1219 -> 0.016791694 | F27: ='Historical Data'!K1219 -> 0.019023949 | G27: ='Historical Data'!M1219 -> 0.013390456 | H27: ='Historical Data'!O1219 -> -0.013955321 | I27: ='Historical Data'!Q1219 -> -0.037151839 | J27: ='Historical Data'!S1219 -> 0.011281951 | K27: ='Historical Data'!U1219 -> -0.001543613 | L27: ='Historical Data'!W1219 -> -0.018233161 | M27: ='Historical Data'!Y1219 -> -0.0044151418
B28: ='Historical Data'!C1218 -> 44491 | C28: ='Historical Data'!E1218 -> -0.001065563 | D28: ='Historical Data'!G1218 -> 0.010840425 | E28: ='Historical Data'!I1218 -> 0.0026690632 | F28: ='Historical Data'!K1218 -> -0.049918814 | G28: ='Historical Data'!M1218 -> -0.016913261 | H28: ='Historical Data'!O1218 -> 0.026688292 | I28: ='Historical Data'!Q1218 -> 0.041800621 | J28: ='Historical Data'!S1218 -> -0.020284118 | K28: ='Historical Data'!U1218 -> 0.0020611105 | L28: ='Historical Data'!W1218 -> -0.018350729 | M28: ='Historical Data'!Y1218 -> 0.002015739
B29: ='Historical Data'!C1217 -> 44494 | C29: ='Historical Data'!E1217 -> -0.0049545932 | D29: ='Historical Data'!G1217 -> 0.033665022 | E29: ='Historical Data'!I1217 -> 0.00020796073 | F29: ='Historical Data'!K1217 -> -0.049978645 | G29: ='Historical Data'!M1217 -> -0.02258056 | H29: ='Historical Data'!O1217 -> -0.018380019 | I29: ='Historical Data'!Q1217 -> 0 | J29: ='Historical Data'!S1217 -> -0.0069011537 | K29: ='Historical Data'!U1217 -> -0.0092565182 | L29: ='Historical Data'!W1217 -> -0.037837706 | M29: ='Historical Data'!Y1217 -> -0.0060349151
B30: ='Historical Data'!C1216 -> 44495 | C30: ='Historical Data'!E1216 -> 0.0087851094 | D30: ='Historical Data'!G1216 -> -0.0080485848 | E30: ='Historical Data'!I1216 -> -0.018671052 | F30: ='Historical Data'!K1216 -> 0.0089928402 | G30: ='Historical Data'!M1216 -> 0.01155111 | H30: ='Historical Data'!O1216 -> -0.010966904 | I30: ='Historical Data'!Q1216 -> -0.02777778 | J30: ='Historical Data'!S1216 -> -0.0048646151 | K30: ='Historical Data'!U1216 -> -0.011679357 | L30: ='Historical Data'!W1216 -> 0.054775249 | M30: ='Historical Data'!Y1216 -> 0.010220434
B31: ='Historical Data'!C1215 -> 44496 | C31: ='Historical Data'!E1215 -> -0.0076972155 | D31: ='Historical Data'!G1215 -> 0.01045908 | E31: ='Historical Data'!I1215 -> 0.022161978 | F31: ='Historical Data'!K1215 -> -0.030748686 | G31: ='Historical Data'!M1215 -> -0.019575827 | H31: ='Historical Data'!O1215 -> -0.0086545049 | I31: ='Historical Data'!Q1215 -> 0.0031746512 | J31: ='Historical Data'!S1215 -> -0.013268016 | K31: ='Historical Data'!U1215 -> -0.00078771638 | L31: ='Historical Data'!W1215 -> -0.0046605498 | M31: ='Historical Data'!Y1215 -> 0.0011019401
B32: ='Historical Data'!C1214 -> 44497 | C32: ='Historical Data'!E1214 -> -0.024974312 | D32: ='Historical Data'!G1214 -> -0.043350674 | E32: ='Historical Data'!I1214 -> -0.048876505 | F32: ='Historical Data'!K1214 -> -0.048735608 | G32: ='Historical Data'!M1214 -> -0.0099833996 | H32: ='Historical Data'!O1214 -> -0.04992493 | I32: ='Historical Data'!Q1214 -> -0.015822809 | J32: ='Historical Data'!S1214 -> -0.027954624 | K32: ='Historical Data'!U1214 -> -0.022864503 | L32: ='Historical Data'!W1214 -> -0.027870674 | M32: ='Historical Data'!Y1214 -> -0.021813081
B33: ='Historical Data'!C1213 -> 44498 | C33: ='Historical Data'!E1213 -> -0.014619914 | D33: ='Historical Data'!G1213 -> -0.014277733 | E33: ='Historical Data'!I1213 -> 0.0049687931 | F33: ='Historical Data'!K1213 -> -0.028516198 | G33: ='Historical Data'!M1213 -> -0.022969307 | H33: ='Historical Data'!O1213 -> 0.0011485563 | I33: ='Historical Data'!Q1213 -> -0.012861785 | J33: ='Historical Data'!S1213 -> -0.034219393 | K33: ='Historical Data'!U1213 -> -0.0045725881 | L33: ='Historical Data'!W1213 -> -0.016972412 | M33: ='Historical Data'!Y1213 -> 0.022811015
B34: ='Historical Data'!C1212 -> 44501 | C34: ='Historical Data'!E1212 -> 0.011550992 | D34: ='Historical Data'!G1212 -> -0.0038757358 | E34: ='Historical Data'!I1212 -> 0.016914603 | F34: ='Historical Data'!K1212 -> 0.02338305 | G34: ='Historical Data'!M1212 -> 0.011467948 | H34: ='Historical Data'!O1212 -> -0.018356536 | I34: ='Historical Data'!Q1212 -> 0.040716641 | J34: ='Historical Data'!S1212 -> 0.012439048 | K34: ='Historical Data'!U1212 -> 0.014590709 | L34: ='Historical Data'!W1212 -> 0.040363927 | M34: ='Historical Data'!Y1212 -> 0.0077006926
B35: ='Historical Data'!C1211 -> 44502 | C35: ='Historical Data'!E1211 -> -0.0035227297 | D35: ='Historical Data'!G1211 -> -0.0012780097 | E35: ='Historical Data'!I1211 -> 0.0016206973 | F35: ='Historical Data'!K1211 -> 0.012153622 | G35: ='Historical Data'!M1211 -> 0.010771024 | H35: ='Historical Data'!O1211 -> -0.016216136 | I35: ='Historical Data'!Q1211 -> -0.01095457 | J35: ='Historical Data'!S1211 -> 0.017497827 | K35: ='Historical Data'!U1211 -> -0.011984103 | L35: ='Historical Data'!W1211 -> 0.024893519 | M35: ='Historical Data'!Y1211 -> 0.0362247
B36: ='Historical Data'!C1210 -> 44503 | C36: ='Historical Data'!E1210 -> 0.0028926167 | D36: ='Historical Data'!G1210 -> 0.048370542 | E36: ='Historical Data'!I1210 -> 0.025761124 | F36: ='Historical Data'!K1210 -> -0.0081652295 | G36: ='Historical Data'!M1210 -> -0.0050477467 | H36: ='Historical Data'!O1210 -> -0.016632125 | I36: ='Historical Data'!Q1210 -> -0.037974613 | J36: ='Historical Data'!S1210 -> 0.00073187207 | K36: ='Historical Data'!U1210 -> -0.0083557472 | L36: ='Historical Data'!W1210 -> 0.0013129574 | M36: ='Historical Data'!Y1210 -> -0.01858061
B37: ='Historical Data'!C1209 -> 44504 | C37: ='Historical Data'!E1209 -> 0.0040273399 | D37: ='Historical Data'!G1209 -> -0.014023368 | E37: ='Historical Data'!I1209 -> -0.0034038818 | F37: ='Historical Data'!K1209 -> 0.02082326 | G37: ='Historical Data'!M1209 -> 0.032694521 | H37: ='Historical Data'!O1209 -> 0.0042284997 | I37: ='Historical Data'!Q1209 -> 0.018092154 | J37: ='Historical Data'!S1209 -> 0.0029250182 | K37: ='Historical Data'!U1209 -> 0.0059798626 | L37: ='Historical Data'!W1209 -> 0.011145091 | M37: ='Historical Data'!Y1209 -> 0.0062457414
B38: ='Historical Data'!C1208 -> 44508 | C38: ='Historical Data'!E1208 -> 0.015041946 | D38: ='Historical Data'!G1208 -> 0.014855571 | E38: ='Historical Data'!I1208 -> 0.021326204 | F38: ='Historical Data'!K1208 -> -0.0085389139 | G38: ='Historical Data'!M1208 -> 0.0032749453 | H38: ='Historical Data'!O1208 -> -0.045714514 | I38: ='Historical Data'!Q1208 -> 0.032310004 | J38: ='Historical Data'!S1208 -> 0.022967855 | K38: ='Historical Data'!U1208 -> 0.022156285 | L38: ='Historical Data'!W1208 -> 0.013831829 | M38: ='Historical Data'!Y1208 -> 0.027349503
B39: ='Historical Data'!C1207 -> 44509 | C39: ='Historical Data'!E1207 -> 0.0027361438 | D39: ='Historical Data'!G1207 -> 0.0082949573 | E39: ='Historical Data'!I1207 -> 0.0039152111 | F39: ='Historical Data'!K1207 -> 0.04976081 | G39: ='Historical Data'!M1207 -> -0.0065286159 | H39: ='Historical Data'!O1207 -> 0.0026789607 | I39: ='Historical Data'!Q1207 -> 0.020344242 | J39: ='Historical Data'!S1207 -> -0.012829815 | K39: ='Historical Data'!U1207 -> -0.013745712 | L39: ='Historical Data'!W1207 -> 0.031336515 | M39: ='Historical Data'!Y1207 -> 0.00028314719
B40: ='Historical Data'!C1206 -> 44510 | C40: ='Historical Data'!E1206 -> 0.0015413905 | D40: ='Historical Data'!G1206 -> 0.007016844 | E40: ='Historical Data'!I1206 -> -0.0015843948 | F40: ='Historical Data'!K1206 -> 0.0041021035 | G40: ='Historical Data'!M1206 -> 0.00054744036 | H40: ='Historical Data'!O1206 -> 0.0045576832 | I40: ='Historical Data'!Q1206 -> -0.01073629 | J40: ='Historical Data'!S1206 -> -0.0079424065 | K40: ='Historical Data'!U1206 -> -0.011525093 | L40: ='Historical Data'!W1206 -> -0.020256228 | M40: ='Historical Data'!Y1206 -> 0.016798883
B41: ='Historical Data'!C1205 -> 44511 | C41: ='Historical Data'!E1205 -> -0.0060957602 | D41: ='Historical Data'!G1205 -> 0.011132753 | E41: ='Historical Data'!I1205 -> 0.0015869091 | F41: ='Historical Data'!K1205 -> -0.018610978 | G41: ='Historical Data'!M1205 -> 0.0010948134 | H41: ='Historical Data'!O1205 -> 0.043648198 | I41: ='Historical Data'!Q1205 -> -0.006201365 | J41: ='Historical Data'!S1205 -> -0.0054585216 | K41: ='Historical Data'!U1205 -> -0.012201608 | L41: ='Historical Data'!W1205 -> 0.011603348 | M41: ='Historical Data'!Y1205 -> -0.0063114655
B42: ='Historical Data'!C1204 -> 44512 | C42: ='Historical Data'!E1204 -> 0.01316398 | D42: ='Historical Data'!G1204 -> 0.049981532 | E42: ='Historical Data'!I1204 -> 0.049967499 | F42: ='Historical Data'!K1204 -> 0.0032377286 | G42: ='Historical Data'!M1204 -> -0.0092947276 | H42: ='Historical Data'!O1204 -> -0.032828572 | I42: ='Historical Data'!Q1204 -> 0.0078004296 | J42: ='Historical Data'!S1204 -> -0.0014634807 | K42: ='Historical Data'!U1204 -> -0.00082367773 | L42: ='Historical Data'!W1204 -> 0.00041716003 | M42: ='Historical Data'!Y1204 -> 0.0074723146
B43: ='Historical Data'!C1203 -> 44515 | C43: ='Historical Data'!E1203 -> 0.0024597985 | D43: ='Historical Data'!G1203 -> -0.026403802 | E43: ='Historical Data'!I1203 -> 0.0098661298 | F43: ='Historical Data'!K1203 -> -0.011987101 | G43: ='Historical Data'!M1203 -> 0 | H43: ='Historical Data'!O1203 -> -0.00093007853 | I43: ='Historical Data'!Q1203 -> -0.015480108 | J43: ='Historical Data'!S1203 -> 0.0051300194 | K43: ='Historical Data'!U1203 -> 0.03461545 | L43: ='Historical Data'!W1203 -> 0.0075046305 | M43: ='Historical Data'!Y1203 -> 0.011403767
B44: ='Historical Data'!C1202 -> 44516 | C44: ='Historical Data'!E1202 -> -0.013358688 | D44: ='Historical Data'!G1202 -> -0.029935146 | E44: ='Historical Data'!I1202 -> 0.0071261074 | F44: ='Historical Data'!K1202 -> -0.0037330808 | G44: ='Historical Data'!M1202 -> -0.0071744991 | H44: ='Historical Data'!O1202 -> 0.00031037956 | I44: ='Historical Data'!Q1202 -> 0.066037745 | J44: ='Historical Data'!S1202 -> -0.020779915 | K44: ='Historical Data'!U1202 -> -0.0037176697 | L44: ='Historical Data'!W1202 -> 0.011793883 | M44: ='Historical Data'!Y1202 -> -0.0048583848
B45: ='Historical Data'!C1201 -> 44517 | C45: ='Historical Data'!E1201 -> -0.0044581984 | D45: ='Historical Data'!G1201 -> -0.010863211 | E45: ='Historical Data'!I1201 -> -0.00064668894 | F45: ='Historical Data'!K1201 -> -0.022950809 | G45: ='Historical Data'!M1201 -> -0.0094495111 | H45: ='Historical Data'!O1201 -> -0.035980329 | I45: ='Historical Data'!Q1201 -> -0.022123764 | J45: ='Historical Data'!S1201 -> 0.016008739 | K45: ='Historical Data'!U1201 -> 0.018390508 | L45: ='Historical Data'!W1201 -> 0.022085909 | M45: ='Historical Data'!Y1201 -> -0.0040531785
B46: ='Historical Data'!C1200 -> 44518 | C46: ='Historical Data'!E1200 -> -0.0018269227 | D46: ='Historical Data'!G1200 -> 0.030040403 | E46: ='Historical Data'!I1200 -> 0.024552722 | F46: ='Historical Data'!K1200 -> -0.013422851 | G46: ='Historical Data'!M1200 -> -0.011784467 | H46: ='Historical Data'!O1200 -> -0.049871194 | I46: ='Historical Data'!Q1200 -> -0.016591365 | J46: ='Historical Data'!S1200 -> -0.0084279078 | K46: ='Historical Data'!U1200 -> 0.0075894054 | L46: ='Historical Data'!W1200 -> -0.051220455 | M46: ='Historical Data'!Y1200 -> -0.025989624
B47: ='Historical Data'!C1199 -> 44522 | C47: ='Historical Data'!E1199 -> -0.028412207 | D47: ='Historical Data'!G1199 -> 7.8347536e-05 | E47: ='Historical Data'!I1199 -> -0.0035668206 | F47: ='Historical Data'!K1199 -> -0.018950408 | G47: ='Historical Data'!M1199 -> -0.051675281 | H47: ='Historical Data'!O1199 -> -0.0033864168 | I47: ='Historical Data'!Q1199 -> -0.038343517 | J47: ='Historical Data'!S1199 -> -0.038063657 | K47: ='Historical Data'!U1199 -> 0.0088311594 | L47: ='Historical Data'!W1199 -> -0.039856634 | M47: ='Historical Data'!Y1199 -> -0.027537809
B48: ='Historical Data'!C1198 -> 44523 | C48: ='Historical Data'!E1198 -> 0.020271819 | D48: ='Historical Data'!G1198 -> 0.021479578 | E48: ='Historical Data'!I1198 -> 0.049293486 | F48: ='Historical Data'!K1198 -> 0.049529469 | G48: ='Historical Data'!M1198 -> 0.078443109 | H48: ='Historical Data'!O1198 -> 0.046041604 | I48: ='Historical Data'!Q1198 -> 0.0079745303 | J48: ='Historical Data'!S1198 -> 0.025739591 | K48: ='Historical Data'!U1198 -> 0.039392171 | L48: ='Historical Data'!W1198 -> 0.040852267 | M48: ='Historical Data'!Y1198 -> 0.045698759
B49: ='Historical Data'!C1197 -> 44524 | C49: ='Historical Data'!E1197 -> 0.0026752081 | D49: ='Historical Data'!G1197 -> -0.0089790736 | E49: ='Historical Data'!I1197 -> -0.011158148 | F49: ='Historical Data'!K1197 -> -0.00047193151 | G49: ='Historical Data'!M1197 -> 0.011660145 | H49: ='Historical Data'!O1197 -> -0.00016262668 | I49: ='Historical Data'!Q1197 -> -0.011075902 | J49: ='Historical Data'!S1197 -> 0.013857858 | K49: ='Historical Data'!U1197 -> 0.0071837853 | L49: ='Historical Data'!W1197 -> 0.0067524329 | M49: ='Historical Data'!Y1197 -> 0.028107259
B50: ='Historical Data'!C1196 -> 44525 | C50: ='Historical Data'!E1196 -> 0.024025319 | D50: ='Historical Data'!G1196 -> 0.047805873 | E50: ='Historical Data'!I1196 -> 0.0098466047 | F50: ='Historical Data'!K1196 -> -0.0080264435 | G50: ='Historical Data'!M1196 -> 0.0027441711 | H50: ='Historical Data'!O1196 -> 0.029889725 | I50: ='Historical Data'!Q1196 -> -0.0048000721 | J50: ='Historical Data'!S1196 -> -0.0011083851 | K50: ='Historical Data'!U1196 -> 0.0046729688 | L50: ='Historical Data'!W1196 -> 0.017816038 | M50: ='Historical Data'!Y1196 -> 0.0037238155
B51: ='Historical Data'!C1195 -> 44526 | C51: ='Historical Data'!E1195 -> -0.035875837 | D51: ='Historical Data'!G1195 -> -0.017614308 | E51: ='Historical Data'!I1195 -> -0.023130849 | F51: ='Historical Data'!K1195 -> -0.036173261 | G51: ='Historical Data'!M1195 -> -0.029009205 | H51: ='Historical Data'!O1195 -> -0.047634004 | I51: ='Historical Data'!Q1195 -> -0.014469454 | J51: ='Historical Data'!S1195 -> -0.0469674 | K51: ='Historical Data'!U1195 -> -0.011015987 | L51: ='Historical Data'!W1195 -> -0.06363269 | M51: ='Historical Data'!Y1195 -> -0.026151455
B52: ='Historical Data'!C1194 -> 44529 | C52: ='Historical Data'!E1194 -> -0.01273052 | D52: ='Historical Data'!G1194 -> -0.049978697 | E52: ='Historical Data'!I1194 -> -0.014425739 | F52: ='Historical Data'!K1194 -> -0.028148133 | G52: ='Historical Data'!M1194 -> -0.030439806 | H52: ='Historical Data'!O1194 -> -0.03858903 | I52: ='Historical Data'!Q1194 -> -0.011419201 | J52: ='Historical Data'!S1194 -> -0.018238288 | K52: ='Historical Data'!U1194 -> -0.0086632835 | L52: ='Historical Data'!W1194 -> -0.038266975 | M52: ='Historical Data'!Y1194 -> -0.0083626677
B53: ='Historical Data'!C1193 -> 44530 | C53: ='Historical Data'!E1193 -> -0.0099209835 | D53: ='Historical Data'!G1193 -> -0.049994696 | E53: ='Historical Data'!I1193 -> -0.042395103 | F53: ='Historical Data'!K1193 -> 0.0096544985 | G53: ='Historical Data'!M1193 -> 0.017441895 | H53: ='Historical Data'!O1193 -> -0.010163628 | I53: ='Historical Data'!Q1193 -> 0.026402591 | J53: ='Historical Data'!S1193 -> 0.0059287171 | K53: ='Historical Data'!U1193 -> 0.032459509 | L53: ='Historical Data'!W1193 -> -0.0084610498 | M53: ='Historical Data'!Y1193 -> 0.032983403
B54: ='Historical Data'!C1192 -> 44531 | C54: ='Historical Data'!E1192 -> 0.012590121 | D54: ='Historical Data'!G1192 -> -0.0013059047 | E54: ='Historical Data'!I1192 -> 0.025629111 | F54: ='Historical Data'!K1192 -> 0.019124265 | G54: ='Historical Data'!M1192 -> -0.0074285709 | H54: ='Historical Data'!O1192 -> 0.049947613 | I54: ='Historical Data'!Q1192 -> 0.014469454 | J54: ='Historical Data'!S1192 -> 0.0035363921 | K54: ='Historical Data'!U1192 -> 0.0021762686 | L54: ='Historical Data'!W1192 -> 0.038745397 | M54: ='Historical Data'!Y1192 -> -0.0014514893
B55: ='Historical Data'!C1191 -> 44532 | C55: ='Historical Data'!E1191 -> 0.016477145 | D55: ='Historical Data'!G1191 -> 0.048994199 | E55: ='Historical Data'!I1191 -> 0.009784736 | F55: ='Historical Data'!K1191 -> 0.0049382904 | G55: ='Historical Data'!M1191 -> 0.014392733 | H55: ='Historical Data'!O1191 -> 0.049726639 | I55: ='Historical Data'!Q1191 -> 0.022186839 | J55: ='Historical Data'!S1191 -> 0.0078308852 | K55: ='Historical Data'!U1191 -> 0.035231784 | L55: ='Historical Data'!W1191 -> 0.0053286481 | M55: ='Historical Data'!Y1191 -> 0.021166509
B56: ='Historical Data'!C1190 -> 44533 | C56: ='Historical Data'!E1190 -> -0.009929081 | D56: ='Historical Data'!G1190 -> -0.0089645145 | E56: ='Historical Data'!I1190 -> 0.035815481 | F56: ='Historical Data'!K1190 -> -0.0093366354 | G56: ='Historical Data'!M1190 -> 0.011918341 | H56: ='Historical Data'!O1190 -> 0.020369619 | I56: ='Historical Data'!Q1190 -> 0.0093025376 | J56: ='Historical Data'!S1190 -> -0.013208905 | K56: ='Historical Data'!U1190 -> -0.039160814 | L56: ='Historical Data'!W1190 -> -0.0035335795 | M56: ='Historical Data'!Y1190 -> 0.0057824357
B57: ='Historical Data'!C1189 -> 44536 | C57: ='Historical Data'!E1189 -> -0.015385872 | D57: ='Historical Data'!G1189 -> 0.0031311756 | E57: ='Historical Data'!I1189 -> -0.0078797345 | F57: ='Historical Data'!K1189 -> -0.012896837 | G57: ='Historical Data'!M1189 -> -0.0016826912 | H57: ='Historical Data'!O1189 -> -0.038378293 | I57: ='Historical Data'!Q1189 -> 0.026113787 | J57: ='Historical Data'!S1189 -> -0.020866269 | K57: ='Historical Data'!U1189 -> -0.019893293 | L57: ='Historical Data'!W1189 -> -0.021054927 | M57: ='Historical Data'!Y1189 -> -0.018751089
B58: ='Historical Data'!C1188 -> 44537 | C58: ='Historical Data'!E1188 -> 0.01187747 | D58: ='Historical Data'!G1188 -> 0.0097643873 | E58: ='Historical Data'!I1188 -> 0.0079785308 | F58: ='Historical Data'!K1188 -> 0.0085427176 | G58: ='Historical Data'!M1188 -> -0.022471807 | H58: ='Historical Data'!O1188 -> -0.011908567 | I58: ='Historical Data'!Q1188 -> 0.004490747 | J58: ='Historical Data'!S1188 -> 0.0080419222 | K58: ='Historical Data'!U1188 -> 0.018812042 | L58: ='Historical Data'!W1188 -> 0.025356581 | M58: ='Historical Data'!Y1188 -> 0.056246793
B59: ='Historical Data'!C1187 -> 44538 | C59: ='Historical Data'!E1187 -> 0.0082123206 | D59: ='Historical Data'!G1187 -> -0.0051520517 | E59: ='Historical Data'!I1187 -> 0.00057569897 | F59: ='Historical Data'!K1187 -> 0.035874501 | G59: ='Historical Data'!M1187 -> 0.011494311 | H59: ='Historical Data'!O1187 -> 0.0030943826 | I59: ='Historical Data'!Q1187 -> 0.0044710742 | J59: ='Historical Data'!S1187 -> 0.015157396 | K59: ='Historical Data'!U1187 -> -0.0048590842 | L59: ='Historical Data'!W1187 -> 0.013027114 | M59: ='Historical Data'!Y1187 -> -0.0053765637
B60: ='Historical Data'!C1186 -> 44539 | C60: ='Historical Data'!E1186 -> 0.0019475405 | D60: ='Historical Data'!G1186 -> -0.0011419251 | E60: ='Historical Data'!I1186 -> -0.00028768386 | F60: ='Historical Data'!K1186 -> -0.0038480918 | G60: ='Historical Data'!M1186 -> 0.0056816808 | H60: ='Historical Data'!O1186 -> -0.040428638 | I60: ='Historical Data'!Q1186 -> -0.023738828 | J60: ='Historical Data'!S1186 -> -0.0094302373 | K60: ='Historical Data'!U1186 -> -0.0078126983 | L60: ='Historical Data'!W1186 -> -0.0074106502 | M60: ='Historical Data'!Y1186 -> -0.0084083778
B61: ='Historical Data'!C1185 -> 44540 | C61: ='Historical Data'!E1185 -> 0.00092488562 | D61: ='Historical Data'!G1185 -> -0.0033767236 | E61: ='Historical Data'!I1185 -> -0.00086321214 | F61: ='Historical Data'!K1185 -> 0.0048286039 | G61: ='Historical Data'!M1185 -> -0.0084744823 | H61: ='Historical Data'!O1185 -> 0.013028864 | I61: ='Historical Data'!Q1185 -> -0.0243162 | J61: ='Historical Data'!S1185 -> 0.00079327494 | K61: ='Historical Data'!U1185 -> -0.0027065235 | L61: ='Historical Data'!W1185 -> 0.0013175704 | M61: ='Historical Data'!Y1185 -> 0.0032015459
B62: ='Historical Data'!C1184 -> 44543 | C62: ='Historical Data'!E1184 -> -0.010781073 | D62: ='Historical Data'!G1184 -> -0.032867345 | E62: ='Historical Data'!I1184 -> -0.0021240357 | F62: ='Historical Data'!K1184 -> -0.0028832036 | G62: ='Historical Data'!M1184 -> 0.011965767 | H62: ='Historical Data'!O1184 -> 0.0030064254 | I62: ='Historical Data'!Q1184 -> -0.0077880687 | J62: ='Historical Data'!S1184 -> -0.0027744399 | K62: ='Historical Data'!U1184 -> 0.0086354949 | L62: ='Historical Data'!W1184 -> 0.0098683596 | M62: ='Historical Data'!Y1184 -> -0.0054338334
B63: ='Historical Data'!C1183 -> 44544 | C63: ='Historical Data'!E1183 -> 0.0079409423 | D63: ='Historical Data'!G1183 -> 0.033156778 | E63: ='Historical Data'!I1183 -> 0.036364967 | F63: ='Historical Data'!K1183 -> -0.003855418 | G63: ='Historical Data'!M1183 -> 0.018581027 | H63: ='Historical Data'!O1183 -> -0.015820159 | I63: ='Historical Data'!Q1183 -> -0.0062795292 | J63: ='Historical Data'!S1183 -> 0.0043720048 | K63: ='Historical Data'!U1183 -> 0.038404976 | L63: ='Historical Data'!W1183 -> -0.0052117079 | M63: ='Historical Data'!Y1183 -> 0.0095396088
B64: ='Historical Data'!C1182 -> 44545 | C64: ='Historical Data'!E1182 -> -0.0075209534 | D64: ='Historical Data'!G1182 -> -0.0068617376 | E64: ='Historical Data'!I1182 -> 0.0020190235 | F64: ='Historical Data'!K1182 -> -0.011127215 | G64: ='Historical Data'!M1182 -> -0.018242071 | H64: ='Historical Data'!O1182 -> -0.014889873 | I64: ='Historical Data'!Q1182 -> -0.022116739 | J64: ='Historical Data'!S1182 -> 0.0027701194 | K64: ='Historical Data'!U1182 -> -0.011307405 | L64: ='Historical Data'!W1182 -> -0.0052390121 | M64: ='Historical Data'!Y1182 -> 0.028433676
B65: ='Historical Data'!C1181 -> 44546 | C65: ='Historical Data'!E1181 -> -0.00045502185 | D65: ='Historical Data'!G1181 -> -0.010753556 | E65: ='Historical Data'!I1181 -> -0.025707834 | F65: ='Historical Data'!K1181 -> -0.0088062769 | G65: ='Historical Data'!M1181 -> 0 | H65: ='Historical Data'!O1181 -> 0.012194965 | I65: ='Historical Data'!Q1181 -> -0.001615679 | J65: ='Historical Data'!S1181 -> 0.0055250762 | K65: ='Historical Data'!U1181 -> -0.0078628217 | L65: ='Historical Data'!W1181 -> -0.026113823 | M65: ='Historical Data'!Y1181 -> -0.068827061
B66: ='Historical Data'!C1180 -> 44547 | C66: ='Historical Data'!E1180 -> -0.01809697 | D66: ='Historical Data'!G1180 -> -0.034051703 | E66: ='Historical Data'!I1180 -> 0.0078445356 | F66: ='Historical Data'!K1180 -> -0.011845991 | G66: ='Historical Data'!M1180 -> -0.048986554 | H66: ='Historical Data'!O1180 -> -0.026641786 | I66: ='Historical Data'!Q1180 -> 0.016181328 | J66: ='Historical Data'!S1180 -> -0.014521239 | K66: ='Historical Data'!U1180 -> 0.0084055485 | L66: ='Historical Data'!W1180 -> -0.027489689 | M66: ='Historical Data'!Y1180 -> -0.023232789
B67: ='Historical Data'!C1179 -> 44550 | C67: ='Historical Data'!E1179 -> -0.030115465 | D67: ='Historical Data'!G1179 -> -0.046139997 | E67: ='Historical Data'!I1179 -> -0.030957014 | F67: ='Historical Data'!K1179 -> -0.029970048 | G67: ='Historical Data'!M1179 -> -0.038484249 | H67: ='Historical Data'!O1179 -> -0.011331957 | I67: ='Historical Data'!Q1179 -> -0.063694362 | J67: ='Historical Data'!S1179 -> -0.030267073 | K67: ='Historical Data'!U1179 -> -0.00047640842 | L67: ='Historical Data'!W1179 -> -0.031047258 | M67: ='Historical Data'!Y1179 -> -0.013040769
B68: ='Historical Data'!C1178 -> 44551 | C68: ='Historical Data'!E1178 -> 0.011565238 | D68: ='Historical Data'!G1178 -> 0.043888642 | E68: ='Historical Data'!I1178 -> 0.0099671591 | F68: ='Historical Data'!K1178 -> 0.018022677 | G68: ='Historical Data'!M1178 -> 0.040640337 | H68: ='Historical Data'!O1178 -> 0.032093181 | I68: ='Historical Data'!Q1178 -> 0.052721272 | J68: ='Historical Data'!S1178 -> 0.0036962951 | K68: ='Historical Data'!U1178 -> -0.015486956 | L68: ='Historical Data'!W1178 -> 0.013390649 | M68: ='Historical Data'!Y1178 -> -0.0011166123
B69: ='Historical Data'!C1177 -> 44552 | C69: ='Historical Data'!E1177 -> 0.011403898 | D69: ='Historical Data'!G1177 -> 0.021332505 | E69: ='Historical Data'!I1177 -> 0.014423563 | F69: ='Historical Data'!K1177 -> 0.0080930624 | G69: ='Historical Data'!M1177 -> 0.010650931 | H69: ='Historical Data'!O1177 -> 0.013668325 | I69: ='Historical Data'!Q1177 -> 0.0016153871 | J69: ='Historical Data'!S1177 -> 0.0028641942 | K69: ='Historical Data'!U1177 -> 0.0097693006 | L69: ='Historical Data'!W1177 -> 0.02878713 | M69: ='Historical Data'!Y1177 -> -0.0030741165
B70: ='Historical Data'!C1176 -> 44553 | C70: ='Historical Data'!E1176 -> 0.012814267 | D70: ='Historical Data'!G1176 -> 0.0083547602 | E70: ='Historical Data'!I1176 -> 0.013505861 | F70: ='Historical Data'!K1176 -> -0.0035122777 | G70: ='Historical Data'!M1176 -> 0.016978833 | H70: ='Historical Data'!O1176 -> 0.0016853443 | I70: ='Historical Data'!Q1176 -> -0.0032258551 | J70: ='Historical Data'!S1176 -> 0.016319934 | K70: ='Historical Data'!U1176 -> 0.033738381 | L70: ='Historical Data'!W1176 -> 0.00022946259 | M70: ='Historical Data'!Y1176 -> 0.013268637
B71: ='Historical Data'!C1175 -> 44554 | C71: ='Historical Data'!E1175 -> -0.012278281 | D71: ='Historical Data'!G1175 -> -0.029657839 | E71: ='Historical Data'!I1175 -> -0.025772668 | F71: ='Historical Data'!K1175 -> -0.0065458743 | G71: ='Historical Data'!M1175 -> -0.018422506 | H71: ='Historical Data'!O1175 -> 0.017499544 | I71: ='Historical Data'!Q1175 -> -0.01779933 | J71: ='Historical Data'!S1175 -> -0.026495507 | K71: ='Historical Data'!U1175 -> -0.014158598 | L71: ='Historical Data'!W1175 -> -0.005732715 | M71: ='Historical Data'!Y1175 -> -0.016230216
B72: ='Historical Data'!C1174 -> 44557 | C72: ='Historical Data'!E1174 -> -0.0012129878 | D72: ='Historical Data'!G1174 -> -0.012355788 | E72: ='Historical Data'!I1174 -> -0.0071459681 | F72: ='Historical Data'!K1174 -> 0.0081094704 | G72: ='Historical Data'!M1174 -> 0.0082112653 | H72: ='Historical Data'!O1174 -> 0.029766883 | I72: ='Historical Data'!Q1174 -> -0.0098846792 | J72: ='Historical Data'!S1174 -> 0.0049485179 | K72: ='Historical Data'!U1174 -> 0.003407964 | L72: ='Historical Data'!W1174 -> 0.0025369673 | M72: ='Historical Data'!Y1174 -> 0.0086239409
B73: ='Historical Data'!C1173 -> 44558 | C73: ='Historical Data'!E1173 -> 0.011309114 | D73: ='Historical Data'!G1173 -> -0.0056397454 | E73: ='Historical Data'!I1173 -> 0.01693933 | F73: ='Historical Data'!K1173 -> 0.015585791 | G73: ='Historical Data'!M1173 -> 0.01337973 | H73: ='Historical Data'!O1173 -> -0.0051388157 | I73: ='Historical Data'!Q1173 -> 0.028286166 | J73: ='Historical Data'!S1173 -> 0.018465122 | K73: ='Historical Data'!U1173 -> -0.0024261049 | L73: ='Historical Data'!W1173 -> 0.019553642 | M73: ='Historical Data'!Y1173 -> 0.012918298
B74: ='Historical Data'!C1172 -> 44559 | C74: ='Historical Data'!E1172 -> -0.0031227264 | D74: ='Historical Data'!G1172 -> -0.0051246056 | E74: ='Historical Data'!I1172 -> -0.004396643 | F74: ='Historical Data'!K1172 -> -0.01138621 | G74: ='Historical Data'!M1172 -> 0.0086109199 | H74: ='Historical Data'!O1172 -> -0.011945292 | I74: ='Historical Data'!Q1172 -> -0.0080905911 | J74: ='Historical Data'!S1172 -> -0.0076550723 | K74: ='Historical Data'!U1172 -> -0.0048637065 | L74: ='Historical Data'!W1172 -> -0.0097021112 | M74: ='Historical Data'!Y1172 -> -0.0074318934
B75: ='Historical Data'!C1171 -> 44560 | C75: ='Historical Data'!E1171 -> -0.01142871 | D75: ='Historical Data'!G1171 -> -0.025697432 | E75: ='Historical Data'!I1171 -> -0.058593311 | F75: ='Historical Data'!K1171 -> -0.0040060053 | G75: ='Historical Data'!M1171 -> -0.020489551 | H75: ='Historical Data'!O1171 -> -0.021891705 | I75: ='Historical Data'!Q1171 -> 0.019575931 | J75: ='Historical Data'!S1171 -> 0.030450776 | K75: ='Historical Data'!U1171 -> 0.0036657457 | L75: ='Historical Data'!W1171 -> -0.0050125194 | M75: ='Historical Data'!Y1171 -> 0.015067416
B76: ='Historical Data'!C1170 -> 44561 | C76: ='Historical Data'!E1170 -> 0.0065175625 | D76: ='Historical Data'!G1170 -> 0.034127332 | E76: ='Historical Data'!I1170 -> 0.014644713 | F76: ='Historical Data'!K1170 -> 0.0025138837 | G76: ='Historical Data'!M1170 -> 0.016850579 | H76: ='Historical Data'!O1170 -> 0.0038416016 | I76: ='Historical Data'!Q1170 -> -0.0095999275 | J76: ='Historical Data'!S1170 -> -0.019700524 | K76: ='Historical Data'!U1170 -> -0.0046264893 | L76: ='Historical Data'!W1170 -> 0.011907506 | M76: ='Historical Data'!Y1170 -> 0.0081959483
B77: ='Historical Data'!C1169 -> 44564 | C77: ='Historical Data'!E1169 -> 0.0096014705 | D77: ='Historical Data'!G1169 -> -0.0056007124 | E77: ='Historical Data'!I1169 -> 0.012516463 | F77: ='Historical Data'!K1169 -> 0.016048129 | G77: ='Historical Data'!M1169 -> 0.010285867 | H77: ='Historical Data'!O1169 -> -0.0049915682 | I77: ='Historical Data'!Q1169 -> 0.0080773004 | J77: ='Historical Data'!S1169 -> 0.012861613 | K77: ='Historical Data'!U1169 -> 0.0029356133 | L77: ='Historical Data'!W1169 -> 0.011088403 | M77: ='Historical Data'!Y1169 -> 0.0028001219
B78: ='Historical Data'!C1168 -> 44565 | C78: ='Historical Data'!E1168 -> 0.022806 | D78: ='Historical Data'!G1168 -> 0.013777353 | E78: ='Historical Data'!I1168 -> 0.014700369 | F78: ='Historical Data'!K1168 -> -0.0074037323 | G78: ='Historical Data'!M1168 -> 0.012443402 | H78: ='Historical Data'!O1168 -> 0.014046756 | I78: ='Historical Data'!Q1168 -> 0.0048077654 | J78: ='Historical Data'!S1168 -> 0.054761906 | K78: ='Historical Data'!U1168 -> 0.02731697 | L78: ='Historical Data'!W1168 -> 0.012981266 | M78: ='Historical Data'!Y1168 -> 0.027923031
B79: ='Historical Data'!C1167 -> 44566 | C79: ='Historical Data'!E1167 -> 0.0063178343 | D79: ='Historical Data'!G1167 -> 0.0034759382 | E79: ='Historical Data'!I1167 -> 0.024109223 | F79: ='Historical Data'!K1167 -> -0.0069617749 | G79: ='Historical Data'!M1167 -> 0.0011173349 | H79: ='Historical Data'!O1167 -> -0.024076656 | I79: ='Historical Data'!Q1167 -> 0.0047846893 | J79: ='Historical Data'!S1167 -> -0.0067720298 | K79: ='Historical Data'!U1167 -> -0.0092592724 | L79: ='Historical Data'!W1167 -> -0.012372958 | M79: ='Historical Data'!Y1167 -> -0.0077112904
B80: ='Historical Data'!C1166 -> 44567 | C80: ='Historical Data'!E1166 -> -0.0062675398 | D80: ='Historical Data'!G1166 -> -0.00056784303 | E80: ='Historical Data'!I1166 -> 0.0072518303 | F80: ='Historical Data'!K1166 -> 0 | G80: ='Historical Data'!M1166 -> 0.011160662 | H80: ='Historical Data'!O1166 -> 0.013011252 | I80: ='Historical Data'!Q1166 -> 0.017460367 | J80: ='Historical Data'!S1166 -> -0.0083332379 | K80: ='Historical Data'!U1166 -> -0.0129404 | L80: ='Historical Data'!W1166 -> 0.022147598 | M80: ='Historical Data'!Y1166 -> 0.0038856082
B81: ='Historical Data'!C1165 -> 44568 | C81: ='Historical Data'!E1165 -> 0.0088615611 | D81: ='Historical Data'!G1165 -> 0.0090622146 | E81: ='Historical Data'!I1165 -> 0.00943391 | F81: ='Historical Data'!K1165 -> 0.0035053382 | G81: ='Historical Data'!M1165 -> -0.00055177732 | H81: ='Historical Data'!O1165 -> 0.025688059 | I81: ='Historical Data'!Q1165 -> -0.026521179 | J81: ='Historical Data'!S1165 -> 0.0034377146 | K81: ='Historical Data'!U1165 -> -0.0036415961 | L81: ='Historical Data'!W1165 -> 0.0059094635 | M81: ='Historical Data'!Y1165 -> 0.011259515
B82: ='Historical Data'!C1164 -> 44571 | C82: ='Historical Data'!E1164 -> 0.0057109048 | D82: ='Historical Data'!G1164 -> 0.024605828 | E82: ='Historical Data'!I1164 -> 0.011102557 | F82: ='Historical Data'!K1164 -> 0.084830278 | G82: ='Historical Data'!M1164 -> -0.0066263781 | H82: ='Historical Data'!O1164 -> 0.032363062 | I82: ='Historical Data'!Q1164 -> 0.011218047 | J82: ='Historical Data'!S1164 -> 0.0038066046 | K82: ='Historical Data'!U1164 -> -0.0058480319 | L82: ='Historical Data'!W1164 -> 0.0084856005 | M82: ='Historical Data'!Y1164 -> 0.00017401638
B83: ='Historical Data'!C1163 -> 44572 | C83: ='Historical Data'!E1163 -> 0.012269977 | D83: ='Historical Data'!G1163 -> 0.02624059 | E83: ='Historical Data'!I1163 -> 0.089686514 | F83: ='Historical Data'!K1163 -> -0.0013799764 | G83: ='Historical Data'!M1163 -> 0.021122945 | H83: ='Historical Data'!O1163 -> -0.010554533 | I83: ='Historical Data'!Q1163 -> -0.015847885 | J83: ='Historical Data'!S1163 -> 0.0034132186 | K83: ='Historical Data'!U1163 -> -0.00073521985 | L83: ='Historical Data'!W1163 -> 0.0058251794 | M83: ='Historical Data'!Y1163 -> 0.010523853
B84: ='Historical Data'!C1162 -> 44573 | C84: ='Historical Data'!E1162 -> 0.021351231 | D84: ='Historical Data'!G1162 -> 0.032557793 | E84: ='Historical Data'!I1162 -> 0.050766989 | F84: ='Historical Data'!K1162 -> 0.099953946 | G84: ='Historical Data'!M1162 -> 0.011975908 | H84: ='Historical Data'!O1162 -> -0.0098710365 | I84: ='Historical Data'!Q1162 -> 0.014492755 | J84: ='Historical Data'!S1162 -> 0.011715743 | K84: ='Historical Data'!U1162 -> 0.0053961717 | L84: ='Historical Data'!W1162 -> 0.019948628 | M84: ='Historical Data'!Y1162 -> -0.013856919
B85: ='Historical Data'!C1161 -> 44574 | C85: ='Historical Data'!E1161 -> 0.012308389 | D85: ='Historical Data'!G1161 -> 0.047426398 | E85: ='Historical Data'!I1161 -> 0.0086492061 | F85: ='Historical Data'!K1161 -> -0.024706795 | G85: ='Historical Data'!M1161 -> -0.0075309386 | H85: ='Historical Data'!O1161 -> -0.0077183906 | I85: ='Historical Data'!Q1161 -> 0.0063493024 | J85: ='Historical Data'!S1161 -> 0.008217924 | K85: ='Historical Data'!U1161 -> 0.014881555 | L85: ='Historical Data'!W1161 -> 0.031755945 | M85: ='Historical Data'!Y1161 -> 0.0096006248
B86: ='Historical Data'!C1160 -> 44575 | C86: ='Historical Data'!E1160 -> 0.0020267915 | D86: ='Historical Data'!G1160 -> 0.00044562283 | E86: ='Historical Data'!I1160 -> 0.021753461 | F86: ='Historical Data'!K1160 -> 0.0060111371 | G86: ='Historical Data'!M1160 -> 0.0032521865 | H86: ='Historical Data'!O1160 -> -0.0030789398 | I86: ='Historical Data'!Q1160 -> -0.015773036 | J86: ='Historical Data'!S1160 -> 0.0029642996 | K86: ='Historical Data'!U1160 -> -0.0012020019 | L86: ='Historical Data'!W1160 -> -0.00366898 | M86: ='Historical Data'!Y1160 -> 0.00077778808
B87: ='Historical Data'!C1159 -> 44578 | C87: ='Historical Data'!E1159 -> 0.012733308 | D87: ='Historical Data'!G1159 -> -0.008858767 | E87: ='Historical Data'!I1159 -> 0.080891723 | F87: ='Historical Data'!K1159 -> -0.0093897233 | G87: ='Historical Data'!M1159 -> 0.0064828682 | H87: ='Historical Data'!O1159 -> 0.016092364 | I87: ='Historical Data'!Q1159 -> 0.0080130147 | J87: ='Historical Data'!S1159 -> 0.0092352349 | K87: ='Historical Data'!U1159 -> -0.0067387701 | L87: ='Historical Data'!W1159 -> 0.014116258 | M87: ='Historical Data'!Y1159 -> 0.0016411778
B88: ='Historical Data'!C1158 -> 44579 | C88: ='Historical Data'!E1158 -> -0.005144037 | D88: ='Historical Data'!G1158 -> 0.012008813 | E88: ='Historical Data'!I1158 -> 0.035307538 | F88: ='Historical Data'!K1158 -> -0.054286875 | G88: ='Historical Data'!M1158 -> -0.017713317 | H88: ='Historical Data'!O1158 -> -0.028315405 | I88: ='Historical Data'!Q1158 -> -0.0047696187 | J88: ='Historical Data'!S1158 -> -0.01171305 | K88: ='Historical Data'!U1158 -> -0.0058152592 | L88: ='Historical Data'!W1158 -> -0.035303562 | M88: ='Historical Data'!Y1158 -> -0.02466394
B89: ='Historical Data'!C1157 -> 44580 | C89: ='Historical Data'!E1157 -> 0.0095390332 | D89: ='Historical Data'!G1157 -> 0.0081411126 | E89: ='Historical Data'!I1157 -> 0.020183136 | F89: ='Historical Data'!K1157 -> 0.037813207 | G89: ='Historical Data'!M1157 -> 0.0016394748 | H89: ='Historical Data'!O1157 -> 0.033256394 | I89: ='Historical Data'!Q1157 -> -0.0063897289 | J89: ='Historical Data'!S1157 -> -0.0014817007 | K89: ='Historical Data'!U1157 -> -0.0024372179 | L89: ='Historical Data'!W1157 -> 0.039314095 | M89: ='Historical Data'!Y1157 -> -0.0031827858
B90: ='Historical Data'!C1156 -> 44581 | C90: ='Historical Data'!E1156 -> -0.00094291323 | D90: ='Historical Data'!G1156 -> -0.0017129573 | E90: ='Historical Data'!I1156 -> 0.0145735 | F90: ='Historical Data'!K1156 -> -0.0013169748 | G90: ='Historical Data'!M1156 -> -0.0076378648 | H90: ='Historical Data'!O1156 -> 0.011312994 | I90: ='Historical Data'!Q1156 -> -0.014469454 | J90: ='Historical Data'!S1156 -> 0.00074211661 | K90: ='Historical Data'!U1156 -> 0.048863937 | L90: ='Historical Data'!W1156 -> 0.00060364337 | M90: ='Historical Data'!Y1156 -> 0.017030184
B91: ='Historical Data'!C1155 -> 44582 | C91: ='Historical Data'!E1155 -> -0.0084783994 | D91: ='Historical Data'!G1155 -> 0.013261453 | E91: ='Historical Data'!I1155 -> -0.016347131 | F91: ='Historical Data'!K1155 -> -0.033406603 | G91: ='Historical Data'!M1155 -> -0.0010994147 | H91: ='Historical Data'!O1155 -> -0.026784298 | I91: ='Historical Data'!Q1155 -> -0.0065253104 | J91: ='Historical Data'!S1155 -> -0.0059303951 | K91: ='Historical Data'!U1155 -> 0.002096224 | L91: ='Historical Data'!W1155 -> -0.026945625 | M91: ='Historical Data'!Y1155 -> -0.039682407
B92: ='Historical Data'!C1154 -> 44585 | C92: ='Historical Data'!E1154 -> -0.025167775 | D92: ='Historical Data'!G1154 -> -0.01495066 | E92: ='Historical Data'!I1154 -> -0.049985821 | F92: ='Historical Data'!K1154 -> -0.065029573 | G92: ='Historical Data'!M1154 -> -0.015634047 | H92: ='Historical Data'!O1154 -> -0.024769185 | I92: ='Historical Data'!Q1154 -> -0.02134657 | J92: ='Historical Data'!S1154 -> -0.011185626 | K92: ='Historical Data'!U1154 -> -0.0051137715 | L92: ='Historical Data'!W1154 -> -0.051250187 | M92: ='Historical Data'!Y1154 -> -0.024793314
B93: ='Historical Data'!C1153 -> 44586 | C93: ='Historical Data'!E1153 -> 0.011920042 | D93: ='Historical Data'!G1153 -> -0.021341948 | E93: ='Historical Data'!I1153 -> 0.049596009 | F93: ='Historical Data'!K1153 -> 0.042315217 | G93: ='Historical Data'!M1153 -> 0.033529363 | H93: ='Historical Data'!O1153 -> 0.010789981 | I93: ='Historical Data'!Q1153 -> 0.0033558316 | J93: ='Historical Data'!S1153 -> 0.020361914 | K93: ='Historical Data'!U1153 -> 0.022663401 | L93: ='Historical Data'!W1153 -> 0.04029621 | M93: ='Historical Data'!Y1153 -> 0.0075432602
B94: ='Historical Data'!C1152 -> 44588 | C94: ='Historical Data'!E1152 -> -0.0064491593 | D94: ='Historical Data'!G1152 -> 0.0084569741 | E94: ='Historical Data'!I1152 -> -0.0097200622 | F94: ='Historical Data'!K1152 -> -0.01399912 | G94: ='Historical Data'!M1152 -> -0.044393901 | H94: ='Historical Data'!O1152 -> -0.018393742 | I94: ='Historical Data'!Q1152 -> 0.0016722661 | J94: ='Historical Data'!S1152 -> -0.0022172571 | K94: ='Historical Data'!U1152 -> -0.018277075 | L94: ='Historical Data'!W1152 -> 0.0094220521 | M94: ='Historical Data'!Y1152 -> -0.0087809351
B95: ='Historical Data'!C1151 -> 44589 | C95: ='Historical Data'!E1151 -> 0.0048865904 | D95: ='Historical Data'!G1151 -> -0.011197929 | E95: ='Historical Data'!I1151 -> 0.014736304 | F95: ='Historical Data'!K1151 -> 0.00094654324 | G95: ='Historical Data'!M1151 -> 0.0077428228 | H95: ='Historical Data'!O1151 -> -0.011042458 | I95: ='Historical Data'!Q1151 -> -0.0066778216 | J95: ='Historical Data'!S1151 -> 0.038148108 | K95: ='Historical Data'!U1151 -> -0.021643142 | L95: ='Historical Data'!W1151 -> 0.012445605 | M95: ='Historical Data'!Y1151 -> 0.010816795
B96: ='Historical Data'!C1150 -> 44592 | C96: ='Historical Data'!E1150 -> 0.012438708 | D96: ='Historical Data'!G1150 -> -0.0080028307 | E96: ='Historical Data'!I1150 -> -0.031237128 | F96: ='Historical Data'!K1150 -> 0.0047281505 | G96: ='Historical Data'!M1150 -> 0.0011817824 | H96: ='Historical Data'!O1150 -> 0.036880606 | I96: ='Historical Data'!Q1150 -> 0.0084032606 | J96: ='Historical Data'!S1150 -> 0.013556822 | K96: ='Historical Data'!U1150 -> 0.024738419 | L96: ='Historical Data'!W1150 -> 0.0081950343 | M96: ='Historical Data'!Y1150 -> 0.0068266181
B97: ='Historical Data'!C1149 -> 44593 | C97: ='Historical Data'!E1149 -> -0.003822454 | D97: ='Historical Data'!G1149 -> 0.0081181185 | E97: ='Historical Data'!I1149 -> 0.013925513 | F97: ='Historical Data'!K1149 -> 0.016470606 | G97: ='Historical Data'!M1149 -> -0.0041321192 | H97: ='Historical Data'!O1149 -> 0.004241991 | I97: ='Historical Data'!Q1149 -> -0.0033332335 | J97: ='Historical Data'!S1149 -> -0.0063357532 | K97: ='Historical Data'!U1149 -> -0.011374352 | L97: ='Historical Data'!W1149 -> 0.015444014 | M97: ='Historical Data'!Y1149 -> -0.003023636
B98: ='Historical Data'!C1148 -> 44594 | C98: ='Historical Data'!E1148 -> 0.0044398104 | D98: ='Historical Data'!G1148 -> 0.014645918 | E98: ='Historical Data'!I1148 -> 0.0064601097 | F98: ='Historical Data'!K1148 -> 0.0032407266 | G98: ='Historical Data'!M1148 -> 0.0088915 | H98: ='Historical Data'!O1148 -> -0.014297182 | I98: ='Historical Data'!Q1148 -> 0.0016722661 | J98: ='Historical Data'!S1148 -> 0 | K98: ='Historical Data'!U1148 -> 0.0049308237 | L98: ='Historical Data'!W1148 -> 0.0030019089 | M98: ='Historical Data'!Y1148 -> 0.0041357299
B99: ='Historical Data'!C1147 -> 44595 | C99: ='Historical Data'!E1147 -> -0.010800454 | D99: ='Historical Data'!G1147 -> -0.0048611353 | E99: ='Historical Data'!I1147 -> -0.0019568961 | F99: ='Historical Data'!K1147 -> -0.0069219944 | G99: ='Historical Data'!M1147 -> -0.0082253929 | H99: ='Historical Data'!O1147 -> -0.0057689384 | I99: ='Historical Data'!Q1147 -> 0 | J99: ='Historical Data'!S1147 -> -0.0036457467 | K99: ='Historical Data'!U1147 -> -0.012616598 | L99: ='Historical Data'!W1147 -> 0.0089783322 | M99: ='Historical Data'!Y1147 -> -0.011806742
B100: ='Historical Data'!C1146 -> 44596 | C100: ='Historical Data'!E1146 -> -0.0012050653 | D100: ='Historical Data'!G1146 -> 0.013408446 | E100: ='Historical Data'!I1146 -> 0.01976415 | F100: ='Historical Data'!K1146 -> 0.0088289323 | G100: ='Historical Data'!M1146 -> -0.01658766 | H100: ='Historical Data'!O1146 -> -0.012765244 | I100: ='Historical Data'!Q1146 -> -0.0016694743 | J100: ='Historical Data'!S1146 -> -0.017928828 | K100: ='Historical Data'!U1146 -> -0.0075724301 | L100: ='Historical Data'!W1146 -> 0.0059323968 | M100: ='Historical Data'!Y1146 -> 0.075020725
B101: ='Historical Data'!C1145 -> 44599 | C101: ='Historical Data'!E1145 -> 0.005095317 | D101: ='Historical Data'!G1145 -> -0.0022625427 | E101: ='Historical Data'!I1145 -> 0.038095752 | F101: ='Historical Data'!K1145 -> 0.029018936 | G101: ='Historical Data'!M1145 -> 0.001807068 | H101: ='Historical Data'!O1145 -> 0.021326524 | I101: ='Historical Data'!Q1145 -> 0.0016722661 | J101: ='Historical Data'!S1145 -> 0.0070789975 | K101: ='Historical Data'!U1145 -> 0.018836476 | L101: ='Historical Data'!W1145 -> -0.010025543 | M101: ='Historical Data'!Y1145 -> -0.096924116
B102: ='Historical Data'!C1144 -> 44600 | C102: ='Historical Data'!E1144 -> -0.013055388 | D102: ='Historical Data'!G1144 -> -0.029677077 | E102: ='Historical Data'!I1144 -> -0.047736657 | F102: ='Historical Data'!K1144 -> -0.031781602 | G102: ='Historical Data'!M1144 -> 0.001202613 | H102: ='Historical Data'!O1144 -> 0.01364686 | I102: ='Historical Data'!Q1144 -> -0.013355643 | J102: ='Historical Data'!S1144 -> -0.0011098898 | K102: ='Historical Data'!U1144 -> -0.016850039 | L102: ='Historical Data'!W1144 -> -0.0673153 | M102: ='Historical Data'!Y1144 -> -0.02671248
...

Sheet Historical Data
C3: Date | D3: Nifty Power (Energy) | E3: Return | F3: Adani Energy Solutions | G3: Return | H3: Adani Green | I3: Return | J3: Adani Power | K3: Return | L3: CESC | M3: Return | N3: JSW Energy | O3: Return | P3: NHPC | Q3: Return | R3: NTPC | S3: Return | T3: Power Grid | U3: Return | V3: Tata Power | W3: Return | X3: Torrent Power | Y3: Return
C4: 46281 | D4: 37183.4 | E4: =D4/D5-1 -> 0.00095429223 | F4: 1349.2 | G4: =F4/F5-1 -> 0.0012615593 | H4: 1270.2 | I4: =H4/H5-1 -> 0.012111515 | J4: 202.34 | K4: =J4/J5-1 -> 0.0016831502 | L4: 141.67 | M4: =L4/L5-1 -> -0.00021170628 | N4: 504.70001 | O4: =N4/N5-1 -> -0.00059403523 | P4: 75.410004 | Q4: =P4/P5-1 -> -0.0082850769 | R4: 327 | S4: =R4/R5-1 -> -0.0075872534 | T4: 262.79999 | U4: =T4/T5-1 -> 0 | V4: 360.39999 | W4: =V4/V5-1 -> -0.0071625512 | X4: 1295.3 | Y4: =X4/X5-1 -> -0.0043046933
C5: 46280 | D5: 37147.95 | E5: =D5/D6-1 -> -0.020752494 | F5: 1347.5 | G5: =F5/F6-1 -> -0.018572469 | H5: 1255 | I5: =H5/H6-1 -> -0.020526066 | J5: 202 | K5: =J5/J6-1 -> -0.037957809 | L5: 141.7 | M5: =L5/L6-1 -> -0.025245912 | N5: 505 | O5: =N5/N6-1 -> -0.040744632 | P5: 76.040001 | Q5: =P5/P6-1 -> -0.0044513793 | R5: 329.5 | S5: =R5/R6-1 -> -0.011697642 | T5: 262.79999 | U5: =T5/T6-1 -> -0.023411439 | V5: 363 | W5: =V5/V6-1 -> -0.0045248702 | X5: 1300.9 | Y5: =X5/X6-1 -> 0.0025431943
C6: 46279 | D6: 37935.2 | E6: =D6/D7-1 -> -0.0075398839 | F6: 1373 | G6: =F6/F7-1 -> 0 | H6: 1281.3 | I6: =H6/H7-1 -> 0 | J6: 209.97 | K6: =J6/J7-1 -> 0 | L6: 145.37 | M6: =L6/L7-1 -> 0 | N6: 526.45001 | O6: =N6/N7-1 -> 0 | P6: 76.379997 | Q6: =P6/P7-1 -> 0 | R6: 333.39999 | S6: =R6/R7-1 -> 0 | T6: 269.10001 | U6: =T6/T7-1 -> 0 | V6: 364.64999 | W6: =V6/V7-1 -> 0 | X6: 1297.6 | Y6: =X6/X7-1 -> 0
C7: 46276 | D7: 38223.4 | E7: =D7/D8-1 -> -0.0028760632 | F7: 1373 | G7: =F7/F8-1 -> -0.013578579 | H7: 1281.3 | I7: =H7/H8-1 -> -0.013701737 | J7: 209.97 | K7: =J7/J8-1 -> -0.016533952 | L7: 145.37 | M7: =L7/L8-1 -> -0.014974974 | N7: 526.45001 | O7: =N7/N8-1 -> -0.0075407671 | P7: 76.379997 | Q7: =P7/P8-1 -> 0.00039291133 | R7: 333.39999 | S7: =R7/R8-1 -> -0.0047761376 | T7: 269.10001 | U7: =T7/T8-1 -> -0.0097515875 | V7: 364.64999 | W7: =V7/V8-1 -> -0.0064032864 | X7: 1297.6 | Y7: =X7/X8-1 -> 0.0010027977
C8: 46275 | D8: 38333.65 | E8: =D8/D9-1 -> 0.0063042251 | F8: 1391.9 | G8: =F8/F9-1 -> -0.022061423 | H8: 1299.1 | I8: =H8/H9-1 -> -0.012091273 | J8: 213.5 | K8: =J8/J9-1 -> -0.0065146298 | L8: 147.58 | M8: =L8/L9-1 -> -0.01396403 | N8: 530.45001 | O8: =N8/N9-1 -> -0.0081338364 | P8: 76.349998 | Q8: =P8/P9-1 -> -0.0044334849 | R8: 335 | S8: =R8/R9-1 -> 0.0014947683 | T8: 271.75 | U8: =T8/T9-1 -> 0.022192942 | V8: 367 | W8: =V8/V9-1 -> -0.0081081081 | X8: 1296.3 | Y8: =X8/X9-1 -> -0.007199129
C9: 46274 | D9: 38093.5 | E9: =D9/D10-1 -> 0.0031640611 | F9: 1423.3 | G9: =F9/F10-1 -> 0.011081976 | H9: 1315 | I9: =H9/H10-1 -> 0.017801858 | J9: 214.89999 | K9: =J9/J10-1 -> 0.03119002 | L9: 149.67 | M9: =L9/L10-1 -> 0.024785998 | N9: 534.79999 | O9: =N9/N10-1 -> 0.015764459 | P9: 76.690002 | Q9: =P9/P10-1 -> 0.010408444 | R9: 334.5 | S9: =R9/R10-1 -> 0.011185043 | T9: 265.85001 | U9: =T9/T10-1 -> 0.00037631648 | V9: 370 | W9: =V9/V10-1 -> 0.012173471 | X9: 1305.7 | Y9: =X9/X10-1 -> 0.027948356
C10: 46273 | D10: 37973.35 | E10: =D10/D11-1 -> -0.0043903117 | F10: 1407.7 | G10: =F10/F11-1 -> -0.0013479175 | H10: 1292 | I10: =H10/H11-1 -> -0.0071467367 | J10: 208.39999 | K10: =J10/J11-1 -> 0.0057914911 | L10: 146.05 | M10: =L10/L11-1 -> -0.0030716515 | N10: 526.5 | O10: =N10/N11-1 -> -0.024729047 | P10: 75.900002 | Q10: =P10/P11-1 -> -0.0045901439 | R10: 330.79999 | S10: =R10/R11-1 -> -0.0051128187 | T10: 265.75 | U10: =T10/T11-1 -> -0.00093984962 | V10: 365.54999 | W10: =V10/V11-1 -> -0.0066576419 | X10: 1270.2 | Y10: =X10/X11-1 -> -0.02224619
C11: 46269 | D11: 38140.8 | E11: =D11/D12-1 -> 0.0029556858 | F11: 1409.6 | G11: =F11/F12-1 -> 0.017247619 | H11: 1301.3 | I11: =H11/H12-1 -> 0.013947346 | J11: 207.2 | K11: =J11/J12-1 -> -0.0052330711 | L11: 146.5 | M11: =L11/L12-1 -> -0.0098675767 | N11: 539.84998 | O11: =N11/N12-1 -> 0.00064870359 | P11: 76.25 | Q11: =P11/P12-1 -> -0.0026160491 | R11: 332.5 | S11: =R11/R12-1 -> 0.0048353162 | T11: 266 | U11: =T11/T12-1 -> 0.0015060011 | V11: 368 | W11: =V11/V12-1 -> 0.0062892746 | X11: 1299.1 | Y11: =X11/X12-1 -> 0.0076009667
C12: 46268 | D12: 38028.4 | E12: =D12/D13-1 -> 0.0058800035 | F12: 1385.7 | G12: =F12/F13-1 -> -0.0078046861 | H12: 1283.4 | I12: =H12/H13-1 -> -0.0097222034 | J12: 208.28999 | K12: =J12/J13-1 -> 0.0028406179 | L12: 147.96001 | M12: =L12/L13-1 -> 0.010379707 | N12: 539.5 | O12: =N12/N13-1 -> -0.00055573879 | P12: 76.449997 | Q12: =P12/P13-1 -> 0.010574956 | R12: 330.89999 | S12: =R12/R13-1 -> 0.0027272542 | T12: 265.60001 | U12: =T12/T13-1 -> -0.0044976827 | V12: 365.70001 | W12: =V12/V13-1 -> 0.0046703632 | X12: 1289.3 | Y12: =X12/X13-1 -> 0.032348486
C13: 46267 | D13: 37806.1 | E13: =D13/D14-1 -> -0.0037721431 | F13: 1396.6 | G13: =F13/F14-1 -> 0.010564382 | H13: 1296 | I13: =H13/H14-1 -> 0.024505929 | J13: 207.7 | K13: =J13/J14-1 -> 0.016343689 | L13: 146.44 | M13: =L13/L14-1 -> 0.0088874171 | N13: 539.79999 | O13: =N13/N14-1 -> 0.042084919 | P13: 75.650002 | Q13: =P13/P14-1 -> -0.0085190236 | R13: 330 | S13: =R13/R14-1 -> 0.018518519 | T13: 266.79999 | U13: =T13/T14-1 -> 0.0085050089 | V13: 364 | W13: =V13/V14-1 -> 0.038368315 | X13: 1248.9 | Y13: =X13/X14-1 -> 0.024276203
C14: 46266 | D14: 37949.25 | E14: =D14/D15-1 -> -0.0014314415 | F14: 1382 | G14: =F14/F15-1 -> -0.024975324 | H14: 1265 | I14: =H14/H15-1 -> 0.041237941 | J14: 204.36 | K14: =J14/J15-1 -> 0.032121215 | L14: 145.14999 | M14: =L14/L15-1 -> -0.006910302 | N14: 518 | O14: =N14/N15-1 -> -0.0046118837 | P14: 76.300003 | Q14: =P14/P15-1 -> -0.0054744286 | R14: 324 | S14: =R14/R15-1 -> 0.00030545744 | T14: 264.54999 | U14: =T14/T15-1 -> 0.0037943466 | V14: 350.54999 | W14: =V14/V15-1 -> 0.010230512 | X14: 1219.3 | Y14: =X14/X15-1 -> 0.003456566
C15: 46265 | D15: 38003.65 | E15: =D15/D16-1 -> -0.002632273 | F15: 1417.4 | G15: =F15/F16-1 -> -0.10370558 | H15: 1214.9 | I15: =H15/H16-1 -> -0.073302804 | J15: 198 | K15: =J15/J16-1 -> -0.068804988 | L15: 146.16 | M15: =L15/L16-1 -> -0.01316587 | N15: 520.40002 | O15: =N15/N16-1 -> -0.027834791 | P15: 76.720001 | Q15: =P15/P16-1 -> 0.0253943 | R15: 323.90106 | S15: =R15/R16-1 -> -0.008029069 | T15: 263.54999 | U15: =T15/T16-1 -> -0.0093967304 | V15: 347 | W15: =V15/V16-1 -> -0.0137843 | X15: 1215.1 | Y15: =X15/X16-1 -> -0.0021351529
... C1240: 44460 | D1240: 21324.5 | E1240: =D1240/D1241-1 -> 0.0052348864 | F1240: 1642.9 | G1240: =F1240/F1241-1 -> -0.049989853 | H1240: 1120.7 | I1240: =H1240/H1241-1 -> -0.0092384503 | J1240: 18.91 | K1240: =J1240/J1241-1 -> -0.0094290363 | L1240: 69.779083 | M1240: =L1240/L1241-1 -> -0.04410956 | N1240: 329.44601 | O1240: =N1240/N1241-1 -> 0.021765439 | P1240: 23.18635 | Q1240: =P1240/P1241-1 -> -0.017888954 | R1240: 105.18897 | S1240: =R1240/R1241-1 -> 0.011409872 | T1240: 103.76832 | U1240: =T1240/T1241-1 -> -0.0062145925 | V1240: 131.32083 | W1240: =V1240/V1241-1 -> 0.011541308 | X1240: 440.72467 | Y1240: =X1240/X1241-1 -> 0.013415896
C1241: 44459 | D1241: 21213.45 | F1241: 1729.35 | H1241: 1131.15 | J1241: 19.09 | L1241: 72.999039 | N1241: 322.42822 | P1241: 23.608685 | R1241: 104.00232 | T1241: 104.41723 | V1241: 129.82251 | X1241: 434.89023
C1244: Average Return | E1244: =AVERAGE(E4:E1240) -> 0.00053116448 | G1244: =AVERAGE(G4:G1240) -> 0.00030568112 | I1244: =AVERAGE(I4:I1240) -> 0.00062814938 | K1244: =AVERAGE(K4:K1240) -> 0.0023804048 | M1244: =AVERAGE(M4:M1240) -> 0.0007441272 | O1244: =AVERAGE(O4:O1240) -> 0.00071189722 | Q1244: =AVERAGE(Q4:Q1240) -> 0.0011706673 | S1244: =AVERAGE(S4:S1240) -> 0.0010512769 | U1244: =AVERAGE(U4:U1240) -> 0.00087270724 | W1244: =AVERAGE(W4:W1240) -> 0.0010324131 | Y1244: =AVERAGE(Y4:Y1240) -> 0.0011367548
C1245: Annualized Return | E1245: =((1+E1244)^250)-1 -> 0.14197117 | G1245: =((1+G1244)^250)-1 -> 0.07940353 | I1245: =((1+I1244)^250)-1 -> 0.16998163 | K1245: =((1+K1244)^250)-1 -> 0.81193263 | M1245: =((1+M1244)^250)-1 -> 0.20437724 | O1245: =((1+O1244)^250)-1 -> 0.19471897 | Q1245: =((1+Q1244)^250)-1 -> 0.33976689 | S1245: =((1+S1244)^250)-1 -> 0.30041204 | U1245: =((1+U1244)^250)-1 -> 0.24368863 | W1245: =((1+W1244)^250)-1 -> 0.29430017 | Y1245: =((1+Y1244)^250)-1 -> 0.3284692
C1247: ST. dev | E1247: =_xlfn.STDEV.S(E4:E1240) -> 0.012390123 | G1247: =_xlfn.STDEV.S(G4:G1240) -> 0.031737343 | I1247: =_xlfn.STDEV.S(I4:I1240) -> 0.032691112 | K1247: =_xlfn.STDEV.S(K4:K1240) -> 0.030984018 | M1247: =_xlfn.STDEV.S(M4:M1240) -> 0.020419601 | O1247: =_xlfn.STDEV.S(O4:O1240) -> 0.026527102 | Q1247: =_xlfn.STDEV.S(Q4:Q1240) -> 0.021519688 | S1247: =_xlfn.STDEV.S(S4:S1240) -> 0.015768016 | U1247: =_xlfn.STDEV.S(U4:U1240) -> 0.015882582 | W1247: =_xlfn.STDEV.S(W4:W1240) -> 0.020397126 | Y1247: =_xlfn.STDEV.S(Y4:Y1240) -> 0.022669778
C1248: Annualized ST dev | E1248: =SQRT(E1247) -> 0.11131093 | G1248: =SQRT(G1247) -> 0.17814978 | I1248: =SQRT(I1247) -> 0.18080684 | K1248: =SQRT(K1247) -> 0.17602278 | M1248: =SQRT(M1247) -> 0.14289717 | O1248: =SQRT(O1247) -> 0.16287143 | Q1248: =SQRT(Q1247) -> 0.1466959 | S1248: =SQRT(S1247) -> 0.12557076 | U1248: =SQRT(U1247) -> 0.12602612 | W1248: =SQRT(W1247) -> 0.14281851 | Y1248: =SQRT(Y1247) -> 0.15056486
